Workbook
Name RosterNames: Roster!$A$2:$A$40
Name DealCodes: Deals!$A$2:$A$355
Name LifecycleList: Settings!$D$8:$D$16
Name PhaseList: Settings!$E$8:$E$11
Name TxnTypeList: Settings!$F$8:$F$12
Name EntityClassList: Settings!$G$8:$G$11
Name ScopeList: Settings!$H$8:$H$15
Name TimelineList: Settings!$I$8:$I$9
Name ActiveList: Settings!$J$8:$J$9
Name YesNoList: Settings!$K$8:$K$9
Name LevelList: Settings!$L$8:$L$14
Name ArchetypeList: Templates!$A$3:$A$10
Name MapNetSuite: Actuals!$N$5:$N$44
Name MapTracker: Actuals!$O$5:$O$44
Name TddTypeList: Settings!$M$8:$M$12
Name TddScopeList: Settings!$N$8:$N$10
Name OtherTddList: Settings!$O$8:$O$11
Name CorpModelList: Settings!$P$8:$P$9
Name YTickList: Settings!$Q$8:$Q$8

Sheet Guide
B1: US M&A Tax - Scheduling & Capacity Tracker
B2: Built from Scheduling_US_MA_July_9.xlsx + the June 4 scheduling brief. This workbook is the bridge tracker: one source of truth for deals, staffing and weekly capacity.
B4: TABS
B5: Capacity - the dashboard: planned hours per person per week. Red = over capacity, amber = above 85%.
B6: Check-in - the weekly 15-20 min meeting agenda, generated automatically: who's over/under-allocated in the next 4 weeks, and which Active/Proposal deals need attention (unstaffed, missing a staffed level, still at the default probability, no dates, or stale). Nothing to edit here - update Settings!B19 to today first.
B7: Scenario - what-if analysis. Fill the violet SCENARIO columns on Deals (probability / start / end) - e.g. bump three proposals to 100% - and this tab shows who would blow up, Live vs Scenario, without touching the real plan. Blank overrides = identical to Live.
B8: Deals - one row per engagement: lifecycle, probability, dates. The yellow WORKSTREAM SCOPING columns are Justine's taxonomy - tick what's in scope. The yellow FEE $ columns (one per group: TDD, Modeling, Structuring, Legal docs, Other) drive the hours - enter a fee and it flows to hours-by-level through Templates. Violet columns are scenario overrides. (Old attribute columns K-P are retired and hidden.)
B9: Assignments - one row per person on a deal. 'Active?' controls whether it counts. Hours come from the deal's fees (split by level), or its archetype, or the level default - unless you set an Override (Override always wins). Columns N onward ('Eff. start/end', 'Seg1/Seg2 ...', 'Fee hrs/wk pp') are calculation helpers - leave them alone.
B10: Roster - the team, weekly capacity, live utilization.
B11: Templates - the fee->hours allocation parameters: rate card ($/hr by level), fee split-% matrix by workstream group, and default durations. Fill the yellow cells with the team's real numbers; Step 9 wires per-deal fees into hours. (The old effort archetypes above are legacy, kept for reference.)
B12: Actuals - paste the NetSuite time export (blue columns); it matches each row to a deal and person and computes variance vs the plan. Fill the name-mapping table (right) when NetSuite names differ from roster names. Sample rows are included and flagged - delete them first.
B13: Variance - estimate vs actual: per deal, and a calibration summary by level and by archetype (actual/planned ratio - >1 means we estimate low, <1 means high). Reads from Actuals.
... B42: Source: Scheduling_US_MA_July_9.xlsx (July 9) and Justine Morin's scheduling brief (June 4, 2026). Migration by scripts/build_workbook.py - regenerating overwrites manual edits, so edit here, not there.

Sheet Capacity
A1: Capacity - planned hours per person per week
A2: ="Probability weighting: "&Settings!$B$4&" | Fees set on a deal drive its hours, spread evenly across its dates; a deal with an Archetype + dates is front/tail phased instead; a deal with no dates counts flat in every week."
A4: Person | B4: Cap hrs/wk | C4: =Settings!$B$3 | D4: =C4+7 | E4: =D4+7 | F4: =E4+7 | G4: =F4+7 | H4: =G4+7 | I4: =H4+7 | J4: =I4+7 | K4: =J4+7 | ... AB4: =AA4+7
A5: =IF(Roster!$A2="","",Roster!$A2) | B5: =IF($A5="","",IFERROR(INDEX(Roster!$D$2:$D$40,MATCH($A5,Roster!$A$2:$A$40,0)),"")) | C5: =IF($A5="","",SUMIFS(Assignments!$X$2:$X$769,Assignments!$A$2:$A$769,$A5,Assignments!$G$2:$G$769,"Active",Assignments!$V$2:$V$769,"<="&C$4,Assignments!$W$2:$W$769,">="&C$4)+SUMIFS(Assignments!$AA$2:$AA$769,Assignments!$A$2:$A$769,$A5,Assignments!$G$2:$G$769,"Active",Assignments!$Y$2:$Y$769,"<="&C$4,Assignments!$Z$2:$Z$769,">="&C$4)) | D5: =IF($A5="","",SUMIFS(Assignments!$X$2:$X$769,Assignments!$A$2:$A$769,$A5,Assignments!$G$2:$G$769,"Active",Assignments!$V$2:$V$769,"<="&D$4,Assignments!$W$2:$W$769,">="&D$4)+SUMIFS(Assignments!$AA$2:$AA$769,Assignments!$A$2:$A$769,$A5,Assignments!$G$2:$G$769,"Active",Assignments!$Y$2:$Y$769,"<="&D$4,Assignments!$Z$2:$Z$769,">="&D$4)) | E5: =IF($A5="","",SUMIFS(Assignments!$X$2:$X$769,Assignments!$A$2:$A$769,$A5,Assignments!$G$2:$G$769,"Active",Assignments!$V$2:$V$769,"<="&E$4,Assignments!$W$2:$W$769,">="&E$4)+SUMIFS(Assignments!$AA$2:$AA$769,Assignments!$A$2:$A$769,$A5,Assignments!$G$2:$G$769,"Active",Assignments!$Y$2:$Y$769,"<="&E$4,Assignments!$Z$2:$Z$769,">="&E$4)) | F5: =IF($A5="","",SUMIFS(Assignments!$X$2:$X$769,Assignments!$A$2:$A$769,$A5,Assignments!$G$2:$G$769,"Active",Assignments!$V$2:$V$769,"<="&F$4,Assignments!$W$2:$W$769,">="&F$4)+SUMIFS(Assignments!$AA$2:$AA$769,Assignments!$A$2:$A$769,$A5,Assignments!$G$2:$G$769,"Active",Assignments!$Y$2:$Y$769,"<="&F$4,Assignments!$Z$2:$Z$769,">="&F$4)) | G5: =IF($A5="","",SUMIFS(Assignments!$X$2:$X$769,Assignments!$A$2:$A$769,$A5,Assignments!$G$2:$G$769,"Active",Assignments!$V$2:$V$769,"<="&G$4,Assignments!$W$2:$W$769,">="&G$4)+SUMIFS(Assignments!$AA$2:$AA$769,Assignments!$A$2:$A$769,$A5,Assignments!$G$2:$G$769,"Active",Assignments!$Y$2:$Y$769,"<="&G$4,Assignments!$Z$2:$Z$769,">="&G$4)) | H5: =IF($A5="","",SUMIFS(Assignments!$X$2:$X$769,Assignments!$A$2:$A$769,$A5,Assignments!$G$2:$G$769,"Active",Assignments!$V$2:$V$769,"<="&H$4,Assignments!$W$2:$W$769,">="&H$4)+SUMIFS(Assignments!$AA$2:$AA$769,Assignments!$A$2:$A$769,$A5,Assignments!$G$2:$G$769,"Active",Assignments!$Y$2:$Y$769,"<="&H$4,Assignments!$Z$2:$Z$769,">="&H$4)) | I5: =IF($A5="","",SUMIFS(Assignments!$X$2:$X$769,Assignments!$A$2:$A$769,$A5,Assignments!$G$2:$G$769,"Active",Assignments!$V$2:$V$769,"<="&I$4,Assignments!$W$2:$W$769,">="&I$4)+SUMIFS(Assignments!$AA$2:$AA$769,Assignments!$A$2:$A$769,$A5,Assignments!$G$2:$G$769,"Active",Assignments!$Y$2:$Y$769,"<="&I$4,Assignments!$Z$2:$Z$769,">="&I$4)) | J5: =IF($A5="","",SUMIFS(Assignments!$X$2:$X$769,Assignments!$A$2:$A$769,$A5,Assignments!$G$2:$G$769,"Active",Assignments!$V$2:$V$769,"<="&J$4,Assignments!$W$2:$W$769,">="&J$4)+SUMIFS(Assignments!$AA$2:$AA$769,Assignments!$A$2:$A$769,$A5,Assignments!$G$2:$G$769,"Active",Assignments!$Y$2:$Y$769,"<="&J$4,Assignments!$Z$2:$Z$769,">="&J$4)) | ... AB5: =IF($A5="","",SUMIFS(Assignments!$X$2:$X$769,Assignments!$A$2:$A$769,$A5,Assignments!$G$2:$G$769,"Active",Assignments!$V$2:$V$769,"<="&AB$4,Assignments!$W$2:$W$769,">="&AB$4)+SUMIFS(Assignments!$AA$2:$AA$769,Assignments!$A$2:$A$769,$A5,Assignments!$G$2:$G$769,"Active",Assignments!$Y$2:$Y$769,"<="&AB$4,Assignments!$Z$2:$Z$769,">="&AB$4))
A6: =IF(Roster!$A3="","",Roster!$A3) | B6: =IF($A6="","",IFERROR(INDEX(Roster!$D$2:$D$40,MATCH($A6,Roster!$A$2:$A$40,0)),"")) | C6: =IF($A6="","",SUMIFS(Assignments!$X$2:$X$769,Assignments!$A$2:$A$769,$A6,Assignments!$G$2:$G$769,"Active",Assignments!$V$2:$V$769,"<="&C$4,Assignments!$W$2:$W$769,">="&C$4)+SUMIFS(Assignments!$AA$2:$AA$769,Assignments!$A$2:$A$769,$A6,Assignments!$G$2:$G$769,"Active",Assignments!$Y$2:$Y$769,"<="&C$4,Assignments!$Z$2:$Z$769,">="&C$4)) | D6: =IF($A6="","",SUMIFS(Assignments!$X$2:$X$769,Assignments!$A$2:$A$769,$A6,Assignments!$G$2:$G$769,"Active",Assignments!$V$2:$V$769,"<="&D$4,Assignments!$W$2:$W$769,">="&D$4)+SUMIFS(Assignments!$AA$2:$AA$769,Assignments!$A$2:$A$769,$A6,Assignments!$G$2:$G$769,"Active",Assignments!$Y$2:$Y$769,"<="&D$4,Assignments!$Z$2:$Z$769,">="&D$4)) | E6: =IF($A6="","",SUMIFS(Assignments!$X$2:$X$769,Assignments!$A$2:$A$769,$A6,Assignments!$G$2:$G$769,"Active",Assignments!$V$2:$V$769,"<="&E$4,Assignments!$W$2:$W$769,">="&E$4)+SUMIFS(Assignments!$AA$2:$AA$769,Assignments!$A$2:$A$769,$A6,Assignments!$G$2:$G$769,"Active",Assignments!$Y$2:$Y$769,"<="&E$4,Assignments!$Z$2:$Z$769,">="&E$4)) | F6: =IF($A6="","",SUMIFS(Assignments!$X$2:$X$769,Assignments!$A$2:$A$769,$A6,Assignments!$G$2:$G$769,"Active",Assignments!$V$2:$V$769,"<="&F$4,Assignments!$W$2:$W$769,">="&F$4)+SUMIFS(Assignments!$AA$2:$AA$769,Assignments!$A$2:$A$769,$A6,Assignments!$G$2:$G$769,"Active",Assignments!$Y$2:$Y$769,"<="&F$4,Assignments!$Z$2:$Z$769,">="&F$4)) | G6: =IF($A6="","",SUMIFS(Assignments!$X$2:$X$769,Assignments!$A$2:$A$769,$A6,Assignments!$G$2:$G$769,"Active",Assignments!$V$2:$V$769,"<="&G$4,Assignments!$W$2:$W$769,">="&G$4)+SUMIFS(Assignments!$AA$2:$AA$769,Assignments!$A$2:$A$769,$A6,Assignments!$G$2:$G$769,"Active",Assignments!$Y$2:$Y$769,"<="&G$4,Assignments!$Z$2:$Z$769,">="&G$4)) | H6: =IF($A6="","",SUMIFS(Assignments!$X$2:$X$769,Assignments!$A$2:$A$769,$A6,Assignments!$G$2:$G$769,"Active",Assignments!$V$2:$V$769,"<="&H$4,Assignments!$W$2:$W$769,">="&H$4)+SUMIFS(Assignments!$AA$2:$AA$769,Assignments!$A$2:$A$769,$A6,Assignments!$G$2:$G$769,"Active",Assignments!$Y$2:$Y$769,"<="&H$4,Assignments!$Z$2:$Z$769,">="&H$4)) | I6: =IF($A6="","",SUMIFS(Assignments!$X$2:$X$769,Assignments!$A$2:$A$769,$A6,Assignments!$G$2:$G$769,"Active",Assignments!$V$2:$V$769,"<="&I$4,Assignments!$W$2:$W$769,">="&I$4)+SUMIFS(Assignments!$AA$2:$AA$769,Assignments!$A$2:$A$769,$A6,Assignments!$G$2:$G$769,"Active",Assignments!$Y$2:$Y$769,"<="&I$4,Assignments!$Z$2:$Z$769,">="&I$4)) | J6: =IF($A6="","",SUMIFS(Assignments!$X$2:$X$769,Assignments!$A$2:$A$769,$A6,Assignments!$G$2:$G$769,"Active",Assignments!$V$2:$V$769,"<="&J$4,Assignments!$W$2:$W$769,">="&J$4)+SUMIFS(Assignments!$AA$2:$AA$769,Assignments!$A$2:$A$769,$A6,Assignments!$G$2:$G$769,"Active",Assignments!$Y$2:$Y$769,"<="&J$4,Assignments!$Z$2:$Z$769,">="&J$4)) | ... AB6: =IF($A6="","",SUMIFS(Assignments!$X$2:$X$769,Assignments!$A$2:$A$769,$A6,Assignments!$G$2:$G$769,"Active",Assignments!$V$2:$V$769,"<="&AB$4,Assignments!$W$2:$W$769,">="&AB$4)+SUMIFS(Assignments!$AA$2:$AA$769,Assignments!$A$2:$A$769,$A6,Assignments!$G$2:$G$769,"Active",Assignments!$Y$2:$Y$769,"<="&AB$4,Assignments!$Z$2:$Z$769,">="&AB$4))
A7: =IF(Roster!$A4="","",Roster!$A4) | B7: =IF($A7="","",IFERROR(INDEX(Roster!$D$2:$D$40,MATCH($A7,Roster!$A$2:$A$40,0)),"")) | C7: =IF($A7="","",SUMIFS(Assignments!$X$2:$X$769,Assignments!$A$2:$A$769,$A7,Assignments!$G$2:$G$769,"Active",Assignments!$V$2:$V$769,"<="&C$4,Assignments!$W$2:$W$769,">="&C$4)+SUMIFS(Assignments!$AA$2:$AA$769,Assignments!$A$2:$A$769,$A7,Assignments!$G$2:$G$769,"Active",Assignments!$Y$2:$Y$769,"<="&C$4,Assignments!$Z$2:$Z$769,">="&C$4)) | D7: =IF($A7="","",SUMIFS(Assignments!$X$2:$X$769,Assignments!$A$2:$A$769,$A7,Assignments!$G$2:$G$769,"Active",Assignments!$V$2:$V$769,"<="&D$4,Assignments!$W$2:$W$769,">="&D$4)+SUMIFS(Assignments!$AA$2:$AA$769,Assignments!$A$2:$A$769,$A7,Assignments!$G$2:$G$769,"Active",Assignments!$Y$2:$Y$769,"<="&D$4,Assignments!$Z$2:$Z$769,">="&D$4)) | E7: =IF($A7="","",SUMIFS(Assignments!$X$2:$X$769,Assignments!$A$2:$A$769,$A7,Assignments!$G$2:$G$769,"Active",Assignments!$V$2:$V$769,"<="&E$4,Assignments!$W$2:$W$769,">="&E$4)+SUMIFS(Assignments!$AA$2:$AA$769,Assignments!$A$2:$A$769,$A7,Assignments!$G$2:$G$769,"Active",Assignments!$Y$2:$Y$769,"<="&E$4,Assignments!$Z$2:$Z$769,">="&E$4)) | F7: =IF($A7="","",SUMIFS(Assignments!$X$2:$X$769,Assignments!$A$2:$A$769,$A7,Assignments!$G$2:$G$769,"Active",Assignments!$V$2:$V$769,"<="&F$4,Assignments!$W$2:$W$769,">="&F$4)+SUMIFS(Assignments!$AA$2:$AA$769,Assignments!$A$2:$A$769,$A7,Assignments!$G$2:$G$769,"Active",Assignments!$Y$2:$Y$769,"<="&F$4,Assignments!$Z$2:$Z$769,">="&F$4)) | G7: =IF($A7="","",SUMIFS(Assignments!$X$2:$X$769,Assignments!$A$2:$A$769,$A7,Assignments!$G$2:$G$769,"Active",Assignments!$V$2:$V$769,"<="&G$4,Assignments!$W$2:$W$769,">="&G$4)+SUMIFS(Assignments!$AA$2:$AA$769,Assignments!$A$2:$A$769,$A7,Assignments!$G$2:$G$769,"Active",Assignments!$Y$2:$Y$769,"<="&G$4,Assignments!$Z$2:$Z$769,">="&G$4)) | H7: =IF($A7="","",SUMIFS(Assignments!$X$2:$X$769,Assignments!$A$2:$A$769,$A7,Assignments!$G$2:$G$769,"Active",Assignments!$V$2:$V$769,"<="&H$4,Assignments!$W$2:$W$769,">="&H$4)+SUMIFS(Assignments!$AA$2:$AA$769,Assignments!$A$2:$A$769,$A7,Assignments!$G$2:$G$769,"Active",Assignments!$Y$2:$Y$769,"<="&H$4,Assignments!$Z$2:$Z$769,">="&H$4)) | I7: =IF($A7="","",SUMIFS(Assignments!$X$2:$X$769,Assignments!$A$2:$A$769,$A7,Assignments!$G$2:$G$769,"Active",Assignments!$V$2:$V$769,"<="&I$4,Assignments!$W$2:$W$769,">="&I$4)+SUMIFS(Assignments!$AA$2:$AA$769,Assignments!$A$2:$A$769,$A7,Assignments!$G$2:$G$769,"Active",Assignments!$Y$2:$Y$769,"<="&I$4,Assignments!$Z$2:$Z$769,">="&I$4)) | J7: =IF($A7="","",SUMIFS(Assignments!$X$2:$X$769,Assignments!$A$2:$A$769,$A7,Assignments!$G$2:$G$769,"Active",Assignments!$V$2:$V$769,"<="&J$4,Assignments!$W$2:$W$769,">="&J$4)+SUMIFS(Assignments!$AA$2:$AA$769,Assignments!$A$2:$A$769,$A7,Assignments!$G$2:$G$769,"Active",Assignments!$Y$2:$Y$769,"<="&J$4,Assignments!$Z$2:$Z$769,">="&J$4)) | ... AB7: =IF($A7="","",SUMIFS(Assignments!$X$2:$X$769,Assignments!$A$2:$A$769,$A7,Assignments!$G$2:$G$769,"Active",Assignments!$V$2:$V$769,"<="&AB$4,Assignments!$W$2:$W$769,">="&AB$4)+SUMIFS(Assignments!$AA$2:$AA$769,Assignments!$A$2:$A$769,$A7,Assignments!$G$2:$G$769,"Active",Assignments!$Y$2:$Y$769,"<="&AB$4,Assignments!$Z$2:$Z$769,">="&AB$4))
A8: =IF(Roster!$A5="","",Roster!$A5) | B8: =IF($A8="","",IFERROR(INDEX(Roster!$D$2:$D$40,MATCH($A8,Roster!$A$2:$A$40,0)),"")) | C8: =IF($A8="","",SUMIFS(Assignments!$X$2:$X$769,Assignments!$A$2:$A$769,$A8,Assignments!$G$2:$G$769,"Active",Assignments!$V$2:$V$769,"<="&C$4,Assignments!$W$2:$W$769,">="&C$4)+SUMIFS(Assignments!$AA$2:$AA$769,Assignments!$A$2:$A$769,$A8,Assignments!$G$2:$G$769,"Active",Assignments!$Y$2:$Y$769,"<="&C$4,Assignments!$Z$2:$Z$769,">="&C$4)) | D8: =IF($A8="","",SUMIFS(Assignments!$X$2:$X$769,Assignments!$A$2:$A$769,$A8,Assignments!$G$2:$G$769,"Active",Assignments!$V$2:$V$769,"<="&D$4,Assignments!$W$2:$W$769,">="&D$4)+SUMIFS(Assignments!$AA$2:$AA$769,Assignments!$A$2:$A$769,$A8,Assignments!$G$2:$G$769,"Active",Assignments!$Y$2:$Y$769,"<="&D$4,Assignments!$Z$2:$Z$769,">="&D$4)) | E8: =IF($A8="","",SUMIFS(Assignments!$X$2:$X$769,Assignments!$A$2:$A$769,$A8,Assignments!$G$2:$G$769,"Active",Assignments!$V$2:$V$769,"<="&E$4,Assignments!$W$2:$W$769,">="&E$4)+SUMIFS(Assignments!$AA$2:$AA$769,Assignments!$A$2:$A$769,$A8,Assignments!$G$2:$G$769,"Active",Assignments!$Y$2:$Y$769,"<="&E$4,Assignments!$Z$2:$Z$769,">="&E$4)) | F8: =IF($A8="","",SUMIFS(Assignments!$X$2:$X$769,Assignments!$A$2:$A$769,$A8,Assignments!$G$2:$G$769,"Active",Assignments!$V$2:$V$769,"<="&F$4,Assignments!$W$2:$W$769,">="&F$4)+SUMIFS(Assignments!$AA$2:$AA$769,Assignments!$A$2:$A$769,$A8,Assignments!$G$2:$G$769,"Active",Assignments!$Y$2:$Y$769,"<="&F$4,Assignments!$Z$2:$Z$769,">="&F$4)) | G8: =IF($A8="","",SUMIFS(Assignments!$X$2:$X$769,Assignments!$A$2:$A$769,$A8,Assignments!$G$2:$G$769,"Active",Assignments!$V$2:$V$769,"<="&G$4,Assignments!$W$2:$W$769,">="&G$4)+SUMIFS(Assignments!$AA$2:$AA$769,Assignments!$A$2:$A$769,$A8,Assignments!$G$2:$G$769,"Active",Assignments!$Y$2:$Y$769,"<="&G$4,Assignments!$Z$2:$Z$769,">="&G$4)) | H8: =IF($A8="","",SUMIFS(Assignments!$X$2:$X$769,Assignments!$A$2:$A$769,$A8,Assignments!$G$2:$G$769,"Active",Assignments!$V$2:$V$769,"<="&H$4,Assignments!$W$2:$W$769,">="&H$4)+SUMIFS(Assignments!$AA$2:$AA$769,Assignments!$A$2:$A$769,$A8,Assignments!$G$2:$G$769,"Active",Assignments!$Y$2:$Y$769,"<="&H$4,Assignments!$Z$2:$Z$769,">="&H$4)) | I8: =IF($A8="","",SUMIFS(Assignments!$X$2:$X$769,Assignments!$A$2:$A$769,$A8,Assignments!$G$2:$G$769,"Active",Assignments!$V$2:$V$769,"<="&I$4,Assignments!$W$2:$W$769,">="&I$4)+SUMIFS(Assignments!$AA$2:$AA$769,Assignments!$A$2:$A$769,$A8,Assignments!$G$2:$G$769,"Active",Assignments!$Y$2:$Y$769,"<="&I$4,Assignments!$Z$2:$Z$769,">="&I$4)) | J8: =IF($A8="","",SUMIFS(Assignments!$X$2:$X$769,Assignments!$A$2:$A$769,$A8,Assignments!$G$2:$G$769,"Active",Assignments!$V$2:$V$769,"<="&J$4,Assignments!$W$2:$W$769,">="&J$4)+SUMIFS(Assignments!$AA$2:$AA$769,Assignments!$A$2:$A$769,$A8,Assignments!$G$2:$G$769,"Active",Assignments!$Y$2:$Y$769,"<="&J$4,Assignments!$Z$2:$Z$769,">="&J$4)) | ... AB8: =IF($A8="","",SUMIFS(Assignments!$X$2:$X$769,Assignments!$A$2:$A$769,$A8,Assignments!$G$2:$G$769,"Active",Assignments!$V$2:$V$769,"<="&AB$4,Assignments!$W$2:$W$769,">="&AB$4)+SUMIFS(Assignments!$AA$2:$AA$769,Assignments!$A$2:$A$769,$A8,Assignments!$G$2:$G$769,"Active",Assignments!$Y$2:$Y$769,"<="&AB$4,Assignments!$Z$2:$Z$769,">="&AB$4))
A9: =IF(Roster!$A6="","",Roster!$A6) | B9: =IF($A9="","",IFERROR(INDEX(Roster!$D$2:$D$40,MATCH($A9,Roster!$A$2:$A$40,0)),"")) | C9: =IF($A9="","",SUMIFS(Assignments!$X$2:$X$769,Assignments!$A$2:$A$769,$A9,Assignments!$G$2:$G$769,"Active",Assignments!$V$2:$V$769,"<="&C$4,Assignments!$W$2:$W$769,">="&C$4)+SUMIFS(Assignments!$AA$2:$AA$769,Assignments!$A$2:$A$769,$A9,Assignments!$G$2:$G$769,"Active",Assignments!$Y$2:$Y$769,"<="&C$4,Assignments!$Z$2:$Z$769,">="&C$4)) | D9: =IF($A9="","",SUMIFS(Assignments!$X$2:$X$769,Assignments!$A$2:$A$769,$A9,Assignments!$G$2:$G$769,"Active",Assignments!$V$2:$V$769,"<="&D$4,Assignments!$W$2:$W$769,">="&D$4)+SUMIFS(Assignments!$AA$2:$AA$769,Assignments!$A$2:$A$769,$A9,Assignments!$G$2:$G$769,"Active",Assignments!$Y$2:$Y$769,"<="&D$4,Assignments!$Z$2:$Z$769,">="&D$4)) | E9: =IF($A9="","",SUMIFS(Assignments!$X$2:$X$769,Assignments!$A$2:$A$769,$A9,Assignments!$G$2:$G$769,"Active",Assignments!$V$2:$V$769,"<="&E$4,Assignments!$W$2:$W$769,">="&E$4)+SUMIFS(Assignments!$AA$2:$AA$769,Assignments!$A$2:$A$769,$A9,Assignments!$G$2:$G$769,"Active",Assignments!$Y$2:$Y$769,"<="&E$4,Assignments!$Z$2:$Z$769,">="&E$4)) | F9: =IF($A9="","",SUMIFS(Assignments!$X$2:$X$769,Assignments!$A$2:$A$769,$A9,Assignments!$G$2:$G$769,"Active",Assignments!$V$2:$V$769,"<="&F$4,Assignments!$W$2:$W$769,">="&F$4)+SUMIFS(Assignments!$AA$2:$AA$769,Assignments!$A$2:$A$769,$A9,Assignments!$G$2:$G$769,"Active",Assignments!$Y$2:$Y$769,"<="&F$4,Assignments!$Z$2:$Z$769,">="&F$4)) | G9: =IF($A9="","",SUMIFS(Assignments!$X$2:$X$769,Assignments!$A$2:$A$769,$A9,Assignments!$G$2:$G$769,"Active",Assignments!$V$2:$V$769,"<="&G$4,Assignments!$W$2:$W$769,">="&G$4)+SUMIFS(Assignments!$AA$2:$AA$769,Assignments!$A$2:$A$769,$A9,Assignments!$G$2:$G$769,"Active",Assignments!$Y$2:$Y$769,"<="&G$4,Assignments!$Z$2:$Z$769,">="&G$4)) | H9: =IF($A9="","",SUMIFS(Assignments!$X$2:$X$769,Assignments!$A$2:$A$769,$A9,Assignments!$G$2:$G$769,"Active",Assignments!$V$2:$V$769,"<="&H$4,Assignments!$W$2:$W$769,">="&H$4)+SUMIFS(Assignments!$AA$2:$AA$769,Assignments!$A$2:$A$769,$A9,Assignments!$G$2:$G$769,"Active",Assignments!$Y$2:$Y$769,"<="&H$4,Assignments!$Z$2:$Z$769,">="&H$4)) | I9: =IF($A9="","",SUMIFS(Assignments!$X$2:$X$769,Assignments!$A$2:$A$769,$A9,Assignments!$G$2:$G$769,"Active",Assignments!$V$2:$V$769,"<="&I$4,Assignments!$W$2:$W$769,">="&I$4)+SUMIFS(Assignments!$AA$2:$AA$769,Assignments!$A$2:$A$769,$A9,Assignments!$G$2:$G$769,"Active",Assignments!$Y$2:$Y$769,"<="&I$4,Assignments!$Z$2:$Z$769,">="&I$4)) | J9: =IF($A9="","",SUMIFS(Assignments!$X$2:$X$769,Assignments!$A$2:$A$769,$A9,Assignments!$G$2:$G$769,"Active",Assignments!$V$2:$V$769,"<="&J$4,Assignments!$W$2:$W$769,">="&J$4)+SUMIFS(Assignments!$AA$2:$AA$769,Assignments!$A$2:$A$769,$A9,Assignments!$G$2:$G$769,"Active",Assignments!$Y$2:$Y$769,"<="&J$4,Assignments!$Z$2:$Z$769,">="&J$4)) | ... AB9: =IF($A9="","",SUMIFS(Assignments!$X$2:$X$769,Assignments!$A$2:$A$769,$A9,Assignments!$G$2:$G$769,"Active",Assignments!$V$2:$V$769,"<="&AB$4,Assignments!$W$2:$W$769,">="&AB$4)+SUMIFS(Assignments!$AA$2:$AA$769,Assignments!$A$2:$A$769,$A9,Assignments!$G$2:$G$769,"Active",Assignments!$Y$2:$Y$769,"<="&AB$4,Assignments!$Z$2:$Z$769,">="&AB$4))
A10: =IF(Roster!$A7="","",Roster!$A7) | B10: =IF($A10="","",IFERROR(INDEX(Roster!$D$2:$D$40,MATCH($A10,Roster!$A$2:$A$40,0)),"")) | C10: =IF($A10="","",SUMIFS(Assignments!$X$2:$X$769,Assignments!$A$2:$A$769,$A10,Assignments!$G$2:$G$769,"Active",Assignments!$V$2:$V$769,"<="&C$4,Assignments!$W$2:$W$769,">="&C$4)+SUMIFS(Assignments!$AA$2:$AA$769,Assignments!$A$2:$A$769,$A10,Assignments!$G$2:$G$769,"Active",Assignments!$Y$2:$Y$769,"<="&C$4,Assignments!$Z$2:$Z$769,">="&C$4)) | D10: =IF($A10="","",SUMIFS(Assignments!$X$2:$X$769,Assignments!$A$2:$A$769,$A10,Assignments!$G$2:$G$769,"Active",Assignments!$V$2:$V$769,"<="&D$4,Assignments!$W$2:$W$769,">="&D$4)+SUMIFS(Assignments!$AA$2:$AA$769,Assignments!$A$2:$A$769,$A10,Assignments!$G$2:$G$769,"Active",Assignments!$Y$2:$Y$769,"<="&D$4,Assignments!$Z$2:$Z$769,">="&D$4)) | E10: =IF($A10="","",SUMIFS(Assignments!$X$2:$X$769,Assignments!$A$2:$A$769,$A10,Assignments!$G$2:$G$769,"Active",Assignments!$V$2:$V$769,"<="&E$4,Assignments!$W$2:$W$769,">="&E$4)+SUMIFS(Assignments!$AA$2:$AA$769,Assignments!$A$2:$A$769,$A10,Assignments!$G$2:$G$769,"Active",Assignments!$Y$2:$Y$769,"<="&E$4,Assignments!$Z$2:$Z$769,">="&E$4)) | F10: =IF($A10="","",SUMIFS(Assignments!$X$2:$X$769,Assignments!$A$2:$A$769,$A10,Assignments!$G$2:$G$769,"Active",Assignments!$V$2:$V$769,"<="&F$4,Assignments!$W$2:$W$769,">="&F$4)+SUMIFS(Assignments!$AA$2:$AA$769,Assignments!$A$2:$A$769,$A10,Assignments!$G$2:$G$769,"Active",Assignments!$Y$2:$Y$769,"<="&F$4,Assignments!$Z$2:$Z$769,">="&F$4)) | G10: =IF($A10="","",SUMIFS(Assignments!$X$2:$X$769,Assignments!$A$2:$A$769,$A10,Assignments!$G$2:$G$769,"Active",Assignments!$V$2:$V$769,"<="&G$4,Assignments!$W$2:$W$769,">="&G$4)+SUMIFS(Assignments!$AA$2:$AA$769,Assignments!$A$2:$A$769,$A10,Assignments!$G$2:$G$769,"Active",Assignments!$Y$2:$Y$769,"<="&G$4,Assignments!$Z$2:$Z$769,">="&G$4)) | H10: =IF($A10="","",SUMIFS(Assignments!$X$2:$X$769,Assignments!$A$2:$A$769,$A10,Assignments!$G$2:$G$769,"Active",Assignments!$V$2:$V$769,"<="&H$4,Assignments!$W$2:$W$769,">="&H$4)+SUMIFS(Assignments!$AA$2:$AA$769,Assignments!$A$2:$A$769,$A10,Assignments!$G$2:$G$769,"Active",Assignments!$Y$2:$Y$769,"<="&H$4,Assignments!$Z$2:$Z$769,">="&H$4)) | I10: =IF($A10="","",SUMIFS(Assignments!$X$2:$X$769,Assignments!$A$2:$A$769,$A10,Assignments!$G$2:$G$769,"Active",Assignments!$V$2:$V$769,"<="&I$4,Assignments!$W$2:$W$769,">="&I$4)+SUMIFS(Assignments!$AA$2:$AA$769,Assignments!$A$2:$A$769,$A10,Assignments!$G$2:$G$769,"Active",Assignments!$Y$2:$Y$769,"<="&I$4,Assignments!$Z$2:$Z$769,">="&I$4)) | J10: =IF($A10="","",SUMIFS(Assignments!$X$2:$X$769,Assignments!$A$2:$A$769,$A10,Assignments!$G$2:$G$769,"Active",Assignments!$V$2:$V$769,"<="&J$4,Assignments!$W$2:$W$769,">="&J$4)+SUMIFS(Assignments!$AA$2:$AA$769,Assignments!$A$2:$A$769,$A10,Assignments!$G$2:$G$769,"Active",Assignments!$Y$2:$Y$769,"<="&J$4,Assignments!$Z$2:$Z$769,">="&J$4)) | ... AB10: =IF($A10="","",SUMIFS(Assignments!$X$2:$X$769,Assignments!$A$2:$A$769,$A10,Assignments!$G$2:$G$769,"Active",Assignments!$V$2:$V$769,"<="&AB$4,Assignments!$W$2:$W$769,">="&AB$4)+SUMIFS(Assignments!$AA$2:$AA$769,Assignments!$A$2:$A$769,$A10,Assignments!$G$2:$G$769,"Active",Assignments!$Y$2:$Y$769,"<="&AB$4,Assignments!$Z$2:$Z$769,">="&AB$4))
A11: =IF(Roster!$A8="","",Roster!$A8) | B11: =IF($A11="","",IFERROR(INDEX(Roster!$D$2:$D$40,MATCH($A11,Roster!$A$2:$A$40,0)),"")) | C11: =IF($A11="","",SUMIFS(Assignments!$X$2:$X$769,Assignments!$A$2:$A$769,$A11,Assignments!$G$2:$G$769,"Active",Assignments!$V$2:$V$769,"<="&C$4,Assignments!$W$2:$W$769,">="&C$4)+SUMIFS(Assignments!$AA$2:$AA$769,Assignments!$A$2:$A$769,$A11,Assignments!$G$2:$G$769,"Active",Assignments!$Y$2:$Y$769,"<="&C$4,Assignments!$Z$2:$Z$769,">="&C$4)) | D11: =IF($A11="","",SUMIFS(Assignments!$X$2:$X$769,Assignments!$A$2:$A$769,$A11,Assignments!$G$2:$G$769,"Active",Assignments!$V$2:$V$769,"<="&D$4,Assignments!$W$2:$W$769,">="&D$4)+SUMIFS(Assignments!$AA$2:$AA$769,Assignments!$A$2:$A$769,$A11,Assignments!$G$2:$G$769,"Active",Assignments!$Y$2:$Y$769,"<="&D$4,Assignments!$Z$2:$Z$769,">="&D$4)) | E11: =IF($A11="","",SUMIFS(Assignments!$X$2:$X$769,Assignments!$A$2:$A$769,$A11,Assignments!$G$2:$G$769,"Active",Assignments!$V$2:$V$769,"<="&E$4,Assignments!$W$2:$W$769,">="&E$4)+SUMIFS(Assignments!$AA$2:$AA$769,Assignments!$A$2:$A$769,$A11,Assignments!$G$2:$G$769,"Active",Assignments!$Y$2:$Y$769,"<="&E$4,Assignments!$Z$2:$Z$769,">="&E$4)) | F11: =IF($A11="","",SUMIFS(Assignments!$X$2:$X$769,Assignments!$A$2:$A$769,$A11,Assignments!$G$2:$G$769,"Active",Assignments!$V$2:$V$769,"<="&F$4,Assignments!$W$2:$W$769,">="&F$4)+SUMIFS(Assignments!$AA$2:$AA$769,Assignments!$A$2:$A$769,$A11,Assignments!$G$2:$G$769,"Active",Assignments!$Y$2:$Y$769,"<="&F$4,Assignments!$Z$2:$Z$769,">="&F$4)) | G11: =IF($A11="","",SUMIFS(Assignments!$X$2:$X$769,Assignments!$A$2:$A$769,$A11,Assignments!$G$2:$G$769,"Active",Assignments!$V$2:$V$769,"<="&G$4,Assignments!$W$2:$W$769,">="&G$4)+SUMIFS(Assignments!$AA$2:$AA$769,Assignments!$A$2:$A$769,$A11,Assignments!$G$2:$G$769,"Active",Assignments!$Y$2:$Y$769,"<="&G$4,Assignments!$Z$2:$Z$769,">="&G$4)) | H11: =IF($A11="","",SUMIFS(Assignments!$X$2:$X$769,Assignments!$A$2:$A$769,$A11,Assignments!$G$2:$G$769,"Active",Assignments!$V$2:$V$769,"<="&H$4,Assignments!$W$2:$W$769,">="&H$4)+SUMIFS(Assignments!$AA$2:$AA$769,Assignments!$A$2:$A$769,$A11,Assignments!$G$2:$G$769,"Active",Assignments!$Y$2:$Y$769,"<="&H$4,Assignments!$Z$2:$Z$769,">="&H$4)) | I11: =IF($A11="","",SUMIFS(Assignments!$X$2:$X$769,Assignments!$A$2:$A$769,$A11,Assignments!$G$2:$G$769,"Active",Assignments!$V$2:$V$769,"<="&I$4,Assignments!$W$2:$W$769,">="&I$4)+SUMIFS(Assignments!$AA$2:$AA$769,Assignments!$A$2:$A$769,$A11,Assignments!$G$2:$G$769,"Active",Assignments!$Y$2:$Y$769,"<="&I$4,Assignments!$Z$2:$Z$769,">="&I$4)) | J11: =IF($A11="","",SUMIFS(Assignments!$X$2:$X$769,Assignments!$A$2:$A$769,$A11,Assignments!$G$2:$G$769,"Active",Assignments!$V$2:$V$769,"<="&J$4,Assignments!$W$2:$W$769,">="&J$4)+SUMIFS(Assignments!$AA$2:$AA$769,Assignments!$A$2:$A$769,$A11,Assignments!$G$2:$G$769,"Active",Assignments!$Y$2:$Y$769,"<="&J$4,Assignments!$Z$2:$Z$769,">="&J$4)) | ... AB11: =IF($A11="","",SUMIFS(Assignments!$X$2:$X$769,Assignments!$A$2:$A$769,$A11,Assignments!$G$2:$G$769,"Active",Assignments!$V$2:$V$769,"<="&AB$4,Assignments!$W$2:$W$769,">="&AB$4)+SUMIFS(Assignments!$AA$2:$AA$769,Assignments!$A$2:$A$769,$A11,Assignments!$G$2:$G$769,"Active",Assignments!$Y$2:$Y$769,"<="&AB$4,Assignments!$Z$2:$Z$769,">="&AB$4))
A12: =IF(Roster!$A9="","",Roster!$A9) | B12: =IF($A12="","",IFERROR(INDEX(Roster!$D$2:$D$40,MATCH($A12,Roster!$A$2:$A$40,0)),"")) | C12: =IF($A12="","",SUMIFS(Assignments!$X$2:$X$769,Assignments!$A$2:$A$769,$A12,Assignments!$G$2:$G$769,"Active",Assignments!$V$2:$V$769,"<="&C$4,Assignments!$W$2:$W$769,">="&C$4)+SUMIFS(Assignments!$AA$2:$AA$769,Assignments!$A$2:$A$769,$A12,Assignments!$G$2:$G$769,"Active",Assignments!$Y$2:$Y$769,"<="&C$4,Assignments!$Z$2:$Z$769,">="&C$4)) | D12: =IF($A12="","",SUMIFS(Assignments!$X$2:$X$769,Assignments!$A$2:$A$769,$A12,Assignments!$G$2:$G$769,"Active",Assignments!$V$2:$V$769,"<="&D$4,Assignments!$W$2:$W$769,">="&D$4)+SUMIFS(Assignments!$AA$2:$AA$769,Assignments!$A$2:$A$769,$A12,Assignments!$G$2:$G$769,"Active",Assignments!$Y$2:$Y$769,"<="&D$4,Assignments!$Z$2:$Z$769,">="&D$4)) | E12: =IF($A12="","",SUMIFS(Assignments!$X$2:$X$769,Assignments!$A$2:$A$769,$A12,Assignments!$G$2:$G$769,"Active",Assignments!$V$2:$V$769,"<="&E$4,Assignments!$W$2:$W$769,">="&E$4)+SUMIFS(Assignments!$AA$2:$AA$769,Assignments!$A$2:$A$769,$A12,Assignments!$G$2:$G$769,"Active",Assignments!$Y$2:$Y$769,"<="&E$4,Assignments!$Z$2:$Z$769,">="&E$4)) | F12: =IF($A12="","",SUMIFS(Assignments!$X$2:$X$769,Assignments!$A$2:$A$769,$A12,Assignments!$G$2:$G$769,"Active",Assignments!$V$2:$V$769,"<="&F$4,Assignments!$W$2:$W$769,">="&F$4)+SUMIFS(Assignments!$AA$2:$AA$769,Assignments!$A$2:$A$769,$A12,Assignments!$G$2:$G$769,"Active",Assignments!$Y$2:$Y$769,"<="&F$4,Assignments!$Z$2:$Z$769,">="&F$4)) | G12: =IF($A12="","",SUMIFS(Assignments!$X$2:$X$769,Assignments!$A$2:$A$769,$A12,Assignments!$G$2:$G$769,"Active",Assignments!$V$2:$V$769,"<="&G$4,Assignments!$W$2:$W$769,">="&G$4)+SUMIFS(Assignments!$AA$2:$AA$769,Assignments!$A$2:$A$769,$A12,Assignments!$G$2:$G$769,"Active",Assignments!$Y$2:$Y$769,"<="&G$4,Assignments!$Z$2:$Z$769,">="&G$4)) | H12: =IF($A12="","",SUMIFS(Assignments!$X$2:$X$769,Assignments!$A$2:$A$769,$A12,Assignments!$G$2:$G$769,"Active",Assignments!$V$2:$V$769,"<="&H$4,Assignments!$W$2:$W$769,">="&H$4)+SUMIFS(Assignments!$AA$2:$AA$769,Assignments!$A$2:$A$769,$A12,Assignments!$G$2:$G$769,"Active",Assignments!$Y$2:$Y$769,"<="&H$4,Assignments!$Z$2:$Z$769,">="&H$4)) | I12: =IF($A12="","",SUMIFS(Assignments!$X$2:$X$769,Assignments!$A$2:$A$769,$A12,Assignments!$G$2:$G$769,"Active",Assignments!$V$2:$V$769,"<="&I$4,Assignments!$W$2:$W$769,">="&I$4)+SUMIFS(Assignments!$AA$2:$AA$769,Assignments!$A$2:$A$769,$A12,Assignments!$G$2:$G$769,"Active",Assignments!$Y$2:$Y$769,"<="&I$4,Assignments!$Z$2:$Z$769,">="&I$4)) | J12: =IF($A12="","",SUMIFS(Assignments!$X$2:$X$769,Assignments!$A$2:$A$769,$A12,Assignments!$G$2:$G$769,"Active",Assignments!$V$2:$V$769,"<="&J$4,Assignments!$W$2:$W$769,">="&J$4)+SUMIFS(Assignments!$AA$2:$AA$769,Assignments!$A$2:$A$769,$A12,Assignments!$G$2:$G$769,"Active",Assignments!$Y$2:$Y$769,"<="&J$4,Assignments!$Z$2:$Z$769,">="&J$4)) | ... AB12: =IF($A12="","",SUMIFS(Assignments!$X$2:$X$769,Assignments!$A$2:$A$769,$A12,Assignments!$G$2:$G$769,"Active",Assignments!$V$2:$V$769,"<="&AB$4,Assignments!$W$2:$W$769,">="&AB$4)+SUMIFS(Assignments!$AA$2:$AA$769,Assignments!$A$2:$A$769,$A12,Assignments!$G$2:$G$769,"Active",Assignments!$Y$2:$Y$769,"<="&AB$4,Assignments!$Z$2:$Z$769,">="&AB$4))
A13: =IF(Roster!$A10="","",Roster!$A10) | B13: =IF($A13="","",IFERROR(INDEX(Roster!$D$2:$D$40,MATCH($A13,Roster!$A$2:$A$40,0)),"")) | C13: =IF($A13="","",SUMIFS(Assignments!$X$2:$X$769,Assignments!$A$2:$A$769,$A13,Assignments!$G$2:$G$769,"Active",Assignments!$V$2:$V$769,"<="&C$4,Assignments!$W$2:$W$769,">="&C$4)+SUMIFS(Assignments!$AA$2:$AA$769,Assignments!$A$2:$A$769,$A13,Assignments!$G$2:$G$769,"Active",Assignments!$Y$2:$Y$769,"<="&C$4,Assignments!$Z$2:$Z$769,">="&C$4)) | D13: =IF($A13="","",SUMIFS(Assignments!$X$2:$X$769,Assignments!$A$2:$A$769,$A13,Assignments!$G$2:$G$769,"Active",Assignments!$V$2:$V$769,"<="&D$4,Assignments!$W$2:$W$769,">="&D$4)+SUMIFS(Assignments!$AA$2:$AA$769,Assignments!$A$2:$A$769,$A13,Assignments!$G$2:$G$769,"Active",Assignments!$Y$2:$Y$769,"<="&D$4,Assignments!$Z$2:$Z$769,">="&D$4)) | E13: =IF($A13="","",SUMIFS(Assignments!$X$2:$X$769,Assignments!$A$2:$A$769,$A13,Assignments!$G$2:$G$769,"Active",Assignments!$V$2:$V$769,"<="&E$4,Assignments!$W$2:$W$769,">="&E$4)+SUMIFS(Assignments!$AA$2:$AA$769,Assignments!$A$2:$A$769,$A13,Assignments!$G$2:$G$769,"Active",Assignments!$Y$2:$Y$769,"<="&E$4,Assignments!$Z$2:$Z$769,">="&E$4)) | F13: =IF($A13="","",SUMIFS(Assignments!$X$2:$X$769,Assignments!$A$2:$A$769,$A13,Assignments!$G$2:$G$769,"Active",Assignments!$V$2:$V$769,"<="&F$4,Assignments!$W$2:$W$769,">="&F$4)+SUMIFS(Assignments!$AA$2:$AA$769,Assignments!$A$2:$A$769,$A13,Assignments!$G$2:$G$769,"Active",Assignments!$Y$2:$Y$769,"<="&F$4,Assignments!$Z$2:$Z$769,">="&F$4)) | G13: =IF($A13="","",SUMIFS(Assignments!$X$2:$X$769,Assignments!$A$2:$A$769,$A13,Assignments!$G$2:$G$769,"Active",Assignments!$V$2:$V$769,"<="&G$4,Assignments!$W$2:$W$769,">="&G$4)+SUMIFS(Assignments!$AA$2:$AA$769,Assignments!$A$2:$A$769,$A13,Assignments!$G$2:$G$769,"Active",Assignments!$Y$2:$Y$769,"<="&G$4,Assignments!$Z$2:$Z$769,">="&G$4)) | H13: =IF($A13="","",SUMIFS(Assignments!$X$2:$X$769,Assignments!$A$2:$A$769,$A13,Assignments!$G$2:$G$769,"Active",Assignments!$V$2:$V$769,"<="&H$4,Assignments!$W$2:$W$769,">="&H$4)+SUMIFS(Assignments!$AA$2:$AA$769,Assignments!$A$2:$A$769,$A13,Assignments!$G$2:$G$769,"Active",Assignments!$Y$2:$Y$769,"<="&H$4,Assignments!$Z$2:$Z$769,">="&H$4)) | I13: =IF($A13="","",SUMIFS(Assignments!$X$2:$X$769,Assignments!$A$2:$A$769,$A13,Assignments!$G$2:$G$769,"Active",Assignments!$V$2:$V$769,"<="&I$4,Assignments!$W$2:$W$769,">="&I$4)+SUMIFS(Assignments!$AA$2:$AA$769,Assignments!$A$2:$A$769,$A13,Assignments!$G$2:$G$769,"Active",Assignments!$Y$2:$Y$769,"<="&I$4,Assignments!$Z$2:$Z$769,">="&I$4)) | J13: =IF($A13="","",SUMIFS(Assignments!$X$2:$X$769,Assignments!$A$2:$A$769,$A13,Assignments!$G$2:$G$769,"Active",Assignments!$V$2:$V$769,"<="&J$4,Assignments!$W$2:$W$769,">="&J$4)+SUMIFS(Assignments!$AA$2:$AA$769,Assignments!$A$2:$A$769,$A13,Assignments!$G$2:$G$769,"Active",Assignments!$Y$2:$Y$769,"<="&J$4,Assignments!$Z$2:$Z$769,">="&J$4)) | ... AB13: =IF($A13="","",SUMIFS(Assignments!$X$2:$X$769,Assignments!$A$2:$A$769,$A13,Assignments!$G$2:$G$769,"Active",Assignments!$V$2:$V$769,"<="&AB$4,Assignments!$W$2:$W$769,">="&AB$4)+SUMIFS(Assignments!$AA$2:$AA$769,Assignments!$A$2:$A$769,$A13,Assignments!$G$2:$G$769,"Active",Assignments!$Y$2:$Y$769,"<="&AB$4,Assignments!$Z$2:$Z$769,">="&AB$4))
A14: =IF(Roster!$A11="","",Roster!$A11) | B14: =IF($A14="","",IFERROR(INDEX(Roster!$D$2:$D$40,MATCH($A14,Roster!$A$2:$A$40,0)),"")) | C14: =IF($A14="","",SUMIFS(Assignments!$X$2:$X$769,Assignments!$A$2:$A$769,$A14,Assignments!$G$2:$G$769,"Active",Assignments!$V$2:$V$769,"<="&C$4,Assignments!$W$2:$W$769,">="&C$4)+SUMIFS(Assignments!$AA$2:$AA$769,Assignments!$A$2:$A$769,$A14,Assignments!$G$2:$G$769,"Active",Assignments!$Y$2:$Y$769,"<="&C$4,Assignments!$Z$2:$Z$769,">="&C$4)) | D14: =IF($A14="","",SUMIFS(Assignments!$X$2:$X$769,Assignments!$A$2:$A$769,$A14,Assignments!$G$2:$G$769,"Active",Assignments!$V$2:$V$769,"<="&D$4,Assignments!$W$2:$W$769,">="&D$4)+SUMIFS(Assignments!$AA$2:$AA$769,Assignments!$A$2:$A$769,$A14,Assignments!$G$2:$G$769,"Active",Assignments!$Y$2:$Y$769,"<="&D$4,Assignments!$Z$2:$Z$769,">="&D$4)) | E14: =IF($A14="","",SUMIFS(Assignments!$X$2:$X$769,Assignments!$A$2:$A$769,$A14,Assignments!$G$2:$G$769,"Active",Assignments!$V$2:$V$769,"<="&E$4,Assignments!$W$2:$W$769,">="&E$4)+SUMIFS(Assignments!$AA$2:$AA$769,Assignments!$A$2:$A$769,$A14,Assignments!$G$2:$G$769,"Active",Assignments!$Y$2:$Y$769,"<="&E$4,Assignments!$Z$2:$Z$769,">="&E$4)) | F14: =IF($A14="","",SUMIFS(Assignments!$X$2:$X$769,Assignments!$A$2:$A$769,$A14,Assignments!$G$2:$G$769,"Active",Assignments!$V$2:$V$769,"<="&F$4,Assignments!$W$2:$W$769,">="&F$4)+SUMIFS(Assignments!$AA$2:$AA$769,Assignments!$A$2:$A$769,$A14,Assignments!$G$2:$G$769,"Active",Assignments!$Y$2:$Y$769,"<="&F$4,Assignments!$Z$2:$Z$769,">="&F$4)) | G14: =IF($A14="","",SUMIFS(Assignments!$X$2:$X$769,Assignments!$A$2:$A$769,$A14,Assignments!$G$2:$G$769,"Active",Assignments!$V$2:$V$769,"<="&G$4,Assignments!$W$2:$W$769,">="&G$4)+SUMIFS(Assignments!$AA$2:$AA$769,Assignments!$A$2:$A$769,$A14,Assignments!$G$2:$G$769,"Active",Assignments!$Y$2:$Y$769,"<="&G$4,Assignments!$Z$2:$Z$769,">="&G$4)) | H14: =IF($A14="","",SUMIFS(Assignments!$X$2:$X$769,Assignments!$A$2:$A$769,$A14,Assignments!$G$2:$G$769,"Active",Assignments!$V$2:$V$769,"<="&H$4,Assignments!$W$2:$W$769,">="&H$4)+SUMIFS(Assignments!$AA$2:$AA$769,Assignments!$A$2:$A$769,$A14,Assignments!$G$2:$G$769,"Active",Assignments!$Y$2:$Y$769,"<="&H$4,Assignments!$Z$2:$Z$769,">="&H$4)) | I14: =IF($A14="","",SUMIFS(Assignments!$X$2:$X$769,Assignments!$A$2:$A$769,$A14,Assignments!$G$2:$G$769,"Active",Assignments!$V$2:$V$769,"<="&I$4,Assignments!$W$2:$W$769,">="&I$4)+SUMIFS(Assignments!$AA$2:$AA$769,Assignments!$A$2:$A$769,$A14,Assignments!$G$2:$G$769,"Active",Assignments!$Y$2:$Y$769,"<="&I$4,Assignments!$Z$2:$Z$769,">="&I$4)) | J14: =IF($A14="","",SUMIFS(Assignments!$X$2:$X$769,Assignments!$A$2:$A$769,$A14,Assignments!$G$2:$G$769,"Active",Assignments!$V$2:$V$769,"<="&J$4,Assignments!$W$2:$W$769,">="&J$4)+SUMIFS(Assignments!$AA$2:$AA$769,Assignments!$A$2:$A$769,$A14,Assignments!$G$2:$G$769,"Active",Assignments!$Y$2:$Y$769,"<="&J$4,Assignments!$Z$2:$Z$769,">="&J$4)) | ... AB14: =IF($A14="","",SUMIFS(Assignments!$X$2:$X$769,Assignments!$A$2:$A$769,$A14,Assignments!$G$2:$G$769,"Active",Assignments!$V$2:$V$769,"<="&AB$4,Assignments!$W$2:$W$769,">="&AB$4)+SUMIFS(Assignments!$AA$2:$AA$769,Assignments!$A$2:$A$769,$A14,Assignments!$G$2:$G$769,"Active",Assignments!$Y$2:$Y$769,"<="&AB$4,Assignments!$Z$2:$Z$769,">="&AB$4))
A15: =IF(Roster!$A12="","",Roster!$A12) | B15: =IF($A15="","",IFERROR(INDEX(Roster!$D$2:$D$40,MATCH($A15,Roster!$A$2:$A$40,0)),"")) | C15: =IF($A15="","",SUMIFS(Assignments!$X$2:$X$769,Assignments!$A$2:$A$769,$A15,Assignments!$G$2:$G$769,"Active",Assignments!$V$2:$V$769,"<="&C$4,Assignments!$W$2:$W$769,">="&C$4)+SUMIFS(Assignments!$AA$2:$AA$769,Assignments!$A$2:$A$769,$A15,Assignments!$G$2:$G$769,"Active",Assignments!$Y$2:$Y$769,"<="&C$4,Assignments!$Z$2:$Z$769,">="&C$4)) | D15: =IF($A15="","",SUMIFS(Assignments!$X$2:$X$769,Assignments!$A$2:$A$769,$A15,Assignments!$G$2:$G$769,"Active",Assignments!$V$2:$V$769,"<="&D$4,Assignments!$W$2:$W$769,">="&D$4)+SUMIFS(Assignments!$AA$2:$AA$769,Assignments!$A$2:$A$769,$A15,Assignments!$G$2:$G$769,"Active",Assignments!$Y$2:$Y$769,"<="&D$4,Assignments!$Z$2:$Z$769,">="&D$4)) | E15: =IF($A15="","",SUMIFS(Assignments!$X$2:$X$769,Assignments!$A$2:$A$769,$A15,Assignments!$G$2:$G$769,"Active",Assignments!$V$2:$V$769,"<="&E$4,Assignments!$W$2:$W$769,">="&E$4)+SUMIFS(Assignments!$AA$2:$AA$769,Assignments!$A$2:$A$769,$A15,Assignments!$G$2:$G$769,"Active",Assignments!$Y$2:$Y$769,"<="&E$4,Assignments!$Z$2:$Z$769,">="&E$4)) | F15: =IF($A15="","",SUMIFS(Assignments!$X$2:$X$769,Assignments!$A$2:$A$769,$A15,Assignments!$G$2:$G$769,"Active",Assignments!$V$2:$V$769,"<="&F$4,Assignments!$W$2:$W$769,">="&F$4)+SUMIFS(Assignments!$AA$2:$AA$769,Assignments!$A$2:$A$769,$A15,Assignments!$G$2:$G$769,"Active",Assignments!$Y$2:$Y$769,"<="&F$4,Assignments!$Z$2:$Z$769,">="&F$4)) | G15: =IF($A15="","",SUMIFS(Assignments!$X$2:$X$769,Assignments!$A$2:$A$769,$A15,Assignments!$G$2:$G$769,"Active",Assignments!$V$2:$V$769,"<="&G$4,Assignments!$W$2:$W$769,">="&G$4)+SUMIFS(Assignments!$AA$2:$AA$769,Assignments!$A$2:$A$769,$A15,Assignments!$G$2:$G$769,"Active",Assignments!$Y$2:$Y$769,"<="&G$4,Assignments!$Z$2:$Z$769,">="&G$4)) | H15: =IF($A15="","",SUMIFS(Assignments!$X$2:$X$769,Assignments!$A$2:$A$769,$A15,Assignments!$G$2:$G$769,"Active",Assignments!$V$2:$V$769,"<="&H$4,Assignments!$W$2:$W$769,">="&H$4)+SUMIFS(Assignments!$AA$2:$AA$769,Assignments!$A$2:$A$769,$A15,Assignments!$G$2:$G$769,"Active",Assignments!$Y$2:$Y$769,"<="&H$4,Assignments!$Z$2:$Z$769,">="&H$4)) | I15: =IF($A15="","",SUMIFS(Assignments!$X$2:$X$769,Assignments!$A$2:$A$769,$A15,Assignments!$G$2:$G$769,"Active",Assignments!$V$2:$V$769,"<="&I$4,Assignments!$W$2:$W$769,">="&I$4)+SUMIFS(Assignments!$AA$2:$AA$769,Assignments!$A$2:$A$769,$A15,Assignments!$G$2:$G$769,"Active",Assignments!$Y$2:$Y$769,"<="&I$4,Assignments!$Z$2:$Z$769,">="&I$4)) | J15: =IF($A15="","",SUMIFS(Assignments!$X$2:$X$769,Assignments!$A$2:$A$769,$A15,Assignments!$G$2:$G$769,"Active",Assignments!$V$2:$V$769,"<="&J$4,Assignments!$W$2:$W$769,">="&J$4)+SUMIFS(Assignments!$AA$2:$AA$769,Assignments!$A$2:$A$769,$A15,Assignments!$G$2:$G$769,"Active",Assignments!$Y$2:$Y$769,"<="&J$4,Assignments!$Z$2:$Z$769,">="&J$4)) | ... AB15: =IF($A15="","",SUMIFS(Assignments!$X$2:$X$769,Assignments!$A$2:$A$769,$A15,Assignments!$G$2:$G$769,"Active",Assignments!$V$2:$V$769,"<="&AB$4,Assignments!$W$2:$W$769,">="&AB$4)+SUMIFS(Assignments!$AA$2:$AA$769,Assignments!$A$2:$A$769,$A15,Assignments!$G$2:$G$769,"Active",Assignments!$Y$2:$Y$769,"<="&AB$4,Assignments!$Z$2:$Z$769,">="&AB$4))
A16: =IF(Roster!$A13="","",Roster!$A13) | B16: =IF($A16="","",IFERROR(INDEX(Roster!$D$2:$D$40,MATCH($A16,Roster!$A$2:$A$40,0)),"")) | C16: =IF($A16="","",SUMIFS(Assignments!$X$2:$X$769,Assignments!$A$2:$A$769,$A16,Assignments!$G$2:$G$769,"Active",Assignments!$V$2:$V$769,"<="&C$4,Assignments!$W$2:$W$769,">="&C$4)+SUMIFS(Assignments!$AA$2:$AA$769,Assignments!$A$2:$A$769,$A16,Assignments!$G$2:$G$769,"Active",Assignments!$Y$2:$Y$769,"<="&C$4,Assignments!$Z$2:$Z$769,">="&C$4)) | D16: =IF($A16="","",SUMIFS(Assignments!$X$2:$X$769,Assignments!$A$2:$A$769,$A16,Assignments!$G$2:$G$769,"Active",Assignments!$V$2:$V$769,"<="&D$4,Assignments!$W$2:$W$769,">="&D$4)+SUMIFS(Assignments!$AA$2:$AA$769,Assignments!$A$2:$A$769,$A16,Assignments!$G$2:$G$769,"Active",Assignments!$Y$2:$Y$769,"<="&D$4,Assignments!$Z$2:$Z$769,">="&D$4)) | E16: =IF($A16="","",SUMIFS(Assignments!$X$2:$X$769,Assignments!$A$2:$A$769,$A16,Assignments!$G$2:$G$769,"Active",Assignments!$V$2:$V$769,"<="&E$4,Assignments!$W$2:$W$769,">="&E$4)+SUMIFS(Assignments!$AA$2:$AA$769,Assignments!$A$2:$A$769,$A16,Assignments!$G$2:$G$769,"Active",Assignments!$Y$2:$Y$769,"<="&E$4,Assignments!$Z$2:$Z$769,">="&E$4)) | F16: =IF($A16="","",SUMIFS(Assignments!$X$2:$X$769,Assignments!$A$2:$A$769,$A16,Assignments!$G$2:$G$769,"Active",Assignments!$V$2:$V$769,"<="&F$4,Assignments!$W$2:$W$769,">="&F$4)+SUMIFS(Assignments!$AA$2:$AA$769,Assignments!$A$2:$A$769,$A16,Assignments!$G$2:$G$769,"Active",Assignments!$Y$2:$Y$769,"<="&F$4,Assignments!$Z$2:$Z$769,">="&F$4)) | G16: =IF($A16="","",SUMIFS(Assignments!$X$2:$X$769,Assignments!$A$2:$A$769,$A16,Assignments!$G$2:$G$769,"Active",Assignments!$V$2:$V$769,"<="&G$4,Assignments!$W$2:$W$769,">="&G$4)+SUMIFS(Assignments!$AA$2:$AA$769,Assignments!$A$2:$A$769,$A16,Assignments!$G$2:$G$769,"Active",Assignments!$Y$2:$Y$769,"<="&G$4,Assignments!$Z$2:$Z$769,">="&G$4)) | H16: =IF($A16="","",SUMIFS(Assignments!$X$2:$X$769,Assignments!$A$2:$A$769,$A16,Assignments!$G$2:$G$769,"Active",Assignments!$V$2:$V$769,"<="&H$4,Assignments!$W$2:$W$769,">="&H$4)+SUMIFS(Assignments!$AA$2:$AA$769,Assignments!$A$2:$A$769,$A16,Assignments!$G$2:$G$769,"Active",Assignments!$Y$2:$Y$769,"<="&H$4,Assignments!$Z$2:$Z$769,">="&H$4)) | I16: =IF($A16="","",SUMIFS(Assignments!$X$2:$X$769,Assignments!$A$2:$A$769,$A16,Assignments!$G$2:$G$769,"Active",Assignments!$V$2:$V$769,"<="&I$4,Assignments!$W$2:$W$769,">="&I$4)+SUMIFS(Assignments!$AA$2:$AA$769,Assignments!$A$2:$A$769,$A16,Assignments!$G$2:$G$769,"Active",Assignments!$Y$2:$Y$769,"<="&I$4,Assignments!$Z$2:$Z$769,">="&I$4)) | J16: =IF($A16="","",SUMIFS(Assignments!$X$2:$X$769,Assignments!$A$2:$A$769,$A16,Assignments!$G$2:$G$769,"Active",Assignments!$V$2:$V$769,"<="&J$4,Assignments!$W$2:$W$769,">="&J$4)+SUMIFS(Assignments!$AA$2:$AA$769,Assignments!$A$2:$A$769,$A16,Assignments!$G$2:$G$769,"Active",Assignments!$Y$2:$Y$769,"<="&J$4,Assignments!$Z$2:$Z$769,">="&J$4)) | ... AB16: =IF($A16="","",SUMIFS(Assignments!$X$2:$X$769,Assignments!$A$2:$A$769,$A16,Assignments!$G$2:$G$769,"Active",Assignments!$V$2:$V$769,"<="&AB$4,Assignments!$W$2:$W$769,">="&AB$4)+SUMIFS(Assignments!$AA$2:$AA$769,Assignments!$A$2:$A$769,$A16,Assignments!$G$2:$G$769,"Active",Assignments!$Y$2:$Y$769,"<="&AB$4,Assignments!$Z$2:$Z$769,">="&AB$4))
... A43: =IF(Roster!$A40="","",Roster!$A40) | B43: =IF($A43="","",IFERROR(INDEX(Roster!$D$2:$D$40,MATCH($A43,Roster!$A$2:$A$40,0)),"")) | C43: =IF($A43="","",SUMIFS(Assignments!$X$2:$X$769,Assignments!$A$2:$A$769,$A43,Assignments!$G$2:$G$769,"Active",Assignments!$V$2:$V$769,"<="&C$4,Assignments!$W$2:$W$769,">="&C$4)+SUMIFS(Assignments!$AA$2:$AA$769,Assignments!$A$2:$A$769,$A43,Assignments!$G$2:$G$769,"Active",Assignments!$Y$2:$Y$769,"<="&C$4,Assignments!$Z$2:$Z$769,">="&C$4)) | D43: =IF($A43="","",SUMIFS(Assignments!$X$2:$X$769,Assignments!$A$2:$A$769,$A43,Assignments!$G$2:$G$769,"Active",Assignments!$V$2:$V$769,"<="&D$4,Assignments!$W$2:$W$769,">="&D$4)+SUMIFS(Assignments!$AA$2:$AA$769,Assignments!$A$2:$A$769,$A43,Assignments!$G$2:$G$769,"Active",Assignments!$Y$2:$Y$769,"<="&D$4,Assignments!$Z$2:$Z$769,">="&D$4)) | E43: =IF($A43="","",SUMIFS(Assignments!$X$2:$X$769,Assignments!$A$2:$A$769,$A43,Assignments!$G$2:$G$769,"Active",Assignments!$V$2:$V$769,"<="&E$4,Assignments!$W$2:$W$769,">="&E$4)+SUMIFS(Assignments!$AA$2:$AA$769,Assignments!$A$2:$A$769,$A43,Assignments!$G$2:$G$769,"Active",Assignments!$Y$2:$Y$769,"<="&E$4,Assignments!$Z$2:$Z$769,">="&E$4)) | F43: =IF($A43="","",SUMIFS(Assignments!$X$2:$X$769,Assignments!$A$2:$A$769,$A43,Assignments!$G$2:$G$769,"Active",Assignments!$V$2:$V$769,"<="&F$4,Assignments!$W$2:$W$769,">="&F$4)+SUMIFS(Assignments!$AA$2:$AA$769,Assignments!$A$2:$A$769,$A43,Assignments!$G$2:$G$769,"Active",Assignments!$Y$2:$Y$769,"<="&F$4,Assignments!$Z$2:$Z$769,">="&F$4)) | G43: =IF($A43="","",SUMIFS(Assignments!$X$2:$X$769,Assignments!$A$2:$A$769,$A43,Assignments!$G$2:$G$769,"Active",Assignments!$V$2:$V$769,"<="&G$4,Assignments!$W$2:$W$769,">="&G$4)+SUMIFS(Assignments!$AA$2:$AA$769,Assignments!$A$2:$A$769,$A43,Assignments!$G$2:$G$769,"Active",Assignments!$Y$2:$Y$769,"<="&G$4,Assignments!$Z$2:$Z$769,">="&G$4)) | H43: =IF($A43="","",SUMIFS(Assignments!$X$2:$X$769,Assignments!$A$2:$A$769,$A43,Assignments!$G$2:$G$769,"Active",Assignments!$V$2:$V$769,"<="&H$4,Assignments!$W$2:$W$769,">="&H$4)+SUMIFS(Assignments!$AA$2:$AA$769,Assignments!$A$2:$A$769,$A43,Assignments!$G$2:$G$769,"Active",Assignments!$Y$2:$Y$769,"<="&H$4,Assignments!$Z$2:$Z$769,">="&H$4)) | I43: =IF($A43="","",SUMIFS(Assignments!$X$2:$X$769,Assignments!$A$2:$A$769,$A43,Assignments!$G$2:$G$769,"Active",Assignments!$V$2:$V$769,"<="&I$4,Assignments!$W$2:$W$769,">="&I$4)+SUMIFS(Assignments!$AA$2:$AA$769,Assignments!$A$2:$A$769,$A43,Assignments!$G$2:$G$769,"Active",Assignments!$Y$2:$Y$769,"<="&I$4,Assignments!$Z$2:$Z$769,">="&I$4)) | J43: =IF($A43="","",SUMIFS(Assignments!$X$2:$X$769,Assignments!$A$2:$A$769,$A43,Assignments!$G$2:$G$769,"Active",Assignments!$V$2:$V$769,"<="&J$4,Assignments!$W$2:$W$769,">="&J$4)+SUMIFS(Assignments!$AA$2:$AA$769,Assignments!$A$2:$A$769,$A43,Assignments!$G$2:$G$769,"Active",Assignments!$Y$2:$Y$769,"<="&J$4,Assignments!$Z$2:$Z$769,">="&J$4)) | ... AB43: =IF($A43="","",SUMIFS(Assignments!$X$2:$X$769,Assignments!$A$2:$A$769,$A43,Assignments!$G$2:$G$769,"Active",Assignments!$V$2:$V$769,"<="&AB$4,Assignments!$W$2:$W$769,">="&AB$4)+SUMIFS(Assignments!$AA$2:$AA$769,Assignments!$A$2:$A$769,$A43,Assignments!$G$2:$G$769,"Active",Assignments!$Y$2:$Y$769,"<="&AB$4,Assignments!$Z$2:$Z$769,">="&AB$4))
A45: Team planned | C45: =SUM(C5:C43) | D45: =SUM(D5:D43) | E45: =SUM(E5:E43) | F45: =SUM(F5:F43) | G45: =SUM(G5:G43) | H45: =SUM(H5:H43) | I45: =SUM(I5:I43) | J45: =SUM(J5:J43) | ... AB45: =SUM(AB5:AB43)
A46: Team capacity | C46: =SUM(Roster!$D$2:$D$40) | D46: =SUM(Roster!$D$2:$D$40) | E46: =SUM(Roster!$D$2:$D$40) | F46: =SUM(Roster!$D$2:$D$40) | G46: =SUM(Roster!$D$2:$D$40) | H46: =SUM(Roster!$D$2:$D$40) | I46: =SUM(Roster!$D$2:$D$40) | J46: =SUM(Roster!$D$2:$D$40) | ... AB46: =SUM(Roster!$D$2:$D$40)
A47: Headroom | C47: =C46-C45 | D47: =D46-D45 | E47: =E46-E45 | F47: =F46-F45 | G47: =G46-G45 | H47: =H46-H45 | I47: =I46-I45 | J47: =J46-J45 | ... AB47: =AB46-AB45

Sheet Check-in
A1: Weekly Check-in Agenda
A2: ="As of "&TEXT(Settings!$B$19,"yyyy-mm-dd")&" | Validate near-term capacity, rebalance workload, confirm staffing on incoming deals. Update Settings!B19 to today before each check-in."
A3: Definitions (adjust in Settings if the team means something different): 'Missing level' = the deal has an Effort archetype that expects hours from a level, but nobody at that level is actively staffed. 'Stale' = weeks since Added-on >= the Settings threshold (currently editable at Settings!B20).
A5: 1) Capacity - next 4 weeks
A6: Person | B6: Level | C6: Cap hrs/wk | D6: Max load (4 wk) | E6: Max utilization | F6: Flag
A7: =IF(Roster!$A2="","",Roster!$A2) | B7: =IF($A7="","",Roster!$B2) | C7: =IF($A7="","",Roster!$D2) | D7: =IF($A7="","",MAX(Capacity!$C$5:$F$5)) | E7: =IF(OR($A7="",$C7=0),"",$D7/$C7) | F7: =IF($A7="","",IF(AND(ISNUMBER($E7),$E7>1),"OVER-ALLOCATED",IF(AND(ISNUMBER($E7),$E7<0.5),"UNDER-UTILIZED","")))
A8: =IF(Roster!$A3="","",Roster!$A3) | B8: =IF($A8="","",Roster!$B3) | C8: =IF($A8="","",Roster!$D3) | D8: =IF($A8="","",MAX(Capacity!$C$6:$F$6)) | E8: =IF(OR($A8="",$C8=0),"",$D8/$C8) | F8: =IF($A8="","",IF(AND(ISNUMBER($E8),$E8>1),"OVER-ALLOCATED",IF(AND(ISNUMBER($E8),$E8<0.5),"UNDER-UTILIZED","")))
A9: =IF(Roster!$A4="","",Roster!$A4) | B9: =IF($A9="","",Roster!$B4) | C9: =IF($A9="","",Roster!$D4) | D9: =IF($A9="","",MAX(Capacity!$C$7:$F$7)) | E9: =IF(OR($A9="",$C9=0),"",$D9/$C9) | F9: =IF($A9="","",IF(AND(ISNUMBER($E9),$E9>1),"OVER-ALLOCATED",IF(AND(ISNUMBER($E9),$E9<0.5),"UNDER-UTILIZED","")))
A10: =IF(Roster!$A5="","",Roster!$A5) | B10: =IF($A10="","",Roster!$B5) | C10: =IF($A10="","",Roster!$D5) | D10: =IF($A10="","",MAX(Capacity!$C$8:$F$8)) | E10: =IF(OR($A10="",$C10=0),"",$D10/$C10) | F10: =IF($A10="","",IF(AND(ISNUMBER($E10),$E10>1),"OVER-ALLOCATED",IF(AND(ISNUMBER($E10),$E10<0.5),"UNDER-UTILIZED","")))
A11: =IF(Roster!$A6="","",Roster!$A6) | B11: =IF($A11="","",Roster!$B6) | C11: =IF($A11="","",Roster!$D6) | D11: =IF($A11="","",MAX(Capacity!$C$9:$F$9)) | E11: =IF(OR($A11="",$C11=0),"",$D11/$C11) | F11: =IF($A11="","",IF(AND(ISNUMBER($E11),$E11>1),"OVER-ALLOCATED",IF(AND(ISNUMBER($E11),$E11<0.5),"UNDER-UTILIZED","")))
A12: =IF(Roster!$A7="","",Roster!$A7) | B12: =IF($A12="","",Roster!$B7) | C12: =IF($A12="","",Roster!$D7) | D12: =IF($A12="","",MAX(Capacity!$C$10:$F$10)) | E12: =IF(OR($A12="",$C12=0),"",$D12/$C12) | F12: =IF($A12="","",IF(AND(ISNUMBER($E12),$E12>1),"OVER-ALLOCATED",IF(AND(ISNUMBER($E12),$E12<0.5),"UNDER-UTILIZED","")))
A13: =IF(Roster!$A8="","",Roster!$A8) | B13: =IF($A13="","",Roster!$B8) | C13: =IF($A13="","",Roster!$D8) | D13: =IF($A13="","",MAX(Capacity!$C$11:$F$11)) | E13: =IF(OR($A13="",$C13=0),"",$D13/$C13) | F13: =IF($A13="","",IF(AND(ISNUMBER($E13),$E13>1),"OVER-ALLOCATED",IF(AND(ISNUMBER($E13),$E13<0.5),"UNDER-UTILIZED","")))
A14: =IF(Roster!$A9="","",Roster!$A9) | B14: =IF($A14="","",Roster!$B9) | C14: =IF($A14="","",Roster!$D9) | D14: =IF($A14="","",MAX(Capacity!$C$12:$F$12)) | E14: =IF(OR($A14="",$C14=0),"",$D14/$C14) | F14: =IF($A14="","",IF(AND(ISNUMBER($E14),$E14>1),"OVER-ALLOCATED",IF(AND(ISNUMBER($E14),$E14<0.5),"UNDER-UTILIZED","")))
A15: =IF(Roster!$A10="","",Roster!$A10) | B15: =IF($A15="","",Roster!$B10) | C15: =IF($A15="","",Roster!$D10) | D15: =IF($A15="","",MAX(Capacity!$C$13:$F$13)) | E15: =IF(OR($A15="",$C15=0),"",$D15/$C15) | F15: =IF($A15="","",IF(AND(ISNUMBER($E15),$E15>1),"OVER-ALLOCATED",IF(AND(ISNUMBER($E15),$E15<0.5),"UNDER-UTILIZED","")))
A16: =IF(Roster!$A11="","",Roster!$A11) | B16: =IF($A16="","",Roster!$B11) | C16: =IF($A16="","",Roster!$D11) | D16: =IF($A16="","",MAX(Capacity!$C$14:$F$14)) | E16: =IF(OR($A16="",$C16=0),"",$D16/$C16) | F16: =IF($A16="","",IF(AND(ISNUMBER($E16),$E16>1),"OVER-ALLOCATED",IF(AND(ISNUMBER($E16),$E16<0.5),"UNDER-UTILIZED","")))
A17: =IF(Roster!$A12="","",Roster!$A12) | B17: =IF($A17="","",Roster!$B12) | C17: =IF($A17="","",Roster!$D12) | D17: =IF($A17="","",MAX(Capacity!$C$15:$F$15)) | E17: =IF(OR($A17="",$C17=0),"",$D17/$C17) | F17: =IF($A17="","",IF(AND(ISNUMBER($E17),$E17>1),"OVER-ALLOCATED",IF(AND(ISNUMBER($E17),$E17<0.5),"UNDER-UTILIZED","")))
A18: =IF(Roster!$A13="","",Roster!$A13) | B18: =IF($A18="","",Roster!$B13) | C18: =IF($A18="","",Roster!$D13) | D18: =IF($A18="","",MAX(Capacity!$C$16:$F$16)) | E18: =IF(OR($A18="",$C18=0),"",$D18/$C18) | F18: =IF($A18="","",IF(AND(ISNUMBER($E18),$E18>1),"OVER-ALLOCATED",IF(AND(ISNUMBER($E18),$E18<0.5),"UNDER-UTILIZED","")))
A19: =IF(Roster!$A14="","",Roster!$A14) | B19: =IF($A19="","",Roster!$B14) | C19: =IF($A19="","",Roster!$D14) | D19: =IF($A19="","",MAX(Capacity!$C$17:$F$17)) | E19: =IF(OR($A19="",$C19=0),"",$D19/$C19) | F19: =IF($A19="","",IF(AND(ISNUMBER($E19),$E19>1),"OVER-ALLOCATED",IF(AND(ISNUMBER($E19),$E19<0.5),"UNDER-UTILIZED","")))
A20: =IF(Roster!$A15="","",Roster!$A15) | B20: =IF($A20="","",Roster!$B15) | C20: =IF($A20="","",Roster!$D15) | D20: =IF($A20="","",MAX(Capacity!$C$18:$F$18)) | E20: =IF(OR($A20="",$C20=0),"",$D20/$C20) | F20: =IF($A20="","",IF(AND(ISNUMBER($E20),$E20>1),"OVER-ALLOCATED",IF(AND(ISNUMBER($E20),$E20<0.5),"UNDER-UTILIZED","")))
A21: =IF(Roster!$A16="","",Roster!$A16) | B21: =IF($A21="","",Roster!$B16) | C21: =IF($A21="","",Roster!$D16) | D21: =IF($A21="","",MAX(Capacity!$C$19:$F$19)) | E21: =IF(OR($A21="",$C21=0),"",$D21/$C21) | F21: =IF($A21="","",IF(AND(ISNUMBER($E21),$E21>1),"OVER-ALLOCATED",IF(AND(ISNUMBER($E21),$E21<0.5),"UNDER-UTILIZED","")))
A22: =IF(Roster!$A17="","",Roster!$A17) | B22: =IF($A22="","",Roster!$B17) | C22: =IF($A22="","",Roster!$D17) | D22: =IF($A22="","",MAX(Capacity!$C$20:$F$20)) | E22: =IF(OR($A22="",$C22=0),"",$D22/$C22) | F22: =IF($A22="","",IF(AND(ISNUMBER($E22),$E22>1),"OVER-ALLOCATED",IF(AND(ISNUMBER($E22),$E22<0.5),"UNDER-UTILIZED","")))
A23: =IF(Roster!$A18="","",Roster!$A18) | B23: =IF($A23="","",Roster!$B18) | C23: =IF($A23="","",Roster!$D18) | D23: =IF($A23="","",MAX(Capacity!$C$21:$F$21)) | E23: =IF(OR($A23="",$C23=0),"",$D23/$C23) | F23: =IF($A23="","",IF(AND(ISNUMBER($E23),$E23>1),"OVER-ALLOCATED",IF(AND(ISNUMBER($E23),$E23<0.5),"UNDER-UTILIZED","")))
A24: =IF(Roster!$A19="","",Roster!$A19) | B24: =IF($A24="","",Roster!$B19) | C24: =IF($A24="","",Roster!$D19) | D24: =IF($A24="","",MAX(Capacity!$C$22:$F$22)) | E24: =IF(OR($A24="",$C24=0),"",$D24/$C24) | F24: =IF($A24="","",IF(AND(ISNUMBER($E24),$E24>1),"OVER-ALLOCATED",IF(AND(ISNUMBER($E24),$E24<0.5),"UNDER-UTILIZED","")))
A25: =IF(Roster!$A20="","",Roster!$A20) | B25: =IF($A25="","",Roster!$B20) | C25: =IF($A25="","",Roster!$D20) | D25: =IF($A25="","",MAX(Capacity!$C$23:$F$23)) | E25: =IF(OR($A25="",$C25=0),"",$D25/$C25) | F25: =IF($A25="","",IF(AND(ISNUMBER($E25),$E25>1),"OVER-ALLOCATED",IF(AND(ISNUMBER($E25),$E25<0.5),"UNDER-UTILIZED","")))
A26: =IF(Roster!$A21="","",Roster!$A21) | B26: =IF($A26="","",Roster!$B21) | C26: =IF($A26="","",Roster!$D21) | D26: =IF($A26="","",MAX(Capacity!$C$24:$F$24)) | E26: =IF(OR($A26="",$C26=0),"",$D26/$C26) | F26: =IF($A26="","",IF(AND(ISNUMBER($E26),$E26>1),"OVER-ALLOCATED",IF(AND(ISNUMBER($E26),$E26<0.5),"UNDER-UTILIZED","")))
A27: =IF(Roster!$A22="","",Roster!$A22) | B27: =IF($A27="","",Roster!$B22) | C27: =IF($A27="","",Roster!$D22) | D27: =IF($A27="","",MAX(Capacity!$C$25:$F$25)) | E27: =IF(OR($A27="",$C27=0),"",$D27/$C27) | F27: =IF($A27="","",IF(AND(ISNUMBER($E27),$E27>1),"OVER-ALLOCATED",IF(AND(ISNUMBER($E27),$E27<0.5),"UNDER-UTILIZED","")))
A28: =IF(Roster!$A23="","",Roster!$A23) | B28: =IF($A28="","",Roster!$B23) | C28: =IF($A28="","",Roster!$D23) | D28: =IF($A28="","",MAX(Capacity!$C$26:$F$26)) | E28: =IF(OR($A28="",$C28=0),"",$D28/$C28) | F28: =IF($A28="","",IF(AND(ISNUMBER($E28),$E28>1),"OVER-ALLOCATED",IF(AND(ISNUMBER($E28),$E28<0.5),"UNDER-UTILIZED","")))
A29: =IF(Roster!$A24="","",Roster!$A24) | B29: =IF($A29="","",Roster!$B24) | C29: =IF($A29="","",Roster!$D24) | D29: =IF($A29="","",MAX(Capacity!$C$27:$F$27)) | E29: =IF(OR($A29="",$C29=0),"",$D29/$C29) | F29: =IF($A29="","",IF(AND(ISNUMBER($E29),$E29>1),"OVER-ALLOCATED",IF(AND(ISNUMBER($E29),$E29<0.5),"UNDER-UTILIZED","")))
A30: =IF(Roster!$A25="","",Roster!$A25) | B30: =IF($A30="","",Roster!$B25) | C30: =IF($A30="","",Roster!$D25) | D30: =IF($A30="","",MAX(Capacity!$C$28:$F$28)) | E30: =IF(OR($A30="",$C30=0),"",$D30/$C30) | F30: =IF($A30="","",IF(AND(ISNUMBER($E30),$E30>1),"OVER-ALLOCATED",IF(AND(ISNUMBER($E30),$E30<0.5),"UNDER-UTILIZED","")))
A31: =IF(Roster!$A26="","",Roster!$A26) | B31: =IF($A31="","",Roster!$B26) | C31: =IF($A31="","",Roster!$D26) | D31: =IF($A31="","",MAX(Capacity!$C$29:$F$29)) | E31: =IF(OR($A31="",$C31=0),"",$D31/$C31) | F31: =IF($A31="","",IF(AND(ISNUMBER($E31),$E31>1),"OVER-ALLOCATED",IF(AND(ISNUMBER($E31),$E31<0.5),"UNDER-UTILIZED","")))
A32: =IF(Roster!$A27="","",Roster!$A27) | B32: =IF($A32="","",Roster!$B27) | C32: =IF($A32="","",Roster!$D27) | D32: =IF($A32="","",MAX(Capacity!$C$30:$F$30)) | E32: =IF(OR($A32="",$C32=0),"",$D32/$C32) | F32: =IF($A32="","",IF(AND(ISNUMBER($E32),$E32>1),"OVER-ALLOCATED",IF(AND(ISNUMBER($E32),$E32<0.5),"UNDER-UTILIZED","")))
A33: =IF(Roster!$A28="","",Roster!$A28) | B33: =IF($A33="","",Roster!$B28) | C33: =IF($A33="","",Roster!$D28) | D33: =IF($A33="","",MAX(Capacity!$C$31:$F$31)) | E33: =IF(OR($A33="",$C33=0),"",$D33/$C33) | F33: =IF($A33="","",IF(AND(ISNUMBER($E33),$E33>1),"OVER-ALLOCATED",IF(AND(ISNUMBER($E33),$E33<0.5),"UNDER-UTILIZED","")))
A34: =IF(Roster!$A29="","",Roster!$A29) | B34: =IF($A34="","",Roster!$B29) | C34: =IF($A34="","",Roster!$D29) | D34: =IF($A34="","",MAX(Capacity!$C$32:$F$32)) | E34: =IF(OR($A34="",$C34=0),"",$D34/$C34) | F34: =IF($A34="","",IF(AND(ISNUMBER($E34),$E34>1),"OVER-ALLOCATED",IF(AND(ISNUMBER($E34),$E34<0.5),"UNDER-UTILIZED","")))
A35: =IF(Roster!$A30="","",Roster!$A30) | B35: =IF($A35="","",Roster!$B30) | C35: =IF($A35="","",Roster!$D30) | D35: =IF($A35="","",MAX(Capacity!$C$33:$F$33)) | E35: =IF(OR($A35="",$C35=0),"",$D35/$C35) | F35: =IF($A35="","",IF(AND(ISNUMBER($E35),$E35>1),"OVER-ALLOCATED",IF(AND(ISNUMBER($E35),$E35<0.5),"UNDER-UTILIZED","")))
A36: =IF(Roster!$A31="","",Roster!$A31) | B36: =IF($A36="","",Roster!$B31) | C36: =IF($A36="","",Roster!$D31) | D36: =IF($A36="","",MAX(Capacity!$C$34:$F$34)) | E36: =IF(OR($A36="",$C36=0),"",$D36/$C36) | F36: =IF($A36="","",IF(AND(ISNUMBER($E36),$E36>1),"OVER-ALLOCATED",IF(AND(ISNUMBER($E36),$E36<0.5),"UNDER-UTILIZED","")))
A37: =IF(Roster!$A32="","",Roster!$A32) | B37: =IF($A37="","",Roster!$B32) | C37: =IF($A37="","",Roster!$D32) | D37: =IF($A37="","",MAX(Capacity!$C$35:$F$35)) | E37: =IF(OR($A37="",$C37=0),"",$D37/$C37) | F37: =IF($A37="","",IF(AND(ISNUMBER($E37),$E37>1),"OVER-ALLOCATED",IF(AND(ISNUMBER($E37),$E37<0.5),"UNDER-UTILIZED","")))
A38: =IF(Roster!$A33="","",Roster!$A33) | B38: =IF($A38="","",Roster!$B33) | C38: =IF($A38="","",Roster!$D33) | D38: =IF($A38="","",MAX(Capacity!$C$36:$F$36)) | E38: =IF(OR($A38="",$C38=0),"",$D38/$C38) | F38: =IF($A38="","",IF(AND(ISNUMBER($E38),$E38>1),"OVER-ALLOCATED",IF(AND(ISNUMBER($E38),$E38<0.5),"UNDER-UTILIZED","")))
A39: =IF(Roster!$A34="","",Roster!$A34) | B39: =IF($A39="","",Roster!$B34) | C39: =IF($A39="","",Roster!$D34) | D39: =IF($A39="","",MAX(Capacity!$C$37:$F$37)) | E39: =IF(OR($A39="",$C39=0),"",$D39/$C39) | F39: =IF($A39="","",IF(AND(ISNUMBER($E39),$E39>1),"OVER-ALLOCATED",IF(AND(ISNUMBER($E39),$E39<0.5),"UNDER-UTILIZED","")))
A40: =IF(Roster!$A35="","",Roster!$A35) | B40: =IF($A40="","",Roster!$B35) | C40: =IF($A40="","",Roster!$D35) | D40: =IF($A40="","",MAX(Capacity!$C$38:$F$38)) | E40: =IF(OR($A40="",$C40=0),"",$D40/$C40) | F40: =IF($A40="","",IF(AND(ISNUMBER($E40),$E40>1),"OVER-ALLOCATED",IF(AND(ISNUMBER($E40),$E40<0.5),"UNDER-UTILIZED","")))
A41: =IF(Roster!$A36="","",Roster!$A36) | B41: =IF($A41="","",Roster!$B36) | C41: =IF($A41="","",Roster!$D36) | D41: =IF($A41="","",MAX(Capacity!$C$39:$F$39)) | E41: =IF(OR($A41="",$C41=0),"",$D41/$C41) | F41: =IF($A41="","",IF(AND(ISNUMBER($E41),$E41>1),"OVER-ALLOCATED",IF(AND(ISNUMBER($E41),$E41<0.5),"UNDER-UTILIZED","")))
A42: =IF(Roster!$A37="","",Roster!$A37) | B42: =IF($A42="","",Roster!$B37) | C42: =IF($A42="","",Roster!$D37) | D42: =IF($A42="","",MAX(Capacity!$C$40:$F$40)) | E42: =IF(OR($A42="",$C42=0),"",$D42/$C42) | F42: =IF($A42="","",IF(AND(ISNUMBER($E42),$E42>1),"OVER-ALLOCATED",IF(AND(ISNUMBER($E42),$E42<0.5),"UNDER-UTILIZED","")))
A43: =IF(Roster!$A38="","",Roster!$A38) | B43: =IF($A43="","",Roster!$B38) | C43: =IF($A43="","",Roster!$D38) | D43: =IF($A43="","",MAX(Capacity!$C$41:$F$41)) | E43: =IF(OR($A43="",$C43=0),"",$D43/$C43) | F43: =IF($A43="","",IF(AND(ISNUMBER($E43),$E43>1),"OVER-ALLOCATED",IF(AND(ISNUMBER($E43),$E43<0.5),"UNDER-UTILIZED","")))
A44: =IF(Roster!$A39="","",Roster!$A39) | B44: =IF($A44="","",Roster!$B39) | C44: =IF($A44="","",Roster!$D39) | D44: =IF($A44="","",MAX(Capacity!$C$42:$F$42)) | E44: =IF(OR($A44="",$C44=0),"",$D44/$C44) | F44: =IF($A44="","",IF(AND(ISNUMBER($E44),$E44>1),"OVER-ALLOCATED",IF(AND(ISNUMBER($E44),$E44<0.5),"UNDER-UTILIZED","")))
A45: =IF(Roster!$A40="","",Roster!$A40) | B45: =IF($A45="","",Roster!$B40) | C45: =IF($A45="","",Roster!$D40) | D45: =IF($A45="","",MAX(Capacity!$C$43:$F$43)) | E45: =IF(OR($A45="",$C45=0),"",$D45/$C45) | F45: =IF($A45="","",IF(AND(ISNUMBER($E45),$E45>1),"OVER-ALLOCATED",IF(AND(ISNUMBER($E45),$E45<0.5),"UNDER-UTILIZED","")))
A48: 2) Deals needing attention
A49: Project ID | B49: Client | C49: Lifecycle | D49: Probability | E49: # staffed | F49: Dates set? | G49: Added on | H49: Weeks since added | I49: Flag
A50: =IF(Deals!$A2="","",Deals!$A2) | B50: =IF($A50="","",Deals!$C2) | C50: =IF($A50="","",Deals!$F2) | D50: =IF($A50="","",Deals!$H2) | E50: =IF($A50="","",Deals!$Q2) | F50: =IF($A50="","",IF(AND(Deals!$I2<>"",Deals!$J2<>""),"Yes","No")) | G50: =IF($A50="","",Deals!$Z2) | H50: =IF(OR($A50="",$G50=""),"",INT((Settings!$B$19-$G50)/7)) | I50: =IF(OR($A50="",NOT(OR(Deals!$F2="Active",Deals!$F2="Proposal"))),"",TRIM(IF($E50=0," Unstaffed","")&IF(IF(Deals!$U2="",FALSE,OR(AND(IFERROR(INDEX(Templates!$B$3:$B$10,MATCH(Deals!$U2,Templates!$A$3:$A$10,0)),0)>0,COUNTIFS(Assignments!$C$2:$C$769,$A50,Assignments!$F$2:$F$769,"Partner",Assignments!$G$2:$G$769,"Active")=0),AND(IFERROR(INDEX(Templates!$C$3:$C$10,MATCH(Deals!$U2,Templates!$A$3:$A$10,0)),0)>0,COUNTIFS(Assignments!$C$2:$C$769,$A50,Assignments!$F$2:$F$769,"MD",Assignments!$G$2:$G$769,"Active")=0),AND(IFERROR(INDEX(Templates!$D$3:$D$10,MATCH(Deals!$U2,Templates!$A$3:$A$10,0)),0)>0,COUNTIFS(Assignments!$C$2:$C$769,$A50,Assignments!$F$2:$F$769,"Director",Assignments!$G$2:$G$769,"Active")=0),AND(IFERROR(INDEX(Templates!$E$3:$E$10,MATCH(Deals!$U2,Templates!$A$3:$A$10,0)),0)>0,COUNTIFS(Assignments!$C$2:$C$769,$A50,Assignments!$F$2:$F$769,"VP",Assignments!$G$2:$G$769,"Active")=0),AND(IFERROR(INDEX(Templates!$F$3:$F$10,MATCH(Deals!$U2,Templates!$A$3:$A$10,0)),0)>0,COUNTIFS(Assignments!$C$2:$C$769,$A50,Assignments!$F$2:$F$769,"Senior Associate",Assignments!$G$2:$G$769,"Active")=0),AND(IFERROR(INDEX(Templates!$G$3:$G$10,MATCH(Deals!$U2,Templates!$A$3:$A$10,0)),0)>0,COUNTIFS(Assignments!$C$2:$C$769,$A50,Assignments!$F$2:$F$769,"Renewable Specialist",Assignments!$G$2:$G$769,"Active")=0),AND(IFERROR(INDEX(Templates!$H$3:$H$10,MATCH(Deals!$U2,Templates!$A$3:$A$10,0)),0)>0,COUNTIFS(Assignments!$C$2:$C$769,$A50,Assignments!$F$2:$F$769,"Associate",Assignments!$G$2:$G$769,"Active")=0)))," MissingLevel","")&IF(AND($C50="Proposal",Deals!$H2=0.5)," DefaultProbability","")&IF($F50="No"," NoDates","")&IF(AND(ISNUMBER($H50),$H50>=Settings!$B$20)," Stale","")))
A51: =IF(Deals!$A3="","",Deals!$A3) | B51: =IF($A51="","",Deals!$C3) | C51: =IF($A51="","",Deals!$F3) | D51: =IF($A51="","",Deals!$H3) | E51: =IF($A51="","",Deals!$Q3) | F51: =IF($A51="","",IF(AND(Deals!$I3<>"",Deals!$J3<>""),"Yes","No")) | G51: =IF($A51="","",Deals!$Z3) | H51: =IF(OR($A51="",$G51=""),"",INT((Settings!$B$19-$G51)/7)) | I51: =IF(OR($A51="",NOT(OR(Deals!$F3="Active",Deals!$F3="Proposal"))),"",TRIM(IF($E51=0," Unstaffed","")&IF(IF(Deals!$U3="",FALSE,OR(AND(IFERROR(INDEX(Templates!$B$3:$B$10,MATCH(Deals!$U3,Templates!$A$3:$A$10,0)),0)>0,COUNTIFS(Assignments!$C$2:$C$769,$A51,Assignments!$F$2:$F$769,"Partner",Assignments!$G$2:$G$769,"Active")=0),AND(IFERROR(INDEX(Templates!$C$3:$C$10,MATCH(Deals!$U3,Templates!$A$3:$A$10,0)),0)>0,COUNTIFS(Assignments!$C$2:$C$769,$A51,Assignments!$F$2:$F$769,"MD",Assignments!$G$2:$G$769,"Active")=0),AND(IFERROR(INDEX(Templates!$D$3:$D$10,MATCH(Deals!$U3,Templates!$A$3:$A$10,0)),0)>0,COUNTIFS(Assignments!$C$2:$C$769,$A51,Assignments!$F$2:$F$769,"Director",Assignments!$G$2:$G$769,"Active")=0),AND(IFERROR(INDEX(Templates!$E$3:$E$10,MATCH(Deals!$U3,Templates!$A$3:$A$10,0)),0)>0,COUNTIFS(Assignments!$C$2:$C$769,$A51,Assignments!$F$2:$F$769,"VP",Assignments!$G$2:$G$769,"Active")=0),AND(IFERROR(INDEX(Templates!$F$3:$F$10,MATCH(Deals!$U3,Templates!$A$3:$A$10,0)),0)>0,COUNTIFS(Assignments!$C$2:$C$769,$A51,Assignments!$F$2:$F$769,"Senior Associate",Assignments!$G$2:$G$769,"Active")=0),AND(IFERROR(INDEX(Templates!$G$3:$G$10,MATCH(Deals!$U3,Templates!$A$3:$A$10,0)),0)>0,COUNTIFS(Assignments!$C$2:$C$769,$A51,Assignments!$F$2:$F$769,"Renewable Specialist",Assignments!$G$2:$G$769,"Active")=0),AND(IFERROR(INDEX(Templates!$H$3:$H$10,MATCH(Deals!$U3,Templates!$A$3:$A$10,0)),0)>0,COUNTIFS(Assignments!$C$2:$C$769,$A51,Assignments!$F$2:$F$769,"Associate",Assignments!$G$2:$G$769,"Active")=0)))," MissingLevel","")&IF(AND($C51="Proposal",Deals!$H3=0.5)," DefaultProbability","")&IF($F51="No"," NoDates","")&IF(AND(ISNUMBER($H51),$H51>=Settings!$B$20)," Stale","")))
A52: =IF(Deals!$A4="","",Deals!$A4) | B52: =IF($A52="","",Deals!$C4) | C52: =IF($A52="","",Deals!$F4) | D52: =IF($A52="","",Deals!$H4) | E52: =IF($A52="","",Deals!$Q4) | F52: =IF($A52="","",IF(AND(Deals!$I4<>"",Deals!$J4<>""),"Yes","No")) | G52: =IF($A52="","",Deals!$Z4) | H52: =IF(OR($A52="",$G52=""),"",INT((Settings!$B$19-$G52)/7)) | I52: =IF(OR($A52="",NOT(OR(Deals!$F4="Active",Deals!$F4="Proposal"))),"",TRIM(IF($E52=0," Unstaffed","")&IF(IF(Deals!$U4="",FALSE,OR(AND(IFERROR(INDEX(Templates!$B$3:$B$10,MATCH(Deals!$U4,Templates!$A$3:$A$10,0)),0)>0,COUNTIFS(Assignments!$C$2:$C$769,$A52,Assignments!$F$2:$F$769,"Partner",Assignments!$G$2:$G$769,"Active")=0),AND(IFERROR(INDEX(Templates!$C$3:$C$10,MATCH(Deals!$U4,Templates!$A$3:$A$10,0)),0)>0,COUNTIFS(Assignments!$C$2:$C$769,$A52,Assignments!$F$2:$F$769,"MD",Assignments!$G$2:$G$769,"Active")=0),AND(IFERROR(INDEX(Templates!$D$3:$D$10,MATCH(Deals!$U4,Templates!$A$3:$A$10,0)),0)>0,COUNTIFS(Assignments!$C$2:$C$769,$A52,Assignments!$F$2:$F$769,"Director",Assignments!$G$2:$G$769,"Active")=0),AND(IFERROR(INDEX(Templates!$E$3:$E$10,MATCH(Deals!$U4,Templates!$A$3:$A$10,0)),0)>0,COUNTIFS(Assignments!$C$2:$C$769,$A52,Assignments!$F$2:$F$769,"VP",Assignments!$G$2:$G$769,"Active")=0),AND(IFERROR(INDEX(Templates!$F$3:$F$10,MATCH(Deals!$U4,Templates!$A$3:$A$10,0)),0)>0,COUNTIFS(Assignments!$C$2:$C$769,$A52,Assignments!$F$2:$F$769,"Senior Associate",Assignments!$G$2:$G$769,"Active")=0),AND(IFERROR(INDEX(Templates!$G$3:$G$10,MATCH(Deals!$U4,Templates!$A$3:$A$10,0)),0)>0,COUNTIFS(Assignments!$C$2:$C$769,$A52,Assignments!$F$2:$F$769,"Renewable Specialist",Assignments!$G$2:$G$769,"Active")=0),AND(IFERROR(INDEX(Templates!$H$3:$H$10,MATCH(Deals!$U4,Templates!$A$3:$A$10,0)),0)>0,COUNTIFS(Assignments!$C$2:$C$769,$A52,Assignments!$F$2:$F$769,"Associate",Assignments!$G$2:$G$769,"Active")=0)))," MissingLevel","")&IF(AND($C52="Proposal",Deals!$H4=0.5)," DefaultProbability","")&IF($F52="No"," NoDates","")&IF(AND(ISNUMBER($H52),$H52>=Settings!$B$20)," Stale","")))
A53: =IF(Deals!$A5="","",Deals!$A5) | B53: =IF($A53="","",Deals!$C5) | C53: =IF($A53="","",Deals!$F5) | D53: =IF($A53="","",Deals!$H5) | E53: =IF($A53="","",Deals!$Q5) | F53: =IF($A53="","",IF(AND(Deals!$I5<>"",Deals!$J5<>""),"Yes","No")) | G53: =IF($A53="","",Deals!$Z5) | H53: =IF(OR($A53="",$G53=""),"",INT((Settings!$B$19-$G53)/7)) | I53: =IF(OR($A53="",NOT(OR(Deals!$F5="Active",Deals!$F5="Proposal"))),"",TRIM(IF($E53=0," Unstaffed","")&IF(IF(Deals!$U5="",FALSE,OR(AND(IFERROR(INDEX(Templates!$B$3:$B$10,MATCH(Deals!$U5,Templates!$A$3:$A$10,0)),0)>0,COUNTIFS(Assignments!$C$2:$C$769,$A53,Assignments!$F$2:$F$769,"Partner",Assignments!$G$2:$G$769,"Active")=0),AND(IFERROR(INDEX(Templates!$C$3:$C$10,MATCH(Deals!$U5,Templates!$A$3:$A$10,0)),0)>0,COUNTIFS(Assignments!$C$2:$C$769,$A53,Assignments!$F$2:$F$769,"MD",Assignments!$G$2:$G$769,"Active")=0),AND(IFERROR(INDEX(Templates!$D$3:$D$10,MATCH(Deals!$U5,Templates!$A$3:$A$10,0)),0)>0,COUNTIFS(Assignments!$C$2:$C$769,$A53,Assignments!$F$2:$F$769,"Director",Assignments!$G$2:$G$769,"Active")=0),AND(IFERROR(INDEX(Templates!$E$3:$E$10,MATCH(Deals!$U5,Templates!$A$3:$A$10,0)),0)>0,COUNTIFS(Assignments!$C$2:$C$769,$A53,Assignments!$F$2:$F$769,"VP",Assignments!$G$2:$G$769,"Active")=0),AND(IFERROR(INDEX(Templates!$F$3:$F$10,MATCH(Deals!$U5,Templates!$A$3:$A$10,0)),0)>0,COUNTIFS(Assignments!$C$2:$C$769,$A53,Assignments!$F$2:$F$769,"Senior Associate",Assignments!$G$2:$G$769,"Active")=0),AND(IFERROR(INDEX(Templates!$G$3:$G$10,MATCH(Deals!$U5,Templates!$A$3:$A$10,0)),0)>0,COUNTIFS(Assignments!$C$2:$C$769,$A53,Assignments!$F$2:$F$769,"Renewable Specialist",Assignments!$G$2:$G$769,"Active")=0),AND(IFERROR(INDEX(Templates!$H$3:$H$10,MATCH(Deals!$U5,Templates!$A$3:$A$10,0)),0)>0,COUNTIFS(Assignments!$C$2:$C$769,$A53,Assignments!$F$2:$F$769,"Associate",Assignments!$G$2:$G$769,"Active")=0)))," MissingLevel","")&IF(AND($C53="Proposal",Deals!$H5=0.5)," DefaultProbability","")&IF($F53="No"," NoDates","")&IF(AND(ISNUMBER($H53),$H53>=Settings!$B$20)," Stale","")))
A54: =IF(Deals!$A6="","",Deals!$A6) | B54: =IF($A54="","",Deals!$C6) | C54: =IF($A54="","",Deals!$F6) | D54: =IF($A54="","",Deals!$H6) | E54: =IF($A54="","",Deals!$Q6) | F54: =IF($A54="","",IF(AND(Deals!$I6<>"",Deals!$J6<>""),"Yes","No")) | G54: =IF($A54="","",Deals!$Z6) | H54: =IF(OR($A54="",$G54=""),"",INT((Settings!$B$19-$G54)/7)) | I54: =IF(OR($A54="",NOT(OR(Deals!$F6="Active",Deals!$F6="Proposal"))),"",TRIM(IF($E54=0," Unstaffed","")&IF(IF(Deals!$U6="",FALSE,OR(AND(IFERROR(INDEX(Templates!$B$3:$B$10,MATCH(Deals!$U6,Templates!$A$3:$A$10,0)),0)>0,COUNTIFS(Assignments!$C$2:$C$769,$A54,Assignments!$F$2:$F$769,"Partner",Assignments!$G$2:$G$769,"Active")=0),AND(IFERROR(INDEX(Templates!$C$3:$C$10,MATCH(Deals!$U6,Templates!$A$3:$A$10,0)),0)>0,COUNTIFS(Assignments!$C$2:$C$769,$A54,Assignments!$F$2:$F$769,"MD",Assignments!$G$2:$G$769,"Active")=0),AND(IFERROR(INDEX(Templates!$D$3:$D$10,MATCH(Deals!$U6,Templates!$A$3:$A$10,0)),0)>0,COUNTIFS(Assignments!$C$2:$C$769,$A54,Assignments!$F$2:$F$769,"Director",Assignments!$G$2:$G$769,"Active")=0),AND(IFERROR(INDEX(Templates!$E$3:$E$10,MATCH(Deals!$U6,Templates!$A$3:$A$10,0)),0)>0,COUNTIFS(Assignments!$C$2:$C$769,$A54,Assignments!$F$2:$F$769,"VP",Assignments!$G$2:$G$769,"Active")=0),AND(IFERROR(INDEX(Templates!$F$3:$F$10,MATCH(Deals!$U6,Templates!$A$3:$A$10,0)),0)>0,COUNTIFS(Assignments!$C$2:$C$769,$A54,Assignments!$F$2:$F$769,"Senior Associate",Assignments!$G$2:$G$769,"Active")=0),AND(IFERROR(INDEX(Templates!$G$3:$G$10,MATCH(Deals!$U6,Templates!$A$3:$A$10,0)),0)>0,COUNTIFS(Assignments!$C$2:$C$769,$A54,Assignments!$F$2:$F$769,"Renewable Specialist",Assignments!$G$2:$G$769,"Active")=0),AND(IFERROR(INDEX(Templates!$H$3:$H$10,MATCH(Deals!$U6,Templates!$A$3:$A$10,0)),0)>0,COUNTIFS(Assignments!$C$2:$C$769,$A54,Assignments!$F$2:$F$769,"Associate",Assignments!$G$2:$G$769,"Active")=0)))," MissingLevel","")&IF(AND($C54="Proposal",Deals!$H6=0.5)," DefaultProbability","")&IF($F54="No"," NoDates","")&IF(AND(ISNUMBER($H54),$H54>=Settings!$B$20)," Stale","")))
A55: =IF(Deals!$A7="","",Deals!$A7) | B55: =IF($A55="","",Deals!$C7) | C55: =IF($A55="","",Deals!$F7) | D55: =IF($A55="","",Deals!$H7) | E55: =IF($A55="","",Deals!$Q7) | F55: =IF($A55="","",IF(AND(Deals!$I7<>"",Deals!$J7<>""),"Yes","No")) | G55: =IF($A55="","",Deals!$Z7) | H55: =IF(OR($A55="",$G55=""),"",INT((Settings!$B$19-$G55)/7)) | I55: =IF(OR($A55="",NOT(OR(Deals!$F7="Active",Deals!$F7="Proposal"))),"",TRIM(IF($E55=0," Unstaffed","")&IF(IF(Deals!$U7="",FALSE,OR(AND(IFERROR(INDEX(Templates!$B$3:$B$10,MATCH(Deals!$U7,Templates!$A$3:$A$10,0)),0)>0,COUNTIFS(Assignments!$C$2:$C$769,$A55,Assignments!$F$2:$F$769,"Partner",Assignments!$G$2:$G$769,"Active")=0),AND(IFERROR(INDEX(Templates!$C$3:$C$10,MATCH(Deals!$U7,Templates!$A$3:$A$10,0)),0)>0,COUNTIFS(Assignments!$C$2:$C$769,$A55,Assignments!$F$2:$F$769,"MD",Assignments!$G$2:$G$769,"Active")=0),AND(IFERROR(INDEX(Templates!$D$3:$D$10,MATCH(Deals!$U7,Templates!$A$3:$A$10,0)),0)>0,COUNTIFS(Assignments!$C$2:$C$769,$A55,Assignments!$F$2:$F$769,"Director",Assignments!$G$2:$G$769,"Active")=0),AND(IFERROR(INDEX(Templates!$E$3:$E$10,MATCH(Deals!$U7,Templates!$A$3:$A$10,0)),0)>0,COUNTIFS(Assignments!$C$2:$C$769,$A55,Assignments!$F$2:$F$769,"VP",Assignments!$G$2:$G$769,"Active")=0),AND(IFERROR(INDEX(Templates!$F$3:$F$10,MATCH(Deals!$U7,Templates!$A$3:$A$10,0)),0)>0,COUNTIFS(Assignments!$C$2:$C$769,$A55,Assignments!$F$2:$F$769,"Senior Associate",Assignments!$G$2:$G$769,"Active")=0),AND(IFERROR(INDEX(Templates!$G$3:$G$10,MATCH(Deals!$U7,Templates!$A$3:$A$10,0)),0)>0,COUNTIFS(Assignments!$C$2:$C$769,$A55,Assignments!$F$2:$F$769,"Renewable Specialist",Assignments!$G$2:$G$769,"Active")=0),AND(IFERROR(INDEX(Templates!$H$3:$H$10,MATCH(Deals!$U7,Templates!$A$3:$A$10,0)),0)>0,COUNTIFS(Assignments!$C$2:$C$769,$A55,Assignments!$F$2:$F$769,"Associate",Assignments!$G$2:$G$769,"Active")=0)))," MissingLevel","")&IF(AND($C55="Proposal",Deals!$H7=0.5)," DefaultProbability","")&IF($F55="No"," NoDates","")&IF(AND(ISNUMBER($H55),$H55>=Settings!$B$20)," Stale","")))
A56: =IF(Deals!$A8="","",Deals!$A8) | B56: =IF($A56="","",Deals!$C8) | C56: =IF($A56="","",Deals!$F8) | D56: =IF($A56="","",Deals!$H8) | E56: =IF($A56="","",Deals!$Q8) | F56: =IF($A56="","",IF(AND(Deals!$I8<>"",Deals!$J8<>""),"Yes","No")) | G56: =IF($A56="","",Deals!$Z8) | H56: =IF(OR($A56="",$G56=""),"",INT((Settings!$B$19-$G56)/7)) | I56: =IF(OR($A56="",NOT(OR(Deals!$F8="Active",Deals!$F8="Proposal"))),"",TRIM(IF($E56=0," Unstaffed","")&IF(IF(Deals!$U8="",FALSE,OR(AND(IFERROR(INDEX(Templates!$B$3:$B$10,MATCH(Deals!$U8,Templates!$A$3:$A$10,0)),0)>0,COUNTIFS(Assignments!$C$2:$C$769,$A56,Assignments!$F$2:$F$769,"Partner",Assignments!$G$2:$G$769,"Active")=0),AND(IFERROR(INDEX(Templates!$C$3:$C$10,MATCH(Deals!$U8,Templates!$A$3:$A$10,0)),0)>0,COUNTIFS(Assignments!$C$2:$C$769,$A56,Assignments!$F$2:$F$769,"MD",Assignments!$G$2:$G$769,"Active")=0),AND(IFERROR(INDEX(Templates!$D$3:$D$10,MATCH(Deals!$U8,Templates!$A$3:$A$10,0)),0)>0,COUNTIFS(Assignments!$C$2:$C$769,$A56,Assignments!$F$2:$F$769,"Director",Assignments!$G$2:$G$769,"Active")=0),AND(IFERROR(INDEX(Templates!$E$3:$E$10,MATCH(Deals!$U8,Templates!$A$3:$A$10,0)),0)>0,COUNTIFS(Assignments!$C$2:$C$769,$A56,Assignments!$F$2:$F$769,"VP",Assignments!$G$2:$G$769,"Active")=0),AND(IFERROR(INDEX(Templates!$F$3:$F$10,MATCH(Deals!$U8,Templates!$A$3:$A$10,0)),0)>0,COUNTIFS(Assignments!$C$2:$C$769,$A56,Assignments!$F$2:$F$769,"Senior Associate",Assignments!$G$2:$G$769,"Active")=0),AND(IFERROR(INDEX(Templates!$G$3:$G$10,MATCH(Deals!$U8,Templates!$A$3:$A$10,0)),0)>0,COUNTIFS(Assignments!$C$2:$C$769,$A56,Assignments!$F$2:$F$769,"Renewable Specialist",Assignments!$G$2:$G$769,"Active")=0),AND(IFERROR(INDEX(Templates!$H$3:$H$10,MATCH(Deals!$U8,Templates!$A$3:$A$10,0)),0)>0,COUNTIFS(Assignments!$C$2:$C$769,$A56,Assignments!$F$2:$F$769,"Associate",Assignments!$G$2:$G$769,"Active")=0)))," MissingLevel","")&IF(AND($C56="Proposal",Deals!$H8=0.5)," DefaultProbability","")&IF($F56="No"," NoDates","")&IF(AND(ISNUMBER($H56),$H56>=Settings!$B$20)," Stale","")))
A57: =IF(Deals!$A9="","",Deals!$A9) | B57: =IF($A57="","",Deals!$C9) | C57: =IF($A57="","",Deals!$F9) | D57: =IF($A57="","",Deals!$H9) | E57: =IF($A57="","",Deals!$Q9) | F57: =IF($A57="","",IF(AND(Deals!$I9<>"",Deals!$J9<>""),"Yes","No")) | G57: =IF($A57="","",Deals!$Z9) | H57: =IF(OR($A57="",$G57=""),"",INT((Settings!$B$19-$G57)/7)) | I57: =IF(OR($A57="",NOT(OR(Deals!$F9="Active",Deals!$F9="Proposal"))),"",TRIM(IF($E57=0," Unstaffed","")&IF(IF(Deals!$U9="",FALSE,OR(AND(IFERROR(INDEX(Templates!$B$3:$B$10,MATCH(Deals!$U9,Templates!$A$3:$A$10,0)),0)>0,COUNTIFS(Assignments!$C$2:$C$769,$A57,Assignments!$F$2:$F$769,"Partner",Assignments!$G$2:$G$769,"Active")=0),AND(IFERROR(INDEX(Templates!$C$3:$C$10,MATCH(Deals!$U9,Templates!$A$3:$A$10,0)),0)>0,COUNTIFS(Assignments!$C$2:$C$769,$A57,Assignments!$F$2:$F$769,"MD",Assignments!$G$2:$G$769,"Active")=0),AND(IFERROR(INDEX(Templates!$D$3:$D$10,MATCH(Deals!$U9,Templates!$A$3:$A$10,0)),0)>0,COUNTIFS(Assignments!$C$2:$C$769,$A57,Assignments!$F$2:$F$769,"Director",Assignments!$G$2:$G$769,"Active")=0),AND(IFERROR(INDEX(Templates!$E$3:$E$10,MATCH(Deals!$U9,Templates!$A$3:$A$10,0)),0)>0,COUNTIFS(Assignments!$C$2:$C$769,$A57,Assignments!$F$2:$F$769,"VP",Assignments!$G$2:$G$769,"Active")=0),AND(IFERROR(INDEX(Templates!$F$3:$F$10,MATCH(Deals!$U9,Templates!$A$3:$A$10,0)),0)>0,COUNTIFS(Assignments!$C$2:$C$769,$A57,Assignments!$F$2:$F$769,"Senior Associate",Assignments!$G$2:$G$769,"Active")=0),AND(IFERROR(INDEX(Templates!$G$3:$G$10,MATCH(Deals!$U9,Templates!$A$3:$A$10,0)),0)>0,COUNTIFS(Assignments!$C$2:$C$769,$A57,Assignments!$F$2:$F$769,"Renewable Specialist",Assignments!$G$2:$G$769,"Active")=0),AND(IFERROR(INDEX(Templates!$H$3:$H$10,MATCH(Deals!$U9,Templates!$A$3:$A$10,0)),0)>0,COUNTIFS(Assignments!$C$2:$C$769,$A57,Assignments!$F$2:$F$769,"Associate",Assignments!$G$2:$G$769,"Active")=0)))," MissingLevel","")&IF(AND($C57="Proposal",Deals!$H9=0.5)," DefaultProbability","")&IF($F57="No"," NoDates","")&IF(AND(ISNUMBER($H57),$H57>=Settings!$B$20)," Stale","")))
A58: =IF(Deals!$A10="","",Deals!$A10) | B58: =IF($A58="","",Deals!$C10) | C58: =IF($A58="","",Deals!$F10) | D58: =IF($A58="","",Deals!$H10) | E58: =IF($A58="","",Deals!$Q10) | F58: =IF($A58="","",IF(AND(Deals!$I10<>"",Deals!$J10<>""),"Yes","No")) | G58: =IF($A58="","",Deals!$Z10) | H58: =IF(OR($A58="",$G58=""),"",INT((Settings!$B$19-$G58)/7)) | I58: =IF(OR($A58="",NOT(OR(Deals!$F10="Active",Deals!$F10="Proposal"))),"",TRIM(IF($E58=0," Unstaffed","")&IF(IF(Deals!$U10="",FALSE,OR(AND(IFERROR(INDEX(Templates!$B$3:$B$10,MATCH(Deals!$U10,Templates!$A$3:$A$10,0)),0)>0,COUNTIFS(Assignments!$C$2:$C$769,$A58,Assignments!$F$2:$F$769,"Partner",Assignments!$G$2:$G$769,"Active")=0),AND(IFERROR(INDEX(Templates!$C$3:$C$10,MATCH(Deals!$U10,Templates!$A$3:$A$10,0)),0)>0,COUNTIFS(Assignments!$C$2:$C$769,$A58,Assignments!$F$2:$F$769,"MD",Assignments!$G$2:$G$769,"Active")=0),AND(IFERROR(INDEX(Templates!$D$3:$D$10,MATCH(Deals!$U10,Templates!$A$3:$A$10,0)),0)>0,COUNTIFS(Assignments!$C$2:$C$769,$A58,Assignments!$F$2:$F$769,"Director",Assignments!$G$2:$G$769,"Active")=0),AND(IFERROR(INDEX(Templates!$E$3:$E$10,MATCH(Deals!$U10,Templates!$A$3:$A$10,0)),0)>0,COUNTIFS(Assignments!$C$2:$C$769,$A58,Assignments!$F$2:$F$769,"VP",Assignments!$G$2:$G$769,"Active")=0),AND(IFERROR(INDEX(Templates!$F$3:$F$10,MATCH(Deals!$U10,Templates!$A$3:$A$10,0)),0)>0,COUNTIFS(Assignments!$C$2:$C$769,$A58,Assignments!$F$2:$F$769,"Senior Associate",Assignments!$G$2:$G$769,"Active")=0),AND(IFERROR(INDEX(Templates!$G$3:$G$10,MATCH(Deals!$U10,Templates!$A$3:$A$10,0)),0)>0,COUNTIFS(Assignments!$C$2:$C$769,$A58,Assignments!$F$2:$F$769,"Renewable Specialist",Assignments!$G$2:$G$769,"Active")=0),AND(IFERROR(INDEX(Templates!$H$3:$H$10,MATCH(Deals!$U10,Templates!$A$3:$A$10,0)),0)>0,COUNTIFS(Assignments!$C$2:$C$769,$A58,Assignments!$F$2:$F$769,"Associate",Assignments!$G$2:$G$769,"Active")=0)))," MissingLevel","")&IF(AND($C58="Proposal",Deals!$H10=0.5)," DefaultProbability","")&IF($F58="No"," NoDates","")&IF(AND(ISNUMBER($H58),$H58>=Settings!$B$20)," Stale","")))
A59: =IF(Deals!$A11="","",Deals!$A11) | B59: =IF($A59="","",Deals!$C11) | C59: =IF($A59="","",Deals!$F11) | D59: =IF($A59="","",Deals!$H11) | E59: =IF($A59="","",Deals!$Q11) | F59: =IF($A59="","",IF(AND(Deals!$I11<>"",Deals!$J11<>""),"Yes","No")) | G59: =IF($A59="","",Deals!$Z11) | H59: =IF(OR($A59="",$G59=""),"",INT((Settings!$B$19-$G59)/7)) | I59: =IF(OR($A59="",NOT(OR(Deals!$F11="Active",Deals!$F11="Proposal"))),"",TRIM(IF($E59=0," Unstaffed","")&IF(IF(Deals!$U11="",FALSE,OR(AND(IFERROR(INDEX(Templates!$B$3:$B$10,MATCH(Deals!$U11,Templates!$A$3:$A$10,0)),0)>0,COUNTIFS(Assignments!$C$2:$C$769,$A59,Assignments!$F$2:$F$769,"Partner",Assignments!$G$2:$G$769,"Active")=0),AND(IFERROR(INDEX(Templates!$C$3:$C$10,MATCH(Deals!$U11,Templates!$A$3:$A$10,0)),0)>0,COUNTIFS(Assignments!$C$2:$C$769,$A59,Assignments!$F$2:$F$769,"MD",Assignments!$G$2:$G$769,"Active")=0),AND(IFERROR(INDEX(Templates!$D$3:$D$10,MATCH(Deals!$U11,Templates!$A$3:$A$10,0)),0)>0,COUNTIFS(Assignments!$C$2:$C$769,$A59,Assignments!$F$2:$F$769,"Director",Assignments!$G$2:$G$769,"Active")=0),AND(IFERROR(INDEX(Templates!$E$3:$E$10,MATCH(Deals!$U11,Templates!$A$3:$A$10,0)),0)>0,COUNTIFS(Assignments!$C$2:$C$769,$A59,Assignments!$F$2:$F$769,"VP",Assignments!$G$2:$G$769,"Active")=0),AND(IFERROR(INDEX(Templates!$F$3:$F$10,MATCH(Deals!$U11,Templates!$A$3:$A$10,0)),0)>0,COUNTIFS(Assignments!$C$2:$C$769,$A59,Assignments!$F$2:$F$769,"Senior Associate",Assignments!$G$2:$G$769,"Active")=0),AND(IFERROR(INDEX(Templates!$G$3:$G$10,MATCH(Deals!$U11,Templates!$A$3:$A$10,0)),0)>0,COUNTIFS(Assignments!$C$2:$C$769,$A59,Assignments!$F$2:$F$769,"Renewable Specialist",Assignments!$G$2:$G$769,"Active")=0),AND(IFERROR(INDEX(Templates!$H$3:$H$10,MATCH(Deals!$U11,Templates!$A$3:$A$10,0)),0)>0,COUNTIFS(Assignments!$C$2:$C$769,$A59,Assignments!$F$2:$F$769,"Associate",Assignments!$G$2:$G$769,"Active")=0)))," MissingLevel","")&IF(AND($C59="Proposal",Deals!$H11=0.5)," DefaultProbability","")&IF($F59="No"," NoDates","")&IF(AND(ISNUMBER($H59),$H59>=Settings!$B$20)," Stale","")))
A60: =IF(Deals!$A12="","",Deals!$A12) | B60: =IF($A60="","",Deals!$C12) | C60: =IF($A60="","",Deals!$F12) | D60: =IF($A60="","",Deals!$H12) | E60: =IF($A60="","",Deals!$Q12) | F60: =IF($A60="","",IF(AND(Deals!$I12<>"",Deals!$J12<>""),"Yes","No")) | G60: =IF($A60="","",Deals!$Z12) | H60: =IF(OR($A60="",$G60=""),"",INT((Settings!$B$19-$G60)/7)) | I60: =IF(OR($A60="",NOT(OR(Deals!$F12="Active",Deals!$F12="Proposal"))),"",TRIM(IF($E60=0," Unstaffed","")&IF(IF(Deals!$U12="",FALSE,OR(AND(IFERROR(INDEX(Templates!$B$3:$B$10,MATCH(Deals!$U12,Templates!$A$3:$A$10,0)),0)>0,COUNTIFS(Assignments!$C$2:$C$769,$A60,Assignments!$F$2:$F$769,"Partner",Assignments!$G$2:$G$769,"Active")=0),AND(IFERROR(INDEX(Templates!$C$3:$C$10,MATCH(Deals!$U12,Templates!$A$3:$A$10,0)),0)>0,COUNTIFS(Assignments!$C$2:$C$769,$A60,Assignments!$F$2:$F$769,"MD",Assignments!$G$2:$G$769,"Active")=0),AND(IFERROR(INDEX(Templates!$D$3:$D$10,MATCH(Deals!$U12,Templates!$A$3:$A$10,0)),0)>0,COUNTIFS(Assignments!$C$2:$C$769,$A60,Assignments!$F$2:$F$769,"Director",Assignments!$G$2:$G$769,"Active")=0),AND(IFERROR(INDEX(Templates!$E$3:$E$10,MATCH(Deals!$U12,Templates!$A$3:$A$10,0)),0)>0,COUNTIFS(Assignments!$C$2:$C$769,$A60,Assignments!$F$2:$F$769,"VP",Assignments!$G$2:$G$769,"Active")=0),AND(IFERROR(INDEX(Templates!$F$3:$F$10,MATCH(Deals!$U12,Templates!$A$3:$A$10,0)),0)>0,COUNTIFS(Assignments!$C$2:$C$769,$A60,Assignments!$F$2:$F$769,"Senior Associate",Assignments!$G$2:$G$769,"Active")=0),AND(IFERROR(INDEX(Templates!$G$3:$G$10,MATCH(Deals!$U12,Templates!$A$3:$A$10,0)),0)>0,COUNTIFS(Assignments!$C$2:$C$769,$A60,Assignments!$F$2:$F$769,"Renewable Specialist",Assignments!$G$2:$G$769,"Active")=0),AND(IFERROR(INDEX(Templates!$H$3:$H$10,MATCH(Deals!$U12,Templates!$A$3:$A$10,0)),0)>0,COUNTIFS(Assignments!$C$2:$C$769,$A60,Assignments!$F$2:$F$769,"Associate",Assignments!$G$2:$G$769,"Active")=0)))," MissingLevel","")&IF(AND($C60="Proposal",Deals!$H12=0.5)," DefaultProbability","")&IF($F60="No"," NoDates","")&IF(AND(ISNUMBER($H60),$H60>=Settings!$B$20)," Stale","")))
A61: =IF(Deals!$A13="","",Deals!$A13) | B61: =IF($A61="","",Deals!$C13) | C61: =IF($A61="","",Deals!$F13) | D61: =IF($A61="","",Deals!$H13) | E61: =IF($A61="","",Deals!$Q13) | F61: =IF($A61="","",IF(AND(Deals!$I13<>"",Deals!$J13<>""),"Yes","No")) | G61: =IF($A61="","",Deals!$Z13) | H61: =IF(OR($A61="",$G61=""),"",INT((Settings!$B$19-$G61)/7)) | I61: =IF(OR($A61="",NOT(OR(Deals!$F13="Active",Deals!$F13="Proposal"))),"",TRIM(IF($E61=0," Unstaffed","")&IF(IF(Deals!$U13="",FALSE,OR(AND(IFERROR(INDEX(Templates!$B$3:$B$10,MATCH(Deals!$U13,Templates!$A$3:$A$10,0)),0)>0,COUNTIFS(Assignments!$C$2:$C$769,$A61,Assignments!$F$2:$F$769,"Partner",Assignments!$G$2:$G$769,"Active")=0),AND(IFERROR(INDEX(Templates!$C$3:$C$10,MATCH(Deals!$U13,Templates!$A$3:$A$10,0)),0)>0,COUNTIFS(Assignments!$C$2:$C$769,$A61,Assignments!$F$2:$F$769,"MD",Assignments!$G$2:$G$769,"Active")=0),AND(IFERROR(INDEX(Templates!$D$3:$D$10,MATCH(Deals!$U13,Templates!$A$3:$A$10,0)),0)>0,COUNTIFS(Assignments!$C$2:$C$769,$A61,Assignments!$F$2:$F$769,"Director",Assignments!$G$2:$G$769,"Active")=0),AND(IFERROR(INDEX(Templates!$E$3:$E$10,MATCH(Deals!$U13,Templates!$A$3:$A$10,0)),0)>0,COUNTIFS(Assignments!$C$2:$C$769,$A61,Assignments!$F$2:$F$769,"VP",Assignments!$G$2:$G$769,"Active")=0),AND(IFERROR(INDEX(Templates!$F$3:$F$10,MATCH(Deals!$U13,Templates!$A$3:$A$10,0)),0)>0,COUNTIFS(Assignments!$C$2:$C$769,$A61,Assignments!$F$2:$F$769,"Senior Associate",Assignments!$G$2:$G$769,"Active")=0),AND(IFERROR(INDEX(Templates!$G$3:$G$10,MATCH(Deals!$U13,Templates!$A$3:$A$10,0)),0)>0,COUNTIFS(Assignments!$C$2:$C$769,$A61,Assignments!$F$2:$F$769,"Renewable Specialist",Assignments!$G$2:$G$769,"Active")=0),AND(IFERROR(INDEX(Templates!$H$3:$H$10,MATCH(Deals!$U13,Templates!$A$3:$A$10,0)),0)>0,COUNTIFS(Assignments!$C$2:$C$769,$A61,Assignments!$F$2:$F$769,"Associate",Assignments!$G$2:$G$769,"Active")=0)))," MissingLevel","")&IF(AND($C61="Proposal",Deals!$H13=0.5)," DefaultProbability","")&IF($F61="No"," NoDates","")&IF(AND(ISNUMBER($H61),$H61>=Settings!$B$20)," Stale","")))
... A403: =IF(Deals!$A355="","",Deals!$A355) | B403: =IF($A403="","",Deals!$C355) | C403: =IF($A403="","",Deals!$F355) | D403: =IF($A403="","",Deals!$H355) | E403: =IF($A403="","",Deals!$Q355) | F403: =IF($A403="","",IF(AND(Deals!$I355<>"",Deals!$J355<>""),"Yes","No")) | G403: =IF($A403="","",Deals!$Z355) | H403: =IF(OR($A403="",$G403=""),"",INT((Settings!$B$19-$G403)/7)) | I403: =IF(OR($A403="",NOT(OR(Deals!$F355="Active",Deals!$F355="Proposal"))),"",TRIM(IF($E403=0," Unstaffed","")&IF(IF(Deals!$U355="",FALSE,OR(AND(IFERROR(INDEX(Templates!$B$3:$B$10,MATCH(Deals!$U355,Templates!$A$3:$A$10,0)),0)>0,COUNTIFS(Assignments!$C$2:$C$769,$A403,Assignments!$F$2:$F$769,"Partner",Assignments!$G$2:$G$769,"Active")=0),AND(IFERROR(INDEX(Templates!$C$3:$C$10,MATCH(Deals!$U355,Templates!$A$3:$A$10,0)),0)>0,COUNTIFS(Assignments!$C$2:$C$769,$A403,Assignments!$F$2:$F$769,"MD",Assignments!$G$2:$G$769,"Active")=0),AND(IFERROR(INDEX(Templates!$D$3:$D$10,MATCH(Deals!$U355,Templates!$A$3:$A$10,0)),0)>0,COUNTIFS(Assignments!$C$2:$C$769,$A403,Assignments!$F$2:$F$769,"Director",Assignments!$G$2:$G$769,"Active")=0),AND(IFERROR(INDEX(Templates!$E$3:$E$10,MATCH(Deals!$U355,Templates!$A$3:$A$10,0)),0)>0,COUNTIFS(Assignments!$C$2:$C$769,$A403,Assignments!$F$2:$F$769,"VP",Assignments!$G$2:$G$769,"Active")=0),AND(IFERROR(INDEX(Templates!$F$3:$F$10,MATCH(Deals!$U355,Templates!$A$3:$A$10,0)),0)>0,COUNTIFS(Assignments!$C$2:$C$769,$A403,Assignments!$F$2:$F$769,"Senior Associate",Assignments!$G$2:$G$769,"Active")=0),AND(IFERROR(INDEX(Templates!$G$3:$G$10,MATCH(Deals!$U355,Templates!$A$3:$A$10,0)),0)>0,COUNTIFS(Assignments!$C$2:$C$769,$A403,Assignments!$F$2:$F$769,"Renewable Specialist",Assignments!$G$2:$G$769,"Active")=0),AND(IFERROR(INDEX(Templates!$H$3:$H$10,MATCH(Deals!$U355,Templates!$A$3:$A$10,0)),0)>0,COUNTIFS(Assignments!$C$2:$C$769,$A403,Assignments!$F$2:$F$769,"Associate",Assignments!$G$2:$G$769,"Active")=0)))," MissingLevel","")&IF(AND($C403="Proposal",Deals!$H355=0.5)," DefaultProbability","")&IF($F403="No"," NoDates","")&IF(AND(ISNUMBER($H403),$H403>=Settings!$B$20)," Stale","")))

Sheet Scenario
A1: Scenario analysis - what-if, without touching the live plan
A2: This mirrors Capacity but applies the SCENARIO overrides you set on the Deals tab (the violet columns: Scenario probability / start / end). Leave them blank and this equals Live exactly (every Change below is 0). Fill an override - e.g. bump three proposals to 100% - to see who would blow up. The live Capacity and Check-in tabs are never affected.
A4: 1) Impact summary - who changes under the scenario (peak over the next 4 weeks)
A5: Person | B5: Cap hrs/wk | C5: Live peak | D5: Scenario peak | E5: Change | F5: Scenario util | G5: Flag
A6: =IF(Roster!$A2="","",Roster!$A2) | B6: =IF($A6="","",Roster!$D2) | C6: =IF($A6="","",MAX(Capacity!$C5:$F5)) | D6: =IF($A6="","",MAX($C48:$F48)) | E6: =IF($A6="","",$D6-$C6) | F6: =IF(OR($A6="",$B6=0),"",$D6/$B6) | G6: =IF($B6=0,"",IF(AND($D6>$B6,$C6<=$B6),"NEWLY OVER",IF($D6>$B6,"over",IF(AND($C6>$B6,$D6<=$B6),"eased",""))))
A7: =IF(Roster!$A3="","",Roster!$A3) | B7: =IF($A7="","",Roster!$D3) | C7: =IF($A7="","",MAX(Capacity!$C6:$F6)) | D7: =IF($A7="","",MAX($C49:$F49)) | E7: =IF($A7="","",$D7-$C7) | F7: =IF(OR($A7="",$B7=0),"",$D7/$B7) | G7: =IF($B7=0,"",IF(AND($D7>$B7,$C7<=$B7),"NEWLY OVER",IF($D7>$B7,"over",IF(AND($C7>$B7,$D7<=$B7),"eased",""))))
A8: =IF(Roster!$A4="","",Roster!$A4) | B8: =IF($A8="","",Roster!$D4) | C8: =IF($A8="","",MAX(Capacity!$C7:$F7)) | D8: =IF($A8="","",MAX($C50:$F50)) | E8: =IF($A8="","",$D8-$C8) | F8: =IF(OR($A8="",$B8=0),"",$D8/$B8) | G8: =IF($B8=0,"",IF(AND($D8>$B8,$C8<=$B8),"NEWLY OVER",IF($D8>$B8,"over",IF(AND($C8>$B8,$D8<=$B8),"eased",""))))
A9: =IF(Roster!$A5="","",Roster!$A5) | B9: =IF($A9="","",Roster!$D5) | C9: =IF($A9="","",MAX(Capacity!$C8:$F8)) | D9: =IF($A9="","",MAX($C51:$F51)) | E9: =IF($A9="","",$D9-$C9) | F9: =IF(OR($A9="",$B9=0),"",$D9/$B9) | G9: =IF($B9=0,"",IF(AND($D9>$B9,$C9<=$B9),"NEWLY OVER",IF($D9>$B9,"over",IF(AND($C9>$B9,$D9<=$B9),"eased",""))))
A10: =IF(Roster!$A6="","",Roster!$A6) | B10: =IF($A10="","",Roster!$D6) | C10: =IF($A10="","",MAX(Capacity!$C9:$F9)) | D10: =IF($A10="","",MAX($C52:$F52)) | E10: =IF($A10="","",$D10-$C10) | F10: =IF(OR($A10="",$B10=0),"",$D10/$B10) | G10: =IF($B10=0,"",IF(AND($D10>$B10,$C10<=$B10),"NEWLY OVER",IF($D10>$B10,"over",IF(AND($C10>$B10,$D10<=$B10),"eased",""))))
A11: =IF(Roster!$A7="","",Roster!$A7) | B11: =IF($A11="","",Roster!$D7) | C11: =IF($A11="","",MAX(Capacity!$C10:$F10)) | D11: =IF($A11="","",MAX($C53:$F53)) | E11: =IF($A11="","",$D11-$C11) | F11: =IF(OR($A11="",$B11=0),"",$D11/$B11) | G11: =IF($B11=0,"",IF(AND($D11>$B11,$C11<=$B11),"NEWLY OVER",IF($D11>$B11,"over",IF(AND($C11>$B11,$D11<=$B11),"eased",""))))
A12: =IF(Roster!$A8="","",Roster!$A8) | B12: =IF($A12="","",Roster!$D8) | C12: =IF($A12="","",MAX(Capacity!$C11:$F11)) | D12: =IF($A12="","",MAX($C54:$F54)) | E12: =IF($A12="","",$D12-$C12) | F12: =IF(OR($A12="",$B12=0),"",$D12/$B12) | G12: =IF($B12=0,"",IF(AND($D12>$B12,$C12<=$B12),"NEWLY OVER",IF($D12>$B12,"over",IF(AND($C12>$B12,$D12<=$B12),"eased",""))))
A13: =IF(Roster!$A9="","",Roster!$A9) | B13: =IF($A13="","",Roster!$D9) | C13: =IF($A13="","",MAX(Capacity!$C12:$F12)) | D13: =IF($A13="","",MAX($C55:$F55)) | E13: =IF($A13="","",$D13-$C13) | F13: =IF(OR($A13="",$B13=0),"",$D13/$B13) | G13: =IF($B13=0,"",IF(AND($D13>$B13,$C13<=$B13),"NEWLY OVER",IF($D13>$B13,"over",IF(AND($C13>$B13,$D13<=$B13),"eased",""))))
A14: =IF(Roster!$A10="","",Roster!$A10) | B14: =IF($A14="","",Roster!$D10) | C14: =IF($A14="","",MAX(Capacity!$C13:$F13)) | D14: =IF($A14="","",MAX($C56:$F56)) | E14: =IF($A14="","",$D14-$C14) | F14: =IF(OR($A14="",$B14=0),"",$D14/$B14) | G14: =IF($B14=0,"",IF(AND($D14>$B14,$C14<=$B14),"NEWLY OVER",IF($D14>$B14,"over",IF(AND($C14>$B14,$D14<=$B14),"eased",""))))
A15: =IF(Roster!$A11="","",Roster!$A11) | B15: =IF($A15="","",Roster!$D11) | C15: =IF($A15="","",MAX(Capacity!$C14:$F14)) | D15: =IF($A15="","",MAX($C57:$F57)) | E15: =IF($A15="","",$D15-$C15) | F15: =IF(OR($A15="",$B15=0),"",$D15/$B15) | G15: =IF($B15=0,"",IF(AND($D15>$B15,$C15<=$B15),"NEWLY OVER",IF($D15>$B15,"over",IF(AND($C15>$B15,$D15<=$B15),"eased",""))))
A16: =IF(Roster!$A12="","",Roster!$A12) | B16: =IF($A16="","",Roster!$D12) | C16: =IF($A16="","",MAX(Capacity!$C15:$F15)) | D16: =IF($A16="","",MAX($C58:$F58)) | E16: =IF($A16="","",$D16-$C16) | F16: =IF(OR($A16="",$B16=0),"",$D16/$B16) | G16: =IF($B16=0,"",IF(AND($D16>$B16,$C16<=$B16),"NEWLY OVER",IF($D16>$B16,"over",IF(AND($C16>$B16,$D16<=$B16),"eased",""))))
A17: =IF(Roster!$A13="","",Roster!$A13) | B17: =IF($A17="","",Roster!$D13) | C17: =IF($A17="","",MAX(Capacity!$C16:$F16)) | D17: =IF($A17="","",MAX($C59:$F59)) | E17: =IF($A17="","",$D17-$C17) | F17: =IF(OR($A17="",$B17=0),"",$D17/$B17) | G17: =IF($B17=0,"",IF(AND($D17>$B17,$C17<=$B17),"NEWLY OVER",IF($D17>$B17,"over",IF(AND($C17>$B17,$D17<=$B17),"eased",""))))
... A44: =IF(Roster!$A40="","",Roster!$A40) | B44: =IF($A44="","",Roster!$D40) | C44: =IF($A44="","",MAX(Capacity!$C43:$F43)) | D44: =IF($A44="","",MAX($C86:$F86)) | E44: =IF($A44="","",$D44-$C44) | F44: =IF(OR($A44="",$B44=0),"",$D44/$B44) | G44: =IF($B44=0,"",IF(AND($D44>$B44,$C44<=$B44),"NEWLY OVER",IF($D44>$B44,"over",IF(AND($C44>$B44,$D44<=$B44),"eased",""))))
A46: 2) Scenario capacity heatmap (person x week, with overrides applied)
A47: Person | B47: Cap | C47: =Settings!$B$3 | D47: =C47+7 | E47: =D47+7 | F47: =E47+7 | G47: =F47+7 | H47: =G47+7 | I47: =H47+7 | J47: =I47+7 | K47: =J47+7 | ... AB47: =AA47+7
A48: =IF(Roster!$A2="","",Roster!$A2) | B48: =IF($A48="","",IFERROR(INDEX(Roster!$D$2:$D$40,MATCH($A48,Roster!$A$2:$A$40,0)),"")) | C48: =IF($A48="","",SUMIFS(Assignments!$AK$2:$AK$769,Assignments!$A$2:$A$769,$A48,Assignments!$G$2:$G$769,"Active",Assignments!$AI$2:$AI$769,"<="&C$47,Assignments!$AJ$2:$AJ$769,">="&C$47)+SUMIFS(Assignments!$AN$2:$AN$769,Assignments!$A$2:$A$769,$A48,Assignments!$G$2:$G$769,"Active",Assignments!$AL$2:$AL$769,"<="&C$47,Assignments!$AM$2:$AM$769,">="&C$47)) | D48: =IF($A48="","",SUMIFS(Assignments!$AK$2:$AK$769,Assignments!$A$2:$A$769,$A48,Assignments!$G$2:$G$769,"Active",Assignments!$AI$2:$AI$769,"<="&D$47,Assignments!$AJ$2:$AJ$769,">="&D$47)+SUMIFS(Assignments!$AN$2:$AN$769,Assignments!$A$2:$A$769,$A48,Assignments!$G$2:$G$769,"Active",Assignments!$AL$2:$AL$769,"<="&D$47,Assignments!$AM$2:$AM$769,">="&D$47)) | E48: =IF($A48="","",SUMIFS(Assignments!$AK$2:$AK$769,Assignments!$A$2:$A$769,$A48,Assignments!$G$2:$G$769,"Active",Assignments!$AI$2:$AI$769,"<="&E$47,Assignments!$AJ$2:$AJ$769,">="&E$47)+SUMIFS(Assignments!$AN$2:$AN$769,Assignments!$A$2:$A$769,$A48,Assignments!$G$2:$G$769,"Active",Assignments!$AL$2:$AL$769,"<="&E$47,Assignments!$AM$2:$AM$769,">="&E$47)) | F48: =IF($A48="","",SUMIFS(Assignments!$AK$2:$AK$769,Assignments!$A$2:$A$769,$A48,Assignments!$G$2:$G$769,"Active",Assignments!$AI$2:$AI$769,"<="&F$47,Assignments!$AJ$2:$AJ$769,">="&F$47)+SUMIFS(Assignments!$AN$2:$AN$769,Assignments!$A$2:$A$769,$A48,Assignments!$G$2:$G$769,"Active",Assignments!$AL$2:$AL$769,"<="&F$47,Assignments!$AM$2:$AM$769,">="&F$47)) | G48: =IF($A48="","",SUMIFS(Assignments!$AK$2:$AK$769,Assignments!$A$2:$A$769,$A48,Assignments!$G$2:$G$769,"Active",Assignments!$AI$2:$AI$769,"<="&G$47,Assignments!$AJ$2:$AJ$769,">="&G$47)+SUMIFS(Assignments!$AN$2:$AN$769,Assignments!$A$2:$A$769,$A48,Assignments!$G$2:$G$769,"Active",Assignments!$AL$2:$AL$769,"<="&G$47,Assignments!$AM$2:$AM$769,">="&G$47)) | H48: =IF($A48="","",SUMIFS(Assignments!$AK$2:$AK$769,Assignments!$A$2:$A$769,$A48,Assignments!$G$2:$G$769,"Active",Assignments!$AI$2:$AI$769,"<="&H$47,Assignments!$AJ$2:$AJ$769,">="&H$47)+SUMIFS(Assignments!$AN$2:$AN$769,Assignments!$A$2:$A$769,$A48,Assignments!$G$2:$G$769,"Active",Assignments!$AL$2:$AL$769,"<="&H$47,Assignments!$AM$2:$AM$769,">="&H$47)) | I48: =IF($A48="","",SUMIFS(Assignments!$AK$2:$AK$769,Assignments!$A$2:$A$769,$A48,Assignments!$G$2:$G$769,"Active",Assignments!$AI$2:$AI$769,"<="&I$47,Assignments!$AJ$2:$AJ$769,">="&I$47)+SUMIFS(Assignments!$AN$2:$AN$769,Assignments!$A$2:$A$769,$A48,Assignments!$G$2:$G$769,"Active",Assignments!$AL$2:$AL$769,"<="&I$47,Assignments!$AM$2:$AM$769,">="&I$47)) | J48: =IF($A48="","",SUMIFS(Assignments!$AK$2:$AK$769,Assignments!$A$2:$A$769,$A48,Assignments!$G$2:$G$769,"Active",Assignments!$AI$2:$AI$769,"<="&J$47,Assignments!$AJ$2:$AJ$769,">="&J$47)+SUMIFS(Assignments!$AN$2:$AN$769,Assignments!$A$2:$A$769,$A48,Assignments!$G$2:$G$769,"Active",Assignments!$AL$2:$AL$769,"<="&J$47,Assignments!$AM$2:$AM$769,">="&J$47)) | ... AB48: =IF($A48="","",SUMIFS(Assignments!$AK$2:$AK$769,Assignments!$A$2:$A$769,$A48,Assignments!$G$2:$G$769,"Active",Assignments!$AI$2:$AI$769,"<="&AB$47,Assignments!$AJ$2:$AJ$769,">="&AB$47)+SUMIFS(Assignments!$AN$2:$AN$769,Assignments!$A$2:$A$769,$A48,Assignments!$G$2:$G$769,"Active",Assignments!$AL$2:$AL$769,"<="&AB$47,Assignments!$AM$2:$AM$769,">="&AB$47))
A49: =IF(Roster!$A3="","",Roster!$A3) | B49: =IF($A49="","",IFERROR(INDEX(Roster!$D$2:$D$40,MATCH($A49,Roster!$A$2:$A$40,0)),"")) | C49: =IF($A49="","",SUMIFS(Assignments!$AK$2:$AK$769,Assignments!$A$2:$A$769,$A49,Assignments!$G$2:$G$769,"Active",Assignments!$AI$2:$AI$769,"<="&C$47,Assignments!$AJ$2:$AJ$769,">="&C$47)+SUMIFS(Assignments!$AN$2:$AN$769,Assignments!$A$2:$A$769,$A49,Assignments!$G$2:$G$769,"Active",Assignments!$AL$2:$AL$769,"<="&C$47,Assignments!$AM$2:$AM$769,">="&C$47)) | D49: =IF($A49="","",SUMIFS(Assignments!$AK$2:$AK$769,Assignments!$A$2:$A$769,$A49,Assignments!$G$2:$G$769,"Active",Assignments!$AI$2:$AI$769,"<="&D$47,Assignments!$AJ$2:$AJ$769,">="&D$47)+SUMIFS(Assignments!$AN$2:$AN$769,Assignments!$A$2:$A$769,$A49,Assignments!$G$2:$G$769,"Active",Assignments!$AL$2:$AL$769,"<="&D$47,Assignments!$AM$2:$AM$769,">="&D$47)) | E49: =IF($A49="","",SUMIFS(Assignments!$AK$2:$AK$769,Assignments!$A$2:$A$769,$A49,Assignments!$G$2:$G$769,"Active",Assignments!$AI$2:$AI$769,"<="&E$47,Assignments!$AJ$2:$AJ$769,">="&E$47)+SUMIFS(Assignments!$AN$2:$AN$769,Assignments!$A$2:$A$769,$A49,Assignments!$G$2:$G$769,"Active",Assignments!$AL$2:$AL$769,"<="&E$47,Assignments!$AM$2:$AM$769,">="&E$47)) | F49: =IF($A49="","",SUMIFS(Assignments!$AK$2:$AK$769,Assignments!$A$2:$A$769,$A49,Assignments!$G$2:$G$769,"Active",Assignments!$AI$2:$AI$769,"<="&F$47,Assignments!$AJ$2:$AJ$769,">="&F$47)+SUMIFS(Assignments!$AN$2:$AN$769,Assignments!$A$2:$A$769,$A49,Assignments!$G$2:$G$769,"Active",Assignments!$AL$2:$AL$769,"<="&F$47,Assignments!$AM$2:$AM$769,">="&F$47)) | G49: =IF($A49="","",SUMIFS(Assignments!$AK$2:$AK$769,Assignments!$A$2:$A$769,$A49,Assignments!$G$2:$G$769,"Active",Assignments!$AI$2:$AI$769,"<="&G$47,Assignments!$AJ$2:$AJ$769,">="&G$47)+SUMIFS(Assignments!$AN$2:$AN$769,Assignments!$A$2:$A$769,$A49,Assignments!$G$2:$G$769,"Active",Assignments!$AL$2:$AL$769,"<="&G$47,Assignments!$AM$2:$AM$769,">="&G$47)) | H49: =IF($A49="","",SUMIFS(Assignments!$AK$2:$AK$769,Assignments!$A$2:$A$769,$A49,Assignments!$G$2:$G$769,"Active",Assignments!$AI$2:$AI$769,"<="&H$47,Assignments!$AJ$2:$AJ$769,">="&H$47)+SUMIFS(Assignments!$AN$2:$AN$769,Assignments!$A$2:$A$769,$A49,Assignments!$G$2:$G$769,"Active",Assignments!$AL$2:$AL$769,"<="&H$47,Assignments!$AM$2:$AM$769,">="&H$47)) | I49: =IF($A49="","",SUMIFS(Assignments!$AK$2:$AK$769,Assignments!$A$2:$A$769,$A49,Assignments!$G$2:$G$769,"Active",Assignments!$AI$2:$AI$769,"<="&I$47,Assignments!$AJ$2:$AJ$769,">="&I$47)+SUMIFS(Assignments!$AN$2:$AN$769,Assignments!$A$2:$A$769,$A49,Assignments!$G$2:$G$769,"Active",Assignments!$AL$2:$AL$769,"<="&I$47,Assignments!$AM$2:$AM$769,">="&I$47)) | J49: =IF($A49="","",SUMIFS(Assignments!$AK$2:$AK$769,Assignments!$A$2:$A$769,$A49,Assignments!$G$2:$G$769,"Active",Assignments!$AI$2:$AI$769,"<="&J$47,Assignments!$AJ$2:$AJ$769,">="&J$47)+SUMIFS(Assignments!$AN$2:$AN$769,Assignments!$A$2:$A$769,$A49,Assignments!$G$2:$G$769,"Active",Assignments!$AL$2:$AL$769,"<="&J$47,Assignments!$AM$2:$AM$769,">="&J$47)) | ... AB49: =IF($A49="","",SUMIFS(Assignments!$AK$2:$AK$769,Assignments!$A$2:$A$769,$A49,Assignments!$G$2:$G$769,"Active",Assignments!$AI$2:$AI$769,"<="&AB$47,Assignments!$AJ$2:$AJ$769,">="&AB$47)+SUMIFS(Assignments!$AN$2:$AN$769,Assignments!$A$2:$A$769,$A49,Assignments!$G$2:$G$769,"Active",Assignments!$AL$2:$AL$769,"<="&AB$47,Assignments!$AM$2:$AM$769,">="&AB$47))
A50: =IF(Roster!$A4="","",Roster!$A4) | B50: =IF($A50="","",IFERROR(INDEX(Roster!$D$2:$D$40,MATCH($A50,Roster!$A$2:$A$40,0)),"")) | C50: =IF($A50="","",SUMIFS(Assignments!$AK$2:$AK$769,Assignments!$A$2:$A$769,$A50,Assignments!$G$2:$G$769,"Active",Assignments!$AI$2:$AI$769,"<="&C$47,Assignments!$AJ$2:$AJ$769,">="&C$47)+SUMIFS(Assignments!$AN$2:$AN$769,Assignments!$A$2:$A$769,$A50,Assignments!$G$2:$G$769,"Active",Assignments!$AL$2:$AL$769,"<="&C$47,Assignments!$AM$2:$AM$769,">="&C$47)) | D50: =IF($A50="","",SUMIFS(Assignments!$AK$2:$AK$769,Assignments!$A$2:$A$769,$A50,Assignments!$G$2:$G$769,"Active",Assignments!$AI$2:$AI$769,"<="&D$47,Assignments!$AJ$2:$AJ$769,">="&D$47)+SUMIFS(Assignments!$AN$2:$AN$769,Assignments!$A$2:$A$769,$A50,Assignments!$G$2:$G$769,"Active",Assignments!$AL$2:$AL$769,"<="&D$47,Assignments!$AM$2:$AM$769,">="&D$47)) | E50: =IF($A50="","",SUMIFS(Assignments!$AK$2:$AK$769,Assignments!$A$2:$A$769,$A50,Assignments!$G$2:$G$769,"Active",Assignments!$AI$2:$AI$769,"<="&E$47,Assignments!$AJ$2:$AJ$769,">="&E$47)+SUMIFS(Assignments!$AN$2:$AN$769,Assignments!$A$2:$A$769,$A50,Assignments!$G$2:$G$769,"Active",Assignments!$AL$2:$AL$769,"<="&E$47,Assignments!$AM$2:$AM$769,">="&E$47)) | F50: =IF($A50="","",SUMIFS(Assignments!$AK$2:$AK$769,Assignments!$A$2:$A$769,$A50,Assignments!$G$2:$G$769,"Active",Assignments!$AI$2:$AI$769,"<="&F$47,Assignments!$AJ$2:$AJ$769,">="&F$47)+SUMIFS(Assignments!$AN$2:$AN$769,Assignments!$A$2:$A$769,$A50,Assignments!$G$2:$G$769,"Active",Assignments!$AL$2:$AL$769,"<="&F$47,Assignments!$AM$2:$AM$769,">="&F$47)) | G50: =IF($A50="","",SUMIFS(Assignments!$AK$2:$AK$769,Assignments!$A$2:$A$769,$A50,Assignments!$G$2:$G$769,"Active",Assignments!$AI$2:$AI$769,"<="&G$47,Assignments!$AJ$2:$AJ$769,">="&G$47)+SUMIFS(Assignments!$AN$2:$AN$769,Assignments!$A$2:$A$769,$A50,Assignments!$G$2:$G$769,"Active",Assignments!$AL$2:$AL$769,"<="&G$47,Assignments!$AM$2:$AM$769,">="&G$47)) | H50: =IF($A50="","",SUMIFS(Assignments!$AK$2:$AK$769,Assignments!$A$2:$A$769,$A50,Assignments!$G$2:$G$769,"Active",Assignments!$AI$2:$AI$769,"<="&H$47,Assignments!$AJ$2:$AJ$769,">="&H$47)+SUMIFS(Assignments!$AN$2:$AN$769,Assignments!$A$2:$A$769,$A50,Assignments!$G$2:$G$769,"Active",Assignments!$AL$2:$AL$769,"<="&H$47,Assignments!$AM$2:$AM$769,">="&H$47)) | I50: =IF($A50="","",SUMIFS(Assignments!$AK$2:$AK$769,Assignments!$A$2:$A$769,$A50,Assignments!$G$2:$G$769,"Active",Assignments!$AI$2:$AI$769,"<="&I$47,Assignments!$AJ$2:$AJ$769,">="&I$47)+SUMIFS(Assignments!$AN$2:$AN$769,Assignments!$A$2:$A$769,$A50,Assignments!$G$2:$G$769,"Active",Assignments!$AL$2:$AL$769,"<="&I$47,Assignments!$AM$2:$AM$769,">="&I$47)) | J50: =IF($A50="","",SUMIFS(Assignments!$AK$2:$AK$769,Assignments!$A$2:$A$769,$A50,Assignments!$G$2:$G$769,"Active",Assignments!$AI$2:$AI$769,"<="&J$47,Assignments!$AJ$2:$AJ$769,">="&J$47)+SUMIFS(Assignments!$AN$2:$AN$769,Assignments!$A$2:$A$769,$A50,Assignments!$G$2:$G$769,"Active",Assignments!$AL$2:$AL$769,"<="&J$47,Assignments!$AM$2:$AM$769,">="&J$47)) | ... AB50: =IF($A50="","",SUMIFS(Assignments!$AK$2:$AK$769,Assignments!$A$2:$A$769,$A50,Assignments!$G$2:$G$769,"Active",Assignments!$AI$2:$AI$769,"<="&AB$47,Assignments!$AJ$2:$AJ$769,">="&AB$47)+SUMIFS(Assignments!$AN$2:$AN$769,Assignments!$A$2:$A$769,$A50,Assignments!$G$2:$G$769,"Active",Assignments!$AL$2:$AL$769,"<="&AB$47,Assignments!$AM$2:$AM$769,">="&AB$47))
A51: =IF(Roster!$A5="","",Roster!$A5) | B51: =IF($A51="","",IFERROR(INDEX(Roster!$D$2:$D$40,MATCH($A51,Roster!$A$2:$A$40,0)),"")) | C51: =IF($A51="","",SUMIFS(Assignments!$AK$2:$AK$769,Assignments!$A$2:$A$769,$A51,Assignments!$G$2:$G$769,"Active",Assignments!$AI$2:$AI$769,"<="&C$47,Assignments!$AJ$2:$AJ$769,">="&C$47)+SUMIFS(Assignments!$AN$2:$AN$769,Assignments!$A$2:$A$769,$A51,Assignments!$G$2:$G$769,"Active",Assignments!$AL$2:$AL$769,"<="&C$47,Assignments!$AM$2:$AM$769,">="&C$47)) | D51: =IF($A51="","",SUMIFS(Assignments!$AK$2:$AK$769,Assignments!$A$2:$A$769,$A51,Assignments!$G$2:$G$769,"Active",Assignments!$AI$2:$AI$769,"<="&D$47,Assignments!$AJ$2:$AJ$769,">="&D$47)+SUMIFS(Assignments!$AN$2:$AN$769,Assignments!$A$2:$A$769,$A51,Assignments!$G$2:$G$769,"Active",Assignments!$AL$2:$AL$769,"<="&D$47,Assignments!$AM$2:$AM$769,">="&D$47)) | E51: =IF($A51="","",SUMIFS(Assignments!$AK$2:$AK$769,Assignments!$A$2:$A$769,$A51,Assignments!$G$2:$G$769,"Active",Assignments!$AI$2:$AI$769,"<="&E$47,Assignments!$AJ$2:$AJ$769,">="&E$47)+SUMIFS(Assignments!$AN$2:$AN$769,Assignments!$A$2:$A$769,$A51,Assignments!$G$2:$G$769,"Active",Assignments!$AL$2:$AL$769,"<="&E$47,Assignments!$AM$2:$AM$769,">="&E$47)) | F51: =IF($A51="","",SUMIFS(Assignments!$AK$2:$AK$769,Assignments!$A$2:$A$769,$A51,Assignments!$G$2:$G$769,"Active",Assignments!$AI$2:$AI$769,"<="&F$47,Assignments!$AJ$2:$AJ$769,">="&F$47)+SUMIFS(Assignments!$AN$2:$AN$769,Assignments!$A$2:$A$769,$A51,Assignments!$G$2:$G$769,"Active",Assignments!$AL$2:$AL$769,"<="&F$47,Assignments!$AM$2:$AM$769,">="&F$47)) | G51: =IF($A51="","",SUMIFS(Assignments!$AK$2:$AK$769,Assignments!$A$2:$A$769,$A51,Assignments!$G$2:$G$769,"Active",Assignments!$AI$2:$AI$769,"<="&G$47,Assignments!$AJ$2:$AJ$769,">="&G$47)+SUMIFS(Assignments!$AN$2:$AN$769,Assignments!$A$2:$A$769,$A51,Assignments!$G$2:$G$769,"Active",Assignments!$AL$2:$AL$769,"<="&G$47,Assignments!$AM$2:$AM$769,">="&G$47)) | H51: =IF($A51="","",SUMIFS(Assignments!$AK$2:$AK$769,Assignments!$A$2:$A$769,$A51,Assignments!$G$2:$G$769,"Active",Assignments!$AI$2:$AI$769,"<="&H$47,Assignments!$AJ$2:$AJ$769,">="&H$47)+SUMIFS(Assignments!$AN$2:$AN$769,Assignments!$A$2:$A$769,$A51,Assignments!$G$2:$G$769,"Active",Assignments!$AL$2:$AL$769,"<="&H$47,Assignments!$AM$2:$AM$769,">="&H$47)) | I51: =IF($A51="","",SUMIFS(Assignments!$AK$2:$AK$769,Assignments!$A$2:$A$769,$A51,Assignments!$G$2:$G$769,"Active",Assignments!$AI$2:$AI$769,"<="&I$47,Assignments!$AJ$2:$AJ$769,">="&I$47)+SUMIFS(Assignments!$AN$2:$AN$769,Assignments!$A$2:$A$769,$A51,Assignments!$G$2:$G$769,"Active",Assignments!$AL$2:$AL$769,"<="&I$47,Assignments!$AM$2:$AM$769,">="&I$47)) | J51: =IF($A51="","",SUMIFS(Assignments!$AK$2:$AK$769,Assignments!$A$2:$A$769,$A51,Assignments!$G$2:$G$769,"Active",Assignments!$AI$2:$AI$769,"<="&J$47,Assignments!$AJ$2:$AJ$769,">="&J$47)+SUMIFS(Assignments!$AN$2:$AN$769,Assignments!$A$2:$A$769,$A51,Assignments!$G$2:$G$769,"Active",Assignments!$AL$2:$AL$769,"<="&J$47,Assignments!$AM$2:$AM$769,">="&J$47)) | ... AB51: =IF($A51="","",SUMIFS(Assignments!$AK$2:$AK$769,Assignments!$A$2:$A$769,$A51,Assignments!$G$2:$G$769,"Active",Assignments!$AI$2:$AI$769,"<="&AB$47,Assignments!$AJ$2:$AJ$769,">="&AB$47)+SUMIFS(Assignments!$AN$2:$AN$769,Assignments!$A$2:$A$769,$A51,Assignments!$G$2:$G$769,"Active",Assignments!$AL$2:$AL$769,"<="&AB$47,Assignments!$AM$2:$AM$769,">="&AB$47))
A52: =IF(Roster!$A6="","",Roster!$A6) | B52: =IF($A52="","",IFERROR(INDEX(Roster!$D$2:$D$40,MATCH($A52,Roster!$A$2:$A$40,0)),"")) | C52: =IF($A52="","",SUMIFS(Assignments!$AK$2:$AK$769,Assignments!$A$2:$A$769,$A52,Assignments!$G$2:$G$769,"Active",Assignments!$AI$2:$AI$769,"<="&C$47,Assignments!$AJ$2:$AJ$769,">="&C$47)+SUMIFS(Assignments!$AN$2:$AN$769,Assignments!$A$2:$A$769,$A52,Assignments!$G$2:$G$769,"Active",Assignments!$AL$2:$AL$769,"<="&C$47,Assignments!$AM$2:$AM$769,">="&C$47)) | D52: =IF($A52="","",SUMIFS(Assignments!$AK$2:$AK$769,Assignments!$A$2:$A$769,$A52,Assignments!$G$2:$G$769,"Active",Assignments!$AI$2:$AI$769,"<="&D$47,Assignments!$AJ$2:$AJ$769,">="&D$47)+SUMIFS(Assignments!$AN$2:$AN$769,Assignments!$A$2:$A$769,$A52,Assignments!$G$2:$G$769,"Active",Assignments!$AL$2:$AL$769,"<="&D$47,Assignments!$AM$2:$AM$769,">="&D$47)) | E52: =IF($A52="","",SUMIFS(Assignments!$AK$2:$AK$769,Assignments!$A$2:$A$769,$A52,Assignments!$G$2:$G$769,"Active",Assignments!$AI$2:$AI$769,"<="&E$47,Assignments!$AJ$2:$AJ$769,">="&E$47)+SUMIFS(Assignments!$AN$2:$AN$769,Assignments!$A$2:$A$769,$A52,Assignments!$G$2:$G$769,"Active",Assignments!$AL$2:$AL$769,"<="&E$47,Assignments!$AM$2:$AM$769,">="&E$47)) | F52: =IF($A52="","",SUMIFS(Assignments!$AK$2:$AK$769,Assignments!$A$2:$A$769,$A52,Assignments!$G$2:$G$769,"Active",Assignments!$AI$2:$AI$769,"<="&F$47,Assignments!$AJ$2:$AJ$769,">="&F$47)+SUMIFS(Assignments!$AN$2:$AN$769,Assignments!$A$2:$A$769,$A52,Assignments!$G$2:$G$769,"Active",Assignments!$AL$2:$AL$769,"<="&F$47,Assignments!$AM$2:$AM$769,">="&F$47)) | G52: =IF($A52="","",SUMIFS(Assignments!$AK$2:$AK$769,Assignments!$A$2:$A$769,$A52,Assignments!$G$2:$G$769,"Active",Assignments!$AI$2:$AI$769,"<="&G$47,Assignments!$AJ$2:$AJ$769,">="&G$47)+SUMIFS(Assignments!$AN$2:$AN$769,Assignments!$A$2:$A$769,$A52,Assignments!$G$2:$G$769,"Active",Assignments!$AL$2:$AL$769,"<="&G$47,Assignments!$AM$2:$AM$769,">="&G$47)) | H52: =IF($A52="","",SUMIFS(Assignments!$AK$2:$AK$769,Assignments!$A$2:$A$769,$A52,Assignments!$G$2:$G$769,"Active",Assignments!$AI$2:$AI$769,"<="&H$47,Assignments!$AJ$2:$AJ$769,">="&H$47)+SUMIFS(Assignments!$AN$2:$AN$769,Assignments!$A$2:$A$769,$A52,Assignments!$G$2:$G$769,"Active",Assignments!$AL$2:$AL$769,"<="&H$47,Assignments!$AM$2:$AM$769,">="&H$47)) | I52: =IF($A52="","",SUMIFS(Assignments!$AK$2:$AK$769,Assignments!$A$2:$A$769,$A52,Assignments!$G$2:$G$769,"Active",Assignments!$AI$2:$AI$769,"<="&I$47,Assignments!$AJ$2:$AJ$769,">="&I$47)+SUMIFS(Assignments!$AN$2:$AN$769,Assignments!$A$2:$A$769,$A52,Assignments!$G$2:$G$769,"Active",Assignments!$AL$2:$AL$769,"<="&I$47,Assignments!$AM$2:$AM$769,">="&I$47)) | J52: =IF($A52="","",SUMIFS(Assignments!$AK$2:$AK$769,Assignments!$A$2:$A$769,$A52,Assignments!$G$2:$G$769,"Active",Assignments!$AI$2:$AI$769,"<="&J$47,Assignments!$AJ$2:$AJ$769,">="&J$47)+SUMIFS(Assignments!$AN$2:$AN$769,Assignments!$A$2:$A$769,$A52,Assignments!$G$2:$G$769,"Active",Assignments!$AL$2:$AL$769,"<="&J$47,Assignments!$AM$2:$AM$769,">="&J$47)) | ... AB52: =IF($A52="","",SUMIFS(Assignments!$AK$2:$AK$769,Assignments!$A$2:$A$769,$A52,Assignments!$G$2:$G$769,"Active",Assignments!$AI$2:$AI$769,"<="&AB$47,Assignments!$AJ$2:$AJ$769,">="&AB$47)+SUMIFS(Assignments!$AN$2:$AN$769,Assignments!$A$2:$A$769,$A52,Assignments!$G$2:$G$769,"Active",Assignments!$AL$2:$AL$769,"<="&AB$47,Assignments!$AM$2:$AM$769,">="&AB$47))
A53: =IF(Roster!$A7="","",Roster!$A7) | B53: =IF($A53="","",IFERROR(INDEX(Roster!$D$2:$D$40,MATCH($A53,Roster!$A$2:$A$40,0)),"")) | C53: =IF($A53="","",SUMIFS(Assignments!$AK$2:$AK$769,Assignments!$A$2:$A$769,$A53,Assignments!$G$2:$G$769,"Active",Assignments!$AI$2:$AI$769,"<="&C$47,Assignments!$AJ$2:$AJ$769,">="&C$47)+SUMIFS(Assignments!$AN$2:$AN$769,Assignments!$A$2:$A$769,$A53,Assignments!$G$2:$G$769,"Active",Assignments!$AL$2:$AL$769,"<="&C$47,Assignments!$AM$2:$AM$769,">="&C$47)) | D53: =IF($A53="","",SUMIFS(Assignments!$AK$2:$AK$769,Assignments!$A$2:$A$769,$A53,Assignments!$G$2:$G$769,"Active",Assignments!$AI$2:$AI$769,"<="&D$47,Assignments!$AJ$2:$AJ$769,">="&D$47)+SUMIFS(Assignments!$AN$2:$AN$769,Assignments!$A$2:$A$769,$A53,Assignments!$G$2:$G$769,"Active",Assignments!$AL$2:$AL$769,"<="&D$47,Assignments!$AM$2:$AM$769,">="&D$47)) | E53: =IF($A53="","",SUMIFS(Assignments!$AK$2:$AK$769,Assignments!$A$2:$A$769,$A53,Assignments!$G$2:$G$769,"Active",Assignments!$AI$2:$AI$769,"<="&E$47,Assignments!$AJ$2:$AJ$769,">="&E$47)+SUMIFS(Assignments!$AN$2:$AN$769,Assignments!$A$2:$A$769,$A53,Assignments!$G$2:$G$769,"Active",Assignments!$AL$2:$AL$769,"<="&E$47,Assignments!$AM$2:$AM$769,">="&E$47)) | F53: =IF($A53="","",SUMIFS(Assignments!$AK$2:$AK$769,Assignments!$A$2:$A$769,$A53,Assignments!$G$2:$G$769,"Active",Assignments!$AI$2:$AI$769,"<="&F$47,Assignments!$AJ$2:$AJ$769,">="&F$47)+SUMIFS(Assignments!$AN$2:$AN$769,Assignments!$A$2:$A$769,$A53,Assignments!$G$2:$G$769,"Active",Assignments!$AL$2:$AL$769,"<="&F$47,Assignments!$AM$2:$AM$769,">="&F$47)) | G53: =IF($A53="","",SUMIFS(Assignments!$AK$2:$AK$769,Assignments!$A$2:$A$769,$A53,Assignments!$G$2:$G$769,"Active",Assignments!$AI$2:$AI$769,"<="&G$47,Assignments!$AJ$2:$AJ$769,">="&G$47)+SUMIFS(Assignments!$AN$2:$AN$769,Assignments!$A$2:$A$769,$A53,Assignments!$G$2:$G$769,"Active",Assignments!$AL$2:$AL$769,"<="&G$47,Assignments!$AM$2:$AM$769,">="&G$47)) | H53: =IF($A53="","",SUMIFS(Assignments!$AK$2:$AK$769,Assignments!$A$2:$A$769,$A53,Assignments!$G$2:$G$769,"Active",Assignments!$AI$2:$AI$769,"<="&H$47,Assignments!$AJ$2:$AJ$769,">="&H$47)+SUMIFS(Assignments!$AN$2:$AN$769,Assignments!$A$2:$A$769,$A53,Assignments!$G$2:$G$769,"Active",Assignments!$AL$2:$AL$769,"<="&H$47,Assignments!$AM$2:$AM$769,">="&H$47)) | I53: =IF($A53="","",SUMIFS(Assignments!$AK$2:$AK$769,Assignments!$A$2:$A$769,$A53,Assignments!$G$2:$G$769,"Active",Assignments!$AI$2:$AI$769,"<="&I$47,Assignments!$AJ$2:$AJ$769,">="&I$47)+SUMIFS(Assignments!$AN$2:$AN$769,Assignments!$A$2:$A$769,$A53,Assignments!$G$2:$G$769,"Active",Assignments!$AL$2:$AL$769,"<="&I$47,Assignments!$AM$2:$AM$769,">="&I$47)) | J53: =IF($A53="","",SUMIFS(Assignments!$AK$2:$AK$769,Assignments!$A$2:$A$769,$A53,Assignments!$G$2:$G$769,"Active",Assignments!$AI$2:$AI$769,"<="&J$47,Assignments!$AJ$2:$AJ$769,">="&J$47)+SUMIFS(Assignments!$AN$2:$AN$769,Assignments!$A$2:$A$769,$A53,Assignments!$G$2:$G$769,"Active",Assignments!$AL$2:$AL$769,"<="&J$47,Assignments!$AM$2:$AM$769,">="&J$47)) | ... AB53: =IF($A53="","",SUMIFS(Assignments!$AK$2:$AK$769,Assignments!$A$2:$A$769,$A53,Assignments!$G$2:$G$769,"Active",Assignments!$AI$2:$AI$769,"<="&AB$47,Assignments!$AJ$2:$AJ$769,">="&AB$47)+SUMIFS(Assignments!$AN$2:$AN$769,Assignments!$A$2:$A$769,$A53,Assignments!$G$2:$G$769,"Active",Assignments!$AL$2:$AL$769,"<="&AB$47,Assignments!$AM$2:$AM$769,">="&AB$47))
A54: =IF(Roster!$A8="","",Roster!$A8) | B54: =IF($A54="","",IFERROR(INDEX(Roster!$D$2:$D$40,MATCH($A54,Roster!$A$2:$A$40,0)),"")) | C54: =IF($A54="","",SUMIFS(Assignments!$AK$2:$AK$769,Assignments!$A$2:$A$769,$A54,Assignments!$G$2:$G$769,"Active",Assignments!$AI$2:$AI$769,"<="&C$47,Assignments!$AJ$2:$AJ$769,">="&C$47)+SUMIFS(Assignments!$AN$2:$AN$769,Assignments!$A$2:$A$769,$A54,Assignments!$G$2:$G$769,"Active",Assignments!$AL$2:$AL$769,"<="&C$47,Assignments!$AM$2:$AM$769,">="&C$47)) | D54: =IF($A54="","",SUMIFS(Assignments!$AK$2:$AK$769,Assignments!$A$2:$A$769,$A54,Assignments!$G$2:$G$769,"Active",Assignments!$AI$2:$AI$769,"<="&D$47,Assignments!$AJ$2:$AJ$769,">="&D$47)+SUMIFS(Assignments!$AN$2:$AN$769,Assignments!$A$2:$A$769,$A54,Assignments!$G$2:$G$769,"Active",Assignments!$AL$2:$AL$769,"<="&D$47,Assignments!$AM$2:$AM$769,">="&D$47)) | E54: =IF($A54="","",SUMIFS(Assignments!$AK$2:$AK$769,Assignments!$A$2:$A$769,$A54,Assignments!$G$2:$G$769,"Active",Assignments!$AI$2:$AI$769,"<="&E$47,Assignments!$AJ$2:$AJ$769,">="&E$47)+SUMIFS(Assignments!$AN$2:$AN$769,Assignments!$A$2:$A$769,$A54,Assignments!$G$2:$G$769,"Active",Assignments!$AL$2:$AL$769,"<="&E$47,Assignments!$AM$2:$AM$769,">="&E$47)) | F54: =IF($A54="","",SUMIFS(Assignments!$AK$2:$AK$769,Assignments!$A$2:$A$769,$A54,Assignments!$G$2:$G$769,"Active",Assignments!$AI$2:$AI$769,"<="&F$47,Assignments!$AJ$2:$AJ$769,">="&F$47)+SUMIFS(Assignments!$AN$2:$AN$769,Assignments!$A$2:$A$769,$A54,Assignments!$G$2:$G$769,"Active",Assignments!$AL$2:$AL$769,"<="&F$47,Assignments!$AM$2:$AM$769,">="&F$47)) | G54: =IF($A54="","",SUMIFS(Assignments!$AK$2:$AK$769,Assignments!$A$2:$A$769,$A54,Assignments!$G$2:$G$769,"Active",Assignments!$AI$2:$AI$769,"<="&G$47,Assignments!$AJ$2:$AJ$769,">="&G$47)+SUMIFS(Assignments!$AN$2:$AN$769,Assignments!$A$2:$A$769,$A54,Assignments!$G$2:$G$769,"Active",Assignments!$AL$2:$AL$769,"<="&G$47,Assignments!$AM$2:$AM$769,">="&G$47)) | H54: =IF($A54="","",SUMIFS(Assignments!$AK$2:$AK$769,Assignments!$A$2:$A$769,$A54,Assignments!$G$2:$G$769,"Active",Assignments!$AI$2:$AI$769,"<="&H$47,Assignments!$AJ$2:$AJ$769,">="&H$47)+SUMIFS(Assignments!$AN$2:$AN$769,Assignments!$A$2:$A$769,$A54,Assignments!$G$2:$G$769,"Active",Assignments!$AL$2:$AL$769,"<="&H$47,Assignments!$AM$2:$AM$769,">="&H$47)) | I54: =IF($A54="","",SUMIFS(Assignments!$AK$2:$AK$769,Assignments!$A$2:$A$769,$A54,Assignments!$G$2:$G$769,"Active",Assignments!$AI$2:$AI$769,"<="&I$47,Assignments!$AJ$2:$AJ$769,">="&I$47)+SUMIFS(Assignments!$AN$2:$AN$769,Assignments!$A$2:$A$769,$A54,Assignments!$G$2:$G$769,"Active",Assignments!$AL$2:$AL$769,"<="&I$47,Assignments!$AM$2:$AM$769,">="&I$47)) | J54: =IF($A54="","",SUMIFS(Assignments!$AK$2:$AK$769,Assignments!$A$2:$A$769,$A54,Assignments!$G$2:$G$769,"Active",Assignments!$AI$2:$AI$769,"<="&J$47,Assignments!$AJ$2:$AJ$769,">="&J$47)+SUMIFS(Assignments!$AN$2:$AN$769,Assignments!$A$2:$A$769,$A54,Assignments!$G$2:$G$769,"Active",Assignments!$AL$2:$AL$769,"<="&J$47,Assignments!$AM$2:$AM$769,">="&J$47)) | ... AB54: =IF($A54="","",SUMIFS(Assignments!$AK$2:$AK$769,Assignments!$A$2:$A$769,$A54,Assignments!$G$2:$G$769,"Active",Assignments!$AI$2:$AI$769,"<="&AB$47,Assignments!$AJ$2:$AJ$769,">="&AB$47)+SUMIFS(Assignments!$AN$2:$AN$769,Assignments!$A$2:$A$769,$A54,Assignments!$G$2:$G$769,"Active",Assignments!$AL$2:$AL$769,"<="&AB$47,Assignments!$AM$2:$AM$769,">="&AB$47))
A55: =IF(Roster!$A9="","",Roster!$A9) | B55: =IF($A55="","",IFERROR(INDEX(Roster!$D$2:$D$40,MATCH($A55,Roster!$A$2:$A$40,0)),"")) | C55: =IF($A55="","",SUMIFS(Assignments!$AK$2:$AK$769,Assignments!$A$2:$A$769,$A55,Assignments!$G$2:$G$769,"Active",Assignments!$AI$2:$AI$769,"<="&C$47,Assignments!$AJ$2:$AJ$769,">="&C$47)+SUMIFS(Assignments!$AN$2:$AN$769,Assignments!$A$2:$A$769,$A55,Assignments!$G$2:$G$769,"Active",Assignments!$AL$2:$AL$769,"<="&C$47,Assignments!$AM$2:$AM$769,">="&C$47)) | D55: =IF($A55="","",SUMIFS(Assignments!$AK$2:$AK$769,Assignments!$A$2:$A$769,$A55,Assignments!$G$2:$G$769,"Active",Assignments!$AI$2:$AI$769,"<="&D$47,Assignments!$AJ$2:$AJ$769,">="&D$47)+SUMIFS(Assignments!$AN$2:$AN$769,Assignments!$A$2:$A$769,$A55,Assignments!$G$2:$G$769,"Active",Assignments!$AL$2:$AL$769,"<="&D$47,Assignments!$AM$2:$AM$769,">="&D$47)) | E55: =IF($A55="","",SUMIFS(Assignments!$AK$2:$AK$769,Assignments!$A$2:$A$769,$A55,Assignments!$G$2:$G$769,"Active",Assignments!$AI$2:$AI$769,"<="&E$47,Assignments!$AJ$2:$AJ$769,">="&E$47)+SUMIFS(Assignments!$AN$2:$AN$769,Assignments!$A$2:$A$769,$A55,Assignments!$G$2:$G$769,"Active",Assignments!$AL$2:$AL$769,"<="&E$47,Assignments!$AM$2:$AM$769,">="&E$47)) | F55: =IF($A55="","",SUMIFS(Assignments!$AK$2:$AK$769,Assignments!$A$2:$A$769,$A55,Assignments!$G$2:$G$769,"Active",Assignments!$AI$2:$AI$769,"<="&F$47,Assignments!$AJ$2:$AJ$769,">="&F$47)+SUMIFS(Assignments!$AN$2:$AN$769,Assignments!$A$2:$A$769,$A55,Assignments!$G$2:$G$769,"Active",Assignments!$AL$2:$AL$769,"<="&F$47,Assignments!$AM$2:$AM$769,">="&F$47)) | G55: =IF($A55="","",SUMIFS(Assignments!$AK$2:$AK$769,Assignments!$A$2:$A$769,$A55,Assignments!$G$2:$G$769,"Active",Assignments!$AI$2:$AI$769,"<="&G$47,Assignments!$AJ$2:$AJ$769,">="&G$47)+SUMIFS(Assignments!$AN$2:$AN$769,Assignments!$A$2:$A$769,$A55,Assignments!$G$2:$G$769,"Active",Assignments!$AL$2:$AL$769,"<="&G$47,Assignments!$AM$2:$AM$769,">="&G$47)) | H55: =IF($A55="","",SUMIFS(Assignments!$AK$2:$AK$769,Assignments!$A$2:$A$769,$A55,Assignments!$G$2:$G$769,"Active",Assignments!$AI$2:$AI$769,"<="&H$47,Assignments!$AJ$2:$AJ$769,">="&H$47)+SUMIFS(Assignments!$AN$2:$AN$769,Assignments!$A$2:$A$769,$A55,Assignments!$G$2:$G$769,"Active",Assignments!$AL$2:$AL$769,"<="&H$47,Assignments!$AM$2:$AM$769,">="&H$47)) | I55: =IF($A55="","",SUMIFS(Assignments!$AK$2:$AK$769,Assignments!$A$2:$A$769,$A55,Assignments!$G$2:$G$769,"Active",Assignments!$AI$2:$AI$769,"<="&I$47,Assignments!$AJ$2:$AJ$769,">="&I$47)+SUMIFS(Assignments!$AN$2:$AN$769,Assignments!$A$2:$A$769,$A55,Assignments!$G$2:$G$769,"Active",Assignments!$AL$2:$AL$769,"<="&I$47,Assignments!$AM$2:$AM$769,">="&I$47)) | J55: =IF($A55="","",SUMIFS(Assignments!$AK$2:$AK$769,Assignments!$A$2:$A$769,$A55,Assignments!$G$2:$G$769,"Active",Assignments!$AI$2:$AI$769,"<="&J$47,Assignments!$AJ$2:$AJ$769,">="&J$47)+SUMIFS(Assignments!$AN$2:$AN$769,Assignments!$A$2:$A$769,$A55,Assignments!$G$2:$G$769,"Active",Assignments!$AL$2:$AL$769,"<="&J$47,Assignments!$AM$2:$AM$769,">="&J$47)) | ... AB55: =IF($A55="","",SUMIFS(Assignments!$AK$2:$AK$769,Assignments!$A$2:$A$769,$A55,Assignments!$G$2:$G$769,"Active",Assignments!$AI$2:$AI$769,"<="&AB$47,Assignments!$AJ$2:$AJ$769,">="&AB$47)+SUMIFS(Assignments!$AN$2:$AN$769,Assignments!$A$2:$A$769,$A55,Assignments!$G$2:$G$769,"Active",Assignments!$AL$2:$AL$769,"<="&AB$47,Assignments!$AM$2:$AM$769,">="&AB$47))
A56: =IF(Roster!$A10="","",Roster!$A10) | B56: =IF($A56="","",IFERROR(INDEX(Roster!$D$2:$D$40,MATCH($A56,Roster!$A$2:$A$40,0)),"")) | C56: =IF($A56="","",SUMIFS(Assignments!$AK$2:$AK$769,Assignments!$A$2:$A$769,$A56,Assignments!$G$2:$G$769,"Active",Assignments!$AI$2:$AI$769,"<="&C$47,Assignments!$AJ$2:$AJ$769,">="&C$47)+SUMIFS(Assignments!$AN$2:$AN$769,Assignments!$A$2:$A$769,$A56,Assignments!$G$2:$G$769,"Active",Assignments!$AL$2:$AL$769,"<="&C$47,Assignments!$AM$2:$AM$769,">="&C$47)) | D56: =IF($A56="","",SUMIFS(Assignments!$AK$2:$AK$769,Assignments!$A$2:$A$769,$A56,Assignments!$G$2:$G$769,"Active",Assignments!$AI$2:$AI$769,"<="&D$47,Assignments!$AJ$2:$AJ$769,">="&D$47)+SUMIFS(Assignments!$AN$2:$AN$769,Assignments!$A$2:$A$769,$A56,Assignments!$G$2:$G$769,"Active",Assignments!$AL$2:$AL$769,"<="&D$47,Assignments!$AM$2:$AM$769,">="&D$47)) | E56: =IF($A56="","",SUMIFS(Assignments!$AK$2:$AK$769,Assignments!$A$2:$A$769,$A56,Assignments!$G$2:$G$769,"Active",Assignments!$AI$2:$AI$769,"<="&E$47,Assignments!$AJ$2:$AJ$769,">="&E$47)+SUMIFS(Assignments!$AN$2:$AN$769,Assignments!$A$2:$A$769,$A56,Assignments!$G$2:$G$769,"Active",Assignments!$AL$2:$AL$769,"<="&E$47,Assignments!$AM$2:$AM$769,">="&E$47)) | F56: =IF($A56="","",SUMIFS(Assignments!$AK$2:$AK$769,Assignments!$A$2:$A$769,$A56,Assignments!$G$2:$G$769,"Active",Assignments!$AI$2:$AI$769,"<="&F$47,Assignments!$AJ$2:$AJ$769,">="&F$47)+SUMIFS(Assignments!$AN$2:$AN$769,Assignments!$A$2:$A$769,$A56,Assignments!$G$2:$G$769,"Active",Assignments!$AL$2:$AL$769,"<="&F$47,Assignments!$AM$2:$AM$769,">="&F$47)) | G56: =IF($A56="","",SUMIFS(Assignments!$AK$2:$AK$769,Assignments!$A$2:$A$769,$A56,Assignments!$G$2:$G$769,"Active",Assignments!$AI$2:$AI$769,"<="&G$47,Assignments!$AJ$2:$AJ$769,">="&G$47)+SUMIFS(Assignments!$AN$2:$AN$769,Assignments!$A$2:$A$769,$A56,Assignments!$G$2:$G$769,"Active",Assignments!$AL$2:$AL$769,"<="&G$47,Assignments!$AM$2:$AM$769,">="&G$47)) | H56: =IF($A56="","",SUMIFS(Assignments!$AK$2:$AK$769,Assignments!$A$2:$A$769,$A56,Assignments!$G$2:$G$769,"Active",Assignments!$AI$2:$AI$769,"<="&H$47,Assignments!$AJ$2:$AJ$769,">="&H$47)+SUMIFS(Assignments!$AN$2:$AN$769,Assignments!$A$2:$A$769,$A56,Assignments!$G$2:$G$769,"Active",Assignments!$AL$2:$AL$769,"<="&H$47,Assignments!$AM$2:$AM$769,">="&H$47)) | I56: =IF($A56="","",SUMIFS(Assignments!$AK$2:$AK$769,Assignments!$A$2:$A$769,$A56,Assignments!$G$2:$G$769,"Active",Assignments!$AI$2:$AI$769,"<="&I$47,Assignments!$AJ$2:$AJ$769,">="&I$47)+SUMIFS(Assignments!$AN$2:$AN$769,Assignments!$A$2:$A$769,$A56,Assignments!$G$2:$G$769,"Active",Assignments!$AL$2:$AL$769,"<="&I$47,Assignments!$AM$2:$AM$769,">="&I$47)) | J56: =IF($A56="","",SUMIFS(Assignments!$AK$2:$AK$769,Assignments!$A$2:$A$769,$A56,Assignments!$G$2:$G$769,"Active",Assignments!$AI$2:$AI$769,"<="&J$47,Assignments!$AJ$2:$AJ$769,">="&J$47)+SUMIFS(Assignments!$AN$2:$AN$769,Assignments!$A$2:$A$769,$A56,Assignments!$G$2:$G$769,"Active",Assignments!$AL$2:$AL$769,"<="&J$47,Assignments!$AM$2:$AM$769,">="&J$47)) | ... AB56: =IF($A56="","",SUMIFS(Assignments!$AK$2:$AK$769,Assignments!$A$2:$A$769,$A56,Assignments!$G$2:$G$769,"Active",Assignments!$AI$2:$AI$769,"<="&AB$47,Assignments!$AJ$2:$AJ$769,">="&AB$47)+SUMIFS(Assignments!$AN$2:$AN$769,Assignments!$A$2:$A$769,$A56,Assignments!$G$2:$G$769,"Active",Assignments!$AL$2:$AL$769,"<="&AB$47,Assignments!$AM$2:$AM$769,">="&AB$47))
A57: =IF(Roster!$A11="","",Roster!$A11) | B57: =IF($A57="","",IFERROR(INDEX(Roster!$D$2:$D$40,MATCH($A57,Roster!$A$2:$A$40,0)),"")) | C57: =IF($A57="","",SUMIFS(Assignments!$AK$2:$AK$769,Assignments!$A$2:$A$769,$A57,Assignments!$G$2:$G$769,"Active",Assignments!$AI$2:$AI$769,"<="&C$47,Assignments!$AJ$2:$AJ$769,">="&C$47)+SUMIFS(Assignments!$AN$2:$AN$769,Assignments!$A$2:$A$769,$A57,Assignments!$G$2:$G$769,"Active",Assignments!$AL$2:$AL$769,"<="&C$47,Assignments!$AM$2:$AM$769,">="&C$47)) | D57: =IF($A57="","",SUMIFS(Assignments!$AK$2:$AK$769,Assignments!$A$2:$A$769,$A57,Assignments!$G$2:$G$769,"Active",Assignments!$AI$2:$AI$769,"<="&D$47,Assignments!$AJ$2:$AJ$769,">="&D$47)+SUMIFS(Assignments!$AN$2:$AN$769,Assignments!$A$2:$A$769,$A57,Assignments!$G$2:$G$769,"Active",Assignments!$AL$2:$AL$769,"<="&D$47,Assignments!$AM$2:$AM$769,">="&D$47)) | E57: =IF($A57="","",SUMIFS(Assignments!$AK$2:$AK$769,Assignments!$A$2:$A$769,$A57,Assignments!$G$2:$G$769,"Active",Assignments!$AI$2:$AI$769,"<="&E$47,Assignments!$AJ$2:$AJ$769,">="&E$47)+SUMIFS(Assignments!$AN$2:$AN$769,Assignments!$A$2:$A$769,$A57,Assignments!$G$2:$G$769,"Active",Assignments!$AL$2:$AL$769,"<="&E$47,Assignments!$AM$2:$AM$769,">="&E$47)) | F57: =IF($A57="","",SUMIFS(Assignments!$AK$2:$AK$769,Assignments!$A$2:$A$769,$A57,Assignments!$G$2:$G$769,"Active",Assignments!$AI$2:$AI$769,"<="&F$47,Assignments!$AJ$2:$AJ$769,">="&F$47)+SUMIFS(Assignments!$AN$2:$AN$769,Assignments!$A$2:$A$769,$A57,Assignments!$G$2:$G$769,"Active",Assignments!$AL$2:$AL$769,"<="&F$47,Assignments!$AM$2:$AM$769,">="&F$47)) | G57: =IF($A57="","",SUMIFS(Assignments!$AK$2:$AK$769,Assignments!$A$2:$A$769,$A57,Assignments!$G$2:$G$769,"Active",Assignments!$AI$2:$AI$769,"<="&G$47,Assignments!$AJ$2:$AJ$769,">="&G$47)+SUMIFS(Assignments!$AN$2:$AN$769,Assignments!$A$2:$A$769,$A57,Assignments!$G$2:$G$769,"Active",Assignments!$AL$2:$AL$769,"<="&G$47,Assignments!$AM$2:$AM$769,">="&G$47)) | H57: =IF($A57="","",SUMIFS(Assignments!$AK$2:$AK$769,Assignments!$A$2:$A$769,$A57,Assignments!$G$2:$G$769,"Active",Assignments!$AI$2:$AI$769,"<="&H$47,Assignments!$AJ$2:$AJ$769,">="&H$47)+SUMIFS(Assignments!$AN$2:$AN$769,Assignments!$A$2:$A$769,$A57,Assignments!$G$2:$G$769,"Active",Assignments!$AL$2:$AL$769,"<="&H$47,Assignments!$AM$2:$AM$769,">="&H$47)) | I57: =IF($A57="","",SUMIFS(Assignments!$AK$2:$AK$769,Assignments!$A$2:$A$769,$A57,Assignments!$G$2:$G$769,"Active",Assignments!$AI$2:$AI$769,"<="&I$47,Assignments!$AJ$2:$AJ$769,">="&I$47)+SUMIFS(Assignments!$AN$2:$AN$769,Assignments!$A$2:$A$769,$A57,Assignments!$G$2:$G$769,"Active",Assignments!$AL$2:$AL$769,"<="&I$47,Assignments!$AM$2:$AM$769,">="&I$47)) | J57: =IF($A57="","",SUMIFS(Assignments!$AK$2:$AK$769,Assignments!$A$2:$A$769,$A57,Assignments!$G$2:$G$769,"Active",Assignments!$AI$2:$AI$769,"<="&J$47,Assignments!$AJ$2:$AJ$769,">="&J$47)+SUMIFS(Assignments!$AN$2:$AN$769,Assignments!$A$2:$A$769,$A57,Assignments!$G$2:$G$769,"Active",Assignments!$AL$2:$AL$769,"<="&J$47,Assignments!$AM$2:$AM$769,">="&J$47)) | ... AB57: =IF($A57="","",SUMIFS(Assignments!$AK$2:$AK$769,Assignments!$A$2:$A$769,$A57,Assignments!$G$2:$G$769,"Active",Assignments!$AI$2:$AI$769,"<="&AB$47,Assignments!$AJ$2:$AJ$769,">="&AB$47)+SUMIFS(Assignments!$AN$2:$AN$769,Assignments!$A$2:$A$769,$A57,Assignments!$G$2:$G$769,"Active",Assignments!$AL$2:$AL$769,"<="&AB$47,Assignments!$AM$2:$AM$769,">="&AB$47))
A58: =IF(Roster!$A12="","",Roster!$A12) | B58: =IF($A58="","",IFERROR(INDEX(Roster!$D$2:$D$40,MATCH($A58,Roster!$A$2:$A$40,0)),"")) | C58: =IF($A58="","",SUMIFS(Assignments!$AK$2:$AK$769,Assignments!$A$2:$A$769,$A58,Assignments!$G$2:$G$769,"Active",Assignments!$AI$2:$AI$769,"<="&C$47,Assignments!$AJ$2:$AJ$769,">="&C$47)+SUMIFS(Assignments!$AN$2:$AN$769,Assignments!$A$2:$A$769,$A58,Assignments!$G$2:$G$769,"Active",Assignments!$AL$2:$AL$769,"<="&C$47,Assignments!$AM$2:$AM$769,">="&C$47)) | D58: =IF($A58="","",SUMIFS(Assignments!$AK$2:$AK$769,Assignments!$A$2:$A$769,$A58,Assignments!$G$2:$G$769,"Active",Assignments!$AI$2:$AI$769,"<="&D$47,Assignments!$AJ$2:$AJ$769,">="&D$47)+SUMIFS(Assignments!$AN$2:$AN$769,Assignments!$A$2:$A$769,$A58,Assignments!$G$2:$G$769,"Active",Assignments!$AL$2:$AL$769,"<="&D$47,Assignments!$AM$2:$AM$769,">="&D$47)) | E58: =IF($A58="","",SUMIFS(Assignments!$AK$2:$AK$769,Assignments!$A$2:$A$769,$A58,Assignments!$G$2:$G$769,"Active",Assignments!$AI$2:$AI$769,"<="&E$47,Assignments!$AJ$2:$AJ$769,">="&E$47)+SUMIFS(Assignments!$AN$2:$AN$769,Assignments!$A$2:$A$769,$A58,Assignments!$G$2:$G$769,"Active",Assignments!$AL$2:$AL$769,"<="&E$47,Assignments!$AM$2:$AM$769,">="&E$47)) | F58: =IF($A58="","",SUMIFS(Assignments!$AK$2:$AK$769,Assignments!$A$2:$A$769,$A58,Assignments!$G$2:$G$769,"Active",Assignments!$AI$2:$AI$769,"<="&F$47,Assignments!$AJ$2:$AJ$769,">="&F$47)+SUMIFS(Assignments!$AN$2:$AN$769,Assignments!$A$2:$A$769,$A58,Assignments!$G$2:$G$769,"Active",Assignments!$AL$2:$AL$769,"<="&F$47,Assignments!$AM$2:$AM$769,">="&F$47)) | G58: =IF($A58="","",SUMIFS(Assignments!$AK$2:$AK$769,Assignments!$A$2:$A$769,$A58,Assignments!$G$2:$G$769,"Active",Assignments!$AI$2:$AI$769,"<="&G$47,Assignments!$AJ$2:$AJ$769,">="&G$47)+SUMIFS(Assignments!$AN$2:$AN$769,Assignments!$A$2:$A$769,$A58,Assignments!$G$2:$G$769,"Active",Assignments!$AL$2:$AL$769,"<="&G$47,Assignments!$AM$2:$AM$769,">="&G$47)) | H58: =IF($A58="","",SUMIFS(Assignments!$AK$2:$AK$769,Assignments!$A$2:$A$769,$A58,Assignments!$G$2:$G$769,"Active",Assignments!$AI$2:$AI$769,"<="&H$47,Assignments!$AJ$2:$AJ$769,">="&H$47)+SUMIFS(Assignments!$AN$2:$AN$769,Assignments!$A$2:$A$769,$A58,Assignments!$G$2:$G$769,"Active",Assignments!$AL$2:$AL$769,"<="&H$47,Assignments!$AM$2:$AM$769,">="&H$47)) | I58: =IF($A58="","",SUMIFS(Assignments!$AK$2:$AK$769,Assignments!$A$2:$A$769,$A58,Assignments!$G$2:$G$769,"Active",Assignments!$AI$2:$AI$769,"<="&I$47,Assignments!$AJ$2:$AJ$769,">="&I$47)+SUMIFS(Assignments!$AN$2:$AN$769,Assignments!$A$2:$A$769,$A58,Assignments!$G$2:$G$769,"Active",Assignments!$AL$2:$AL$769,"<="&I$47,Assignments!$AM$2:$AM$769,">="&I$47)) | J58: =IF($A58="","",SUMIFS(Assignments!$AK$2:$AK$769,Assignments!$A$2:$A$769,$A58,Assignments!$G$2:$G$769,"Active",Assignments!$AI$2:$AI$769,"<="&J$47,Assignments!$AJ$2:$AJ$769,">="&J$47)+SUMIFS(Assignments!$AN$2:$AN$769,Assignments!$A$2:$A$769,$A58,Assignments!$G$2:$G$769,"Active",Assignments!$AL$2:$AL$769,"<="&J$47,Assignments!$AM$2:$AM$769,">="&J$47)) | ... AB58: =IF($A58="","",SUMIFS(Assignments!$AK$2:$AK$769,Assignments!$A$2:$A$769,$A58,Assignments!$G$2:$G$769,"Active",Assignments!$AI$2:$AI$769,"<="&AB$47,Assignments!$AJ$2:$AJ$769,">="&AB$47)+SUMIFS(Assignments!$AN$2:$AN$769,Assignments!$A$2:$A$769,$A58,Assignments!$G$2:$G$769,"Active",Assignments!$AL$2:$AL$769,"<="&AB$47,Assignments!$AM$2:$AM$769,">="&AB$47))
A59: =IF(Roster!$A13="","",Roster!$A13) | B59: =IF($A59="","",IFERROR(INDEX(Roster!$D$2:$D$40,MATCH($A59,Roster!$A$2:$A$40,0)),"")) | C59: =IF($A59="","",SUMIFS(Assignments!$AK$2:$AK$769,Assignments!$A$2:$A$769,$A59,Assignments!$G$2:$G$769,"Active",Assignments!$AI$2:$AI$769,"<="&C$47,Assignments!$AJ$2:$AJ$769,">="&C$47)+SUMIFS(Assignments!$AN$2:$AN$769,Assignments!$A$2:$A$769,$A59,Assignments!$G$2:$G$769,"Active",Assignments!$AL$2:$AL$769,"<="&C$47,Assignments!$AM$2:$AM$769,">="&C$47)) | D59: =IF($A59="","",SUMIFS(Assignments!$AK$2:$AK$769,Assignments!$A$2:$A$769,$A59,Assignments!$G$2:$G$769,"Active",Assignments!$AI$2:$AI$769,"<="&D$47,Assignments!$AJ$2:$AJ$769,">="&D$47)+SUMIFS(Assignments!$AN$2:$AN$769,Assignments!$A$2:$A$769,$A59,Assignments!$G$2:$G$769,"Active",Assignments!$AL$2:$AL$769,"<="&D$47,Assignments!$AM$2:$AM$769,">="&D$47)) | E59: =IF($A59="","",SUMIFS(Assignments!$AK$2:$AK$769,Assignments!$A$2:$A$769,$A59,Assignments!$G$2:$G$769,"Active",Assignments!$AI$2:$AI$769,"<="&E$47,Assignments!$AJ$2:$AJ$769,">="&E$47)+SUMIFS(Assignments!$AN$2:$AN$769,Assignments!$A$2:$A$769,$A59,Assignments!$G$2:$G$769,"Active",Assignments!$AL$2:$AL$769,"<="&E$47,Assignments!$AM$2:$AM$769,">="&E$47)) | F59: =IF($A59="","",SUMIFS(Assignments!$AK$2:$AK$769,Assignments!$A$2:$A$769,$A59,Assignments!$G$2:$G$769,"Active",Assignments!$AI$2:$AI$769,"<="&F$47,Assignments!$AJ$2:$AJ$769,">="&F$47)+SUMIFS(Assignments!$AN$2:$AN$769,Assignments!$A$2:$A$769,$A59,Assignments!$G$2:$G$769,"Active",Assignments!$AL$2:$AL$769,"<="&F$47,Assignments!$AM$2:$AM$769,">="&F$47)) | G59: =IF($A59="","",SUMIFS(Assignments!$AK$2:$AK$769,Assignments!$A$2:$A$769,$A59,Assignments!$G$2:$G$769,"Active",Assignments!$AI$2:$AI$769,"<="&G$47,Assignments!$AJ$2:$AJ$769,">="&G$47)+SUMIFS(Assignments!$AN$2:$AN$769,Assignments!$A$2:$A$769,$A59,Assignments!$G$2:$G$769,"Active",Assignments!$AL$2:$AL$769,"<="&G$47,Assignments!$AM$2:$AM$769,">="&G$47)) | H59: =IF($A59="","",SUMIFS(Assignments!$AK$2:$AK$769,Assignments!$A$2:$A$769,$A59,Assignments!$G$2:$G$769,"Active",Assignments!$AI$2:$AI$769,"<="&H$47,Assignments!$AJ$2:$AJ$769,">="&H$47)+SUMIFS(Assignments!$AN$2:$AN$769,Assignments!$A$2:$A$769,$A59,Assignments!$G$2:$G$769,"Active",Assignments!$AL$2:$AL$769,"<="&H$47,Assignments!$AM$2:$AM$769,">="&H$47)) | I59: =IF($A59="","",SUMIFS(Assignments!$AK$2:$AK$769,Assignments!$A$2:$A$769,$A59,Assignments!$G$2:$G$769,"Active",Assignments!$AI$2:$AI$769,"<="&I$47,Assignments!$AJ$2:$AJ$769,">="&I$47)+SUMIFS(Assignments!$AN$2:$AN$769,Assignments!$A$2:$A$769,$A59,Assignments!$G$2:$G$769,"Active",Assignments!$AL$2:$AL$769,"<="&I$47,Assignments!$AM$2:$AM$769,">="&I$47)) | J59: =IF($A59="","",SUMIFS(Assignments!$AK$2:$AK$769,Assignments!$A$2:$A$769,$A59,Assignments!$G$2:$G$769,"Active",Assignments!$AI$2:$AI$769,"<="&J$47,Assignments!$AJ$2:$AJ$769,">="&J$47)+SUMIFS(Assignments!$AN$2:$AN$769,Assignments!$A$2:$A$769,$A59,Assignments!$G$2:$G$769,"Active",Assignments!$AL$2:$AL$769,"<="&J$47,Assignments!$AM$2:$AM$769,">="&J$47)) | ... AB59: =IF($A59="","",SUMIFS(Assignments!$AK$2:$AK$769,Assignments!$A$2:$A$769,$A59,Assignments!$G$2:$G$769,"Active",Assignments!$AI$2:$AI$769,"<="&AB$47,Assignments!$AJ$2:$AJ$769,">="&AB$47)+SUMIFS(Assignments!$AN$2:$AN$769,Assignments!$A$2:$A$769,$A59,Assignments!$G$2:$G$769,"Active",Assignments!$AL$2:$AL$769,"<="&AB$47,Assignments!$AM$2:$AM$769,">="&AB$47))
... A86: =IF(Roster!$A40="","",Roster!$A40) | B86: =IF($A86="","",IFERROR(INDEX(Roster!$D$2:$D$40,MATCH($A86,Roster!$A$2:$A$40,0)),"")) | C86: =IF($A86="","",SUMIFS(Assignments!$AK$2:$AK$769,Assignments!$A$2:$A$769,$A86,Assignments!$G$2:$G$769,"Active",Assignments!$AI$2:$AI$769,"<="&C$47,Assignments!$AJ$2:$AJ$769,">="&C$47)+SUMIFS(Assignments!$AN$2:$AN$769,Assignments!$A$2:$A$769,$A86,Assignments!$G$2:$G$769,"Active",Assignments!$AL$2:$AL$769,"<="&C$47,Assignments!$AM$2:$AM$769,">="&C$47)) | D86: =IF($A86="","",SUMIFS(Assignments!$AK$2:$AK$769,Assignments!$A$2:$A$769,$A86,Assignments!$G$2:$G$769,"Active",Assignments!$AI$2:$AI$769,"<="&D$47,Assignments!$AJ$2:$AJ$769,">="&D$47)+SUMIFS(Assignments!$AN$2:$AN$769,Assignments!$A$2:$A$769,$A86,Assignments!$G$2:$G$769,"Active",Assignments!$AL$2:$AL$769,"<="&D$47,Assignments!$AM$2:$AM$769,">="&D$47)) | E86: =IF($A86="","",SUMIFS(Assignments!$AK$2:$AK$769,Assignments!$A$2:$A$769,$A86,Assignments!$G$2:$G$769,"Active",Assignments!$AI$2:$AI$769,"<="&E$47,Assignments!$AJ$2:$AJ$769,">="&E$47)+SUMIFS(Assignments!$AN$2:$AN$769,Assignments!$A$2:$A$769,$A86,Assignments!$G$2:$G$769,"Active",Assignments!$AL$2:$AL$769,"<="&E$47,Assignments!$AM$2:$AM$769,">="&E$47)) | F86: =IF($A86="","",SUMIFS(Assignments!$AK$2:$AK$769,Assignments!$A$2:$A$769,$A86,Assignments!$G$2:$G$769,"Active",Assignments!$AI$2:$AI$769,"<="&F$47,Assignments!$AJ$2:$AJ$769,">="&F$47)+SUMIFS(Assignments!$AN$2:$AN$769,Assignments!$A$2:$A$769,$A86,Assignments!$G$2:$G$769,"Active",Assignments!$AL$2:$AL$769,"<="&F$47,Assignments!$AM$2:$AM$769,">="&F$47)) | G86: =IF($A86="","",SUMIFS(Assignments!$AK$2:$AK$769,Assignments!$A$2:$A$769,$A86,Assignments!$G$2:$G$769,"Active",Assignments!$AI$2:$AI$769,"<="&G$47,Assignments!$AJ$2:$AJ$769,">="&G$47)+SUMIFS(Assignments!$AN$2:$AN$769,Assignments!$A$2:$A$769,$A86,Assignments!$G$2:$G$769,"Active",Assignments!$AL$2:$AL$769,"<="&G$47,Assignments!$AM$2:$AM$769,">="&G$47)) | H86: =IF($A86="","",SUMIFS(Assignments!$AK$2:$AK$769,Assignments!$A$2:$A$769,$A86,Assignments!$G$2:$G$769,"Active",Assignments!$AI$2:$AI$769,"<="&H$47,Assignments!$AJ$2:$AJ$769,">="&H$47)+SUMIFS(Assignments!$AN$2:$AN$769,Assignments!$A$2:$A$769,$A86,Assignments!$G$2:$G$769,"Active",Assignments!$AL$2:$AL$769,"<="&H$47,Assignments!$AM$2:$AM$769,">="&H$47)) | I86: =IF($A86="","",SUMIFS(Assignments!$AK$2:$AK$769,Assignments!$A$2:$A$769,$A86,Assignments!$G$2:$G$769,"Active",Assignments!$AI$2:$AI$769,"<="&I$47,Assignments!$AJ$2:$AJ$769,">="&I$47)+SUMIFS(Assignments!$AN$2:$AN$769,Assignments!$A$2:$A$769,$A86,Assignments!$G$2:$G$769,"Active",Assignments!$AL$2:$AL$769,"<="&I$47,Assignments!$AM$2:$AM$769,">="&I$47)) | J86: =IF($A86="","",SUMIFS(Assignments!$AK$2:$AK$769,Assignments!$A$2:$A$769,$A86,Assignments!$G$2:$G$769,"Active",Assignments!$AI$2:$AI$769,"<="&J$47,Assignments!$AJ$2:$AJ$769,">="&J$47)+SUMIFS(Assignments!$AN$2:$AN$769,Assignments!$A$2:$A$769,$A86,Assignments!$G$2:$G$769,"Active",Assignments!$AL$2:$AL$769,"<="&J$47,Assignments!$AM$2:$AM$769,">="&J$47)) | ... AB86: =IF($A86="","",SUMIFS(Assignments!$AK$2:$AK$769,Assignments!$A$2:$A$769,$A86,Assignments!$G$2:$G$769,"Active",Assignments!$AI$2:$AI$769,"<="&AB$47,Assignments!$AJ$2:$AJ$769,">="&AB$47)+SUMIFS(Assignments!$AN$2:$AN$769,Assignments!$A$2:$A$769,$A86,Assignments!$G$2:$G$769,"Active",Assignments!$AL$2:$AL$769,"<="&AB$47,Assignments!$AM$2:$AM$769,">="&AB$47))
A88: Team planned (scenario) | C88: =SUM(C48:C86) | D88: =SUM(D48:D86) | E88: =SUM(E48:E86) | F88: =SUM(F48:F86) | G88: =SUM(G48:G86) | H88: =SUM(H48:H86) | I88: =SUM(I48:I86) | J88: =SUM(J48:J86) | ... AB88: =SUM(AB48:AB86)
A89: Team planned (live) | C89: =Capacity!C45 | D89: =Capacity!D45 | E89: =Capacity!E45 | F89: =Capacity!F45 | G89: =Capacity!G45 | H89: =Capacity!H45 | I89: =Capacity!I45 | J89: =Capacity!J45 | ... AB89: =Capacity!AB45
A90: Change | C90: =C88-C89 | D90: =D88-D89 | E90: =E88-E89 | F90: =F88-F89 | G90: =G88-G89 | H90: =H88-H89 | I90: =I88-I89 | J90: =J88-J89 | ... AB90: =AB88-AB89

Sheet Deals
A1: Project ID | B1: Client (as filed) | C1: Primary client | D1: End client / target | E1: Referral? | F1: Lifecycle | G1: Phase | H1: Probability | I1: Expected start | J1: Expected end | K1: (retired: workstream scoping ->) | L1: (retired) | M1: (retired) | N1: (retired) | O1: (retired) | P1: (retired) | Q1: # staffed | R1: Planned hrs/wk | S1: Source status (Jul 9) | T1: Notes | U1: Effort archetype (legacy) | V1: Front x (calc) | W1: Tail x (calc) | X1: Front frac (calc) | Y1: Phase split date (calc) | Z1: Added on | AA1: SCENARIO probability | AB1: SCENARIO start | AC1: SCENARIO end | AD1: Eff. scn prob (calc) | AE1: Eff. scn start (calc) | AF1: Eff. scn end (calc) | AG1: Scenario split (calc) | AH1: TDD deal type | AI1: Domestic only? (Y/N) | AJ1: TDD scope | AK1: Other TDD scoping | AL1: Modeling: Corporate tax modeling | AM1: Modeling: Tracking Model Review | AN1: Modeling: Property tax Modeling | AO1: Modeling: SALT Modeling | AP1: Modeling: Tax Credit Assumption Review | AQ1: Modeling: Step Up Calculation | AR1: Modeling: Section 382 limitation | AS1: Modeling: FIRPTA Modeling | AT1: Modeling: Other modeling complexities | AU1: Structuring: Strawman deck | AV1: Structuring: Structure paper | AW1: Structuring: Opinion | AX1: Legal docs review | AY1: Fee $ - TDD | AZ1: Fee $ - Modeling | BA1: Fee $ - Structuring | BB1: Fee $ - Legal docs review | BC1: Fee $ - Other | BD1: Fee $ total (calc) | BE1: Dur wk - TDD (calc) | BF1: Dur wk - Modeling (calc) | BG1: Dur wk - Structuring (calc) | BH1: Dur wk - Legal docs review (calc) | BI1: Dur wk - Other (calc) | BJ1: Partner | BK1: MD | BL1: Director | BM1: VP | BN1: Senior Associate | BO1: Renewable Specialist | BP1: Associate
A2: EXAMPLE_0 | B2: Example Client LLC : Example Target | C2: Example Client LLC | D2: Example Target | E2: No | F2: Active | G2: Diligence | H2: 1 | I2: 46223 | J2: 46325 | Q2: =IF($A2="","",COUNTIFS(Assignments!$C$2:$C$769,$A2,Assignments!$G$2:$G$769,"Active")) | R2: =IF($A2="","",SUMIFS(Assignments!$I$2:$I$769,Assignments!$C$2:$C$769,$A2,Assignments!$G$2:$G$769,"Active")) | S2: (example) | T2: EXAMPLE row - shows the expected formats; delete any time. Nobody is staffed on it. | U2: Buy-side TDD + Structuring | V2: =IF($U2="","",IFERROR(INDEX(Templates!$K$3:$K$10,MATCH($U2,Templates!$A$3:$A$10,0)),"")) | W2: =IF($U2="","",IFERROR(INDEX(Templates!$L$3:$L$10,MATCH($U2,Templates!$A$3:$A$10,0)),"")) | X2: =IF($U2="","",IFERROR(INDEX(Templates!$J$3:$J$10,MATCH($U2,Templates!$A$3:$A$10,0)),"")) | Y2: =IF(OR($U2="",$I2="",$J2="",$X2=""),"",$I2+$X2*($J2-$I2)) | Z2: 46212 | AD2: =IF($A2="","",IF($AA2="",$H2,$AA2)) | AE2: =IF($A2="","",IF($AB2="",$I2,$AB2)) | AF2: =IF($A2="","",IF($AC2="",$J2,$AC2)) | AG2: =IF(OR($U2="",$AE2="",$AF2="",$X2=""),"",$AE2+$X2*($AF2-$AE2)) | AH2: Asset Deal (or DRE) | AI2: Y | AJ2: Limited Procedures | AK2: Carve out | AL2: Building roll up | AO2: Y | AQ2: Y | AU2: Y | AX2: Y | AY2: 250000 | AZ2: 90000 | BD2: =IF($A2="","",SUM($AY2:$BC2)) | BE2: =IF($A2="","",IF(AND($I2<>"",$J2<>""),MAX(1,($J2-$I2)/7),Templates!$B$35)) | BF2: =IF($A2="","",IF(AND($I2<>"",$J2<>""),MAX(1,($J2-$I2)/7),Templates!$B$36)) | BG2: =IF($A2="","",IF(AND($I2<>"",$J2<>""),MAX(1,($J2-$I2)/7),Templates!$B$37)) | BH2: =IF($A2="","",IF(AND($I2<>"",$J2<>""),MAX(1,($J2-$I2)/7),Templates!$B$38)) | BI2: =IF($A2="","",IF(AND($I2<>"",$J2<>""),MAX(1,($J2-$I2)/7),Templates!$B$39)) | BJ2: =IF(OR($A2="",$BD2=0),0,($AY2*Templates!$B$27/$BE2+$AZ2*Templates!$B$28/$BF2+$BA2*Templates!$B$29/$BG2+$BB2*Templates!$B$30/$BH2+$BC2*Templates!$B$31/$BI2)/Templates!$B$17) | BK2: =IF(OR($A2="",$BD2=0),0,($AY2*Templates!$C$27/$BE2+$AZ2*Templates!$C$28/$BF2+$BA2*Templates!$C$29/$BG2+$BB2*Templates!$C$30/$BH2+$BC2*Templates!$C$31/$BI2)/Templates!$B$18) | BL2: =IF(OR($A2="",$BD2=0),0,($AY2*Templates!$D$27/$BE2+$AZ2*Templates!$D$28/$BF2+$BA2*Templates!$D$29/$BG2+$BB2*Templates!$D$30/$BH2+$BC2*Templates!$D$31/$BI2)/Templates!$B$19) | BM2: =IF(OR($A2="",$BD2=0),0,($AY2*Templates!$E$27/$BE2+$AZ2*Templates!$E$28/$BF2+$BA2*Templates!$E$29/$BG2+$BB2*Templates!$E$30/$BH2+$BC2*Templates!$E$31/$BI2)/Templates!$B$20) | BN2: =IF(OR($A2="",$BD2=0),0,($AY2*Templates!$F$27/$BE2+$AZ2*Templates!$F$28/$BF2+$BA2*Templates!$F$29/$BG2+$BB2*Templates!$F$30/$BH2+$BC2*Templates!$F$31/$BI2)/Templates!$B$21) | BO2: =IF(OR($A2="",$BD2=0),0,($AY2*Templates!$G$27/$BE2+$AZ2*Templates!$G$28/$BF2+$BA2*Templates!$G$29/$BG2+$BB2*Templates!$G$30/$BH2+$BC2*Templates!$G$31/$BI2)/Templates!$B$22) | BP2: =IF(OR($A2="",$BD2=0),0,($AY2*Templates!$H$27/$BE2+$AZ2*Templates!$H$28/$BF2+$BA2*Templates!$H$29/$BG2+$BB2*Templates!$H$30/$BH2+$BC2*Templates!$H$31/$BI2)/Templates!$B$23)
A3: 2026 Structuring_1 | B3: Torch Clean Energy | C3: Torch Clean Energy | E3: No | F3: Active | H3: 1 | Q3: =IF($A3="","",COUNTIFS(Assignments!$C$2:$C$769,$A3,Assignments!$G$2:$G$769,"Active")) | R3: =IF($A3="","",SUMIFS(Assignments!$I$2:$I$769,Assignments!$C$2:$C$769,$A3,Assignments!$G$2:$G$769,"Active")) | S3: WIP | V3: =IF($U3="","",IFERROR(INDEX(Templates!$K$3:$K$10,MATCH($U3,Templates!$A$3:$A$10,0)),"")) | W3: =IF($U3="","",IFERROR(INDEX(Templates!$L$3:$L$10,MATCH($U3,Templates!$A$3:$A$10,0)),"")) | X3: =IF($U3="","",IFERROR(INDEX(Templates!$J$3:$J$10,MATCH($U3,Templates!$A$3:$A$10,0)),"")) | Y3: =IF(OR($U3="",$I3="",$J3="",$X3=""),"",$I3+$X3*($J3-$I3)) | Z3: 46212 | AD3: =IF($A3="","",IF($AA3="",$H3,$AA3)) | AE3: =IF($A3="","",IF($AB3="",$I3,$AB3)) | AF3: =IF($A3="","",IF($AC3="",$J3,$AC3)) | AG3: =IF(OR($U3="",$AE3="",$AF3="",$X3=""),"",$AE3+$X3*($AF3-$AE3)) | BD3: =IF($A3="","",SUM($AY3:$BC3)) | BE3: =IF($A3="","",IF(AND($I3<>"",$J3<>""),MAX(1,($J3-$I3)/7),Templates!$B$35)) | BF3: =IF($A3="","",IF(AND($I3<>"",$J3<>""),MAX(1,($J3-$I3)/7),Templates!$B$36)) | BG3: =IF($A3="","",IF(AND($I3<>"",$J3<>""),MAX(1,($J3-$I3)/7),Templates!$B$37)) | BH3: =IF($A3="","",IF(AND($I3<>"",$J3<>""),MAX(1,($J3-$I3)/7),Templates!$B$38)) | BI3: =IF($A3="","",IF(AND($I3<>"",$J3<>""),MAX(1,($J3-$I3)/7),Templates!$B$39)) | BJ3: =IF(OR($A3="",$BD3=0),0,($AY3*Templates!$B$27/$BE3+$AZ3*Templates!$B$28/$BF3+$BA3*Templates!$B$29/$BG3+$BB3*Templates!$B$30/$BH3+$BC3*Templates!$B$31/$BI3)/Templates!$B$17) | BK3: =IF(OR($A3="",$BD3=0),0,($AY3*Templates!$C$27/$BE3+$AZ3*Templates!$C$28/$BF3+$BA3*Templates!$C$29/$BG3+$BB3*Templates!$C$30/$BH3+$BC3*Templates!$C$31/$BI3)/Templates!$B$18) | BL3: =IF(OR($A3="",$BD3=0),0,($AY3*Templates!$D$27/$BE3+$AZ3*Templates!$D$28/$BF3+$BA3*Templates!$D$29/$BG3+$BB3*Templates!$D$30/$BH3+$BC3*Templates!$D$31/$BI3)/Templates!$B$19) | BM3: =IF(OR($A3="",$BD3=0),0,($AY3*Templates!$E$27/$BE3+$AZ3*Templates!$E$28/$BF3+$BA3*Templates!$E$29/$BG3+$BB3*Templates!$E$30/$BH3+$BC3*Templates!$E$31/$BI3)/Templates!$B$20) | BN3: =IF(OR($A3="",$BD3=0),0,($AY3*Templates!$F$27/$BE3+$AZ3*Templates!$F$28/$BF3+$BA3*Templates!$F$29/$BG3+$BB3*Templates!$F$30/$BH3+$BC3*Templates!$F$31/$BI3)/Templates!$B$21) | BO3: =IF(OR($A3="",$BD3=0),0,($AY3*Templates!$G$27/$BE3+$AZ3*Templates!$G$28/$BF3+$BA3*Templates!$G$29/$BG3+$BB3*Templates!$G$30/$BH3+$BC3*Templates!$G$31/$BI3)/Templates!$B$22) | BP3: =IF(OR($A3="",$BD3=0),0,($AY3*Templates!$H$27/$BE3+$AZ3*Templates!$H$28/$BF3+$BA3*Templates!$H$29/$BG3+$BB3*Templates!$H$30/$BH3+$BC3*Templates!$H$31/$BI3)/Templates!$B$23)
A4: 360_2 | B4: 360 Behavioral Health | C4: 360 Behavioral Health | E4: No | F4: Active | H4: 1 | Q4: =IF($A4="","",COUNTIFS(Assignments!$C$2:$C$769,$A4,Assignments!$G$2:$G$769,"Active")) | R4: =IF($A4="","",SUMIFS(Assignments!$I$2:$I$769,Assignments!$C$2:$C$769,$A4,Assignments!$G$2:$G$769,"Active")) | S4: WIP | V4: =IF($U4="","",IFERROR(INDEX(Templates!$K$3:$K$10,MATCH($U4,Templates!$A$3:$A$10,0)),"")) | W4: =IF($U4="","",IFERROR(INDEX(Templates!$L$3:$L$10,MATCH($U4,Templates!$A$3:$A$10,0)),"")) | X4: =IF($U4="","",IFERROR(INDEX(Templates!$J$3:$J$10,MATCH($U4,Templates!$A$3:$A$10,0)),"")) | Y4: =IF(OR($U4="",$I4="",$J4="",$X4=""),"",$I4+$X4*($J4-$I4)) | Z4: 46212 | AD4: =IF($A4="","",IF($AA4="",$H4,$AA4)) | AE4: =IF($A4="","",IF($AB4="",$I4,$AB4)) | AF4: =IF($A4="","",IF($AC4="",$J4,$AC4)) | AG4: =IF(OR($U4="",$AE4="",$AF4="",$X4=""),"",$AE4+$X4*($AF4-$AE4)) | BD4: =IF($A4="","",SUM($AY4:$BC4)) | BE4: =IF($A4="","",IF(AND($I4<>"",$J4<>""),MAX(1,($J4-$I4)/7),Templates!$B$35)) | BF4: =IF($A4="","",IF(AND($I4<>"",$J4<>""),MAX(1,($J4-$I4)/7),Templates!$B$36)) | BG4: =IF($A4="","",IF(AND($I4<>"",$J4<>""),MAX(1,($J4-$I4)/7),Templates!$B$37)) | BH4: =IF($A4="","",IF(AND($I4<>"",$J4<>""),MAX(1,($J4-$I4)/7),Templates!$B$38)) | BI4: =IF($A4="","",IF(AND($I4<>"",$J4<>""),MAX(1,($J4-$I4)/7),Templates!$B$39)) | BJ4: =IF(OR($A4="",$BD4=0),0,($AY4*Templates!$B$27/$BE4+$AZ4*Templates!$B$28/$BF4+$BA4*Templates!$B$29/$BG4+$BB4*Templates!$B$30/$BH4+$BC4*Templates!$B$31/$BI4)/Templates!$B$17) | BK4: =IF(OR($A4="",$BD4=0),0,($AY4*Templates!$C$27/$BE4+$AZ4*Templates!$C$28/$BF4+$BA4*Templates!$C$29/$BG4+$BB4*Templates!$C$30/$BH4+$BC4*Templates!$C$31/$BI4)/Templates!$B$18) | BL4: =IF(OR($A4="",$BD4=0),0,($AY4*Templates!$D$27/$BE4+$AZ4*Templates!$D$28/$BF4+$BA4*Templates!$D$29/$BG4+$BB4*Templates!$D$30/$BH4+$BC4*Templates!$D$31/$BI4)/Templates!$B$19) | BM4: =IF(OR($A4="",$BD4=0),0,($AY4*Templates!$E$27/$BE4+$AZ4*Templates!$E$28/$BF4+$BA4*Templates!$E$29/$BG4+$BB4*Templates!$E$30/$BH4+$BC4*Templates!$E$31/$BI4)/Templates!$B$20) | BN4: =IF(OR($A4="",$BD4=0),0,($AY4*Templates!$F$27/$BE4+$AZ4*Templates!$F$28/$BF4+$BA4*Templates!$F$29/$BG4+$BB4*Templates!$F$30/$BH4+$BC4*Templates!$F$31/$BI4)/Templates!$B$21) | BO4: =IF(OR($A4="",$BD4=0),0,($AY4*Templates!$G$27/$BE4+$AZ4*Templates!$G$28/$BF4+$BA4*Templates!$G$29/$BG4+$BB4*Templates!$G$30/$BH4+$BC4*Templates!$G$31/$BI4)/Templates!$B$22) | BP4: =IF(OR($A4="",$BD4=0),0,($AY4*Templates!$H$27/$BE4+$AZ4*Templates!$H$28/$BF4+$BA4*Templates!$H$29/$BG4+$BB4*Templates!$H$30/$BH4+$BC4*Templates!$H$31/$BI4)/Templates!$B$23)
A5: 5C Ocean_1 | B5: 5C AI Group Inc. | C5: 5C AI Group Inc. | E5: No | F5: Active | H5: 1 | Q5: =IF($A5="","",COUNTIFS(Assignments!$C$2:$C$769,$A5,Assignments!$G$2:$G$769,"Active")) | R5: =IF($A5="","",SUMIFS(Assignments!$I$2:$I$769,Assignments!$C$2:$C$769,$A5,Assignments!$G$2:$G$769,"Active")) | S5: WIP | V5: =IF($U5="","",IFERROR(INDEX(Templates!$K$3:$K$10,MATCH($U5,Templates!$A$3:$A$10,0)),"")) | W5: =IF($U5="","",IFERROR(INDEX(Templates!$L$3:$L$10,MATCH($U5,Templates!$A$3:$A$10,0)),"")) | X5: =IF($U5="","",IFERROR(INDEX(Templates!$J$3:$J$10,MATCH($U5,Templates!$A$3:$A$10,0)),"")) | Y5: =IF(OR($U5="",$I5="",$J5="",$X5=""),"",$I5+$X5*($J5-$I5)) | Z5: 46212 | AD5: =IF($A5="","",IF($AA5="",$H5,$AA5)) | AE5: =IF($A5="","",IF($AB5="",$I5,$AB5)) | AF5: =IF($A5="","",IF($AC5="",$J5,$AC5)) | AG5: =IF(OR($U5="",$AE5="",$AF5="",$X5=""),"",$AE5+$X5*($AF5-$AE5)) | BD5: =IF($A5="","",SUM($AY5:$BC5)) | BE5: =IF($A5="","",IF(AND($I5<>"",$J5<>""),MAX(1,($J5-$I5)/7),Templates!$B$35)) | BF5: =IF($A5="","",IF(AND($I5<>"",$J5<>""),MAX(1,($J5-$I5)/7),Templates!$B$36)) | BG5: =IF($A5="","",IF(AND($I5<>"",$J5<>""),MAX(1,($J5-$I5)/7),Templates!$B$37)) | BH5: =IF($A5="","",IF(AND($I5<>"",$J5<>""),MAX(1,($J5-$I5)/7),Templates!$B$38)) | BI5: =IF($A5="","",IF(AND($I5<>"",$J5<>""),MAX(1,($J5-$I5)/7),Templates!$B$39)) | BJ5: =IF(OR($A5="",$BD5=0),0,($AY5*Templates!$B$27/$BE5+$AZ5*Templates!$B$28/$BF5+$BA5*Templates!$B$29/$BG5+$BB5*Templates!$B$30/$BH5+$BC5*Templates!$B$31/$BI5)/Templates!$B$17) | BK5: =IF(OR($A5="",$BD5=0),0,($AY5*Templates!$C$27/$BE5+$AZ5*Templates!$C$28/$BF5+$BA5*Templates!$C$29/$BG5+$BB5*Templates!$C$30/$BH5+$BC5*Templates!$C$31/$BI5)/Templates!$B$18) | BL5: =IF(OR($A5="",$BD5=0),0,($AY5*Templates!$D$27/$BE5+$AZ5*Templates!$D$28/$BF5+$BA5*Templates!$D$29/$BG5+$BB5*Templates!$D$30/$BH5+$BC5*Templates!$D$31/$BI5)/Templates!$B$19) | BM5: =IF(OR($A5="",$BD5=0),0,($AY5*Templates!$E$27/$BE5+$AZ5*Templates!$E$28/$BF5+$BA5*Templates!$E$29/$BG5+$BB5*Templates!$E$30/$BH5+$BC5*Templates!$E$31/$BI5)/Templates!$B$20) | BN5: =IF(OR($A5="",$BD5=0),0,($AY5*Templates!$F$27/$BE5+$AZ5*Templates!$F$28/$BF5+$BA5*Templates!$F$29/$BG5+$BB5*Templates!$F$30/$BH5+$BC5*Templates!$F$31/$BI5)/Templates!$B$21) | BO5: =IF(OR($A5="",$BD5=0),0,($AY5*Templates!$G$27/$BE5+$AZ5*Templates!$G$28/$BF5+$BA5*Templates!$G$29/$BG5+$BB5*Templates!$G$30/$BH5+$BC5*Templates!$G$31/$BI5)/Templates!$B$22) | BP5: =IF(OR($A5="",$BD5=0),0,($AY5*Templates!$H$27/$BE5+$AZ5*Templates!$H$28/$BF5+$BA5*Templates!$H$29/$BG5+$BB5*Templates!$H$30/$BH5+$BC5*Templates!$H$31/$BI5)/Templates!$B$23)
A6: 80/20 Assistance_1 | B6: CVC Capital Partners : DIF Capital Partners | C6: CVC Capital Partners | D6: DIF Capital Partners | E6: No | F6: Active | H6: 1 | Q6: =IF($A6="","",COUNTIFS(Assignments!$C$2:$C$769,$A6,Assignments!$G$2:$G$769,"Active")) | R6: =IF($A6="","",SUMIFS(Assignments!$I$2:$I$769,Assignments!$C$2:$C$769,$A6,Assignments!$G$2:$G$769,"Active")) | S6: WIP | V6: =IF($U6="","",IFERROR(INDEX(Templates!$K$3:$K$10,MATCH($U6,Templates!$A$3:$A$10,0)),"")) | W6: =IF($U6="","",IFERROR(INDEX(Templates!$L$3:$L$10,MATCH($U6,Templates!$A$3:$A$10,0)),"")) | X6: =IF($U6="","",IFERROR(INDEX(Templates!$J$3:$J$10,MATCH($U6,Templates!$A$3:$A$10,0)),"")) | Y6: =IF(OR($U6="",$I6="",$J6="",$X6=""),"",$I6+$X6*($J6-$I6)) | Z6: 46212 | AD6: =IF($A6="","",IF($AA6="",$H6,$AA6)) | AE6: =IF($A6="","",IF($AB6="",$I6,$AB6)) | AF6: =IF($A6="","",IF($AC6="",$J6,$AC6)) | AG6: =IF(OR($U6="",$AE6="",$AF6="",$X6=""),"",$AE6+$X6*($AF6-$AE6)) | BD6: =IF($A6="","",SUM($AY6:$BC6)) | BE6: =IF($A6="","",IF(AND($I6<>"",$J6<>""),MAX(1,($J6-$I6)/7),Templates!$B$35)) | BF6: =IF($A6="","",IF(AND($I6<>"",$J6<>""),MAX(1,($J6-$I6)/7),Templates!$B$36)) | BG6: =IF($A6="","",IF(AND($I6<>"",$J6<>""),MAX(1,($J6-$I6)/7),Templates!$B$37)) | BH6: =IF($A6="","",IF(AND($I6<>"",$J6<>""),MAX(1,($J6-$I6)/7),Templates!$B$38)) | BI6: =IF($A6="","",IF(AND($I6<>"",$J6<>""),MAX(1,($J6-$I6)/7),Templates!$B$39)) | BJ6: =IF(OR($A6="",$BD6=0),0,($AY6*Templates!$B$27/$BE6+$AZ6*Templates!$B$28/$BF6+$BA6*Templates!$B$29/$BG6+$BB6*Templates!$B$30/$BH6+$BC6*Templates!$B$31/$BI6)/Templates!$B$17) | BK6: =IF(OR($A6="",$BD6=0),0,($AY6*Templates!$C$27/$BE6+$AZ6*Templates!$C$28/$BF6+$BA6*Templates!$C$29/$BG6+$BB6*Templates!$C$30/$BH6+$BC6*Templates!$C$31/$BI6)/Templates!$B$18) | BL6: =IF(OR($A6="",$BD6=0),0,($AY6*Templates!$D$27/$BE6+$AZ6*Templates!$D$28/$BF6+$BA6*Templates!$D$29/$BG6+$BB6*Templates!$D$30/$BH6+$BC6*Templates!$D$31/$BI6)/Templates!$B$19) | BM6: =IF(OR($A6="",$BD6=0),0,($AY6*Templates!$E$27/$BE6+$AZ6*Templates!$E$28/$BF6+$BA6*Templates!$E$29/$BG6+$BB6*Templates!$E$30/$BH6+$BC6*Templates!$E$31/$BI6)/Templates!$B$20) | BN6: =IF(OR($A6="",$BD6=0),0,($AY6*Templates!$F$27/$BE6+$AZ6*Templates!$F$28/$BF6+$BA6*Templates!$F$29/$BG6+$BB6*Templates!$F$30/$BH6+$BC6*Templates!$F$31/$BI6)/Templates!$B$21) | BO6: =IF(OR($A6="",$BD6=0),0,($AY6*Templates!$G$27/$BE6+$AZ6*Templates!$G$28/$BF6+$BA6*Templates!$G$29/$BG6+$BB6*Templates!$G$30/$BH6+$BC6*Templates!$G$31/$BI6)/Templates!$B$22) | BP6: =IF(OR($A6="",$BD6=0),0,($AY6*Templates!$H$27/$BE6+$AZ6*Templates!$H$28/$BF6+$BA6*Templates!$H$29/$BG6+$BB6*Templates!$H$30/$BH6+$BC6*Templates!$H$31/$BI6)/Templates!$B$23)
A7: Adanac_1 | B7: Walk-On Capital | C7: Walk-On Capital | E7: No | F7: Active | H7: 1 | Q7: =IF($A7="","",COUNTIFS(Assignments!$C$2:$C$769,$A7,Assignments!$G$2:$G$769,"Active")) | R7: =IF($A7="","",SUMIFS(Assignments!$I$2:$I$769,Assignments!$C$2:$C$769,$A7,Assignments!$G$2:$G$769,"Active")) | S7: WIP | V7: =IF($U7="","",IFERROR(INDEX(Templates!$K$3:$K$10,MATCH($U7,Templates!$A$3:$A$10,0)),"")) | W7: =IF($U7="","",IFERROR(INDEX(Templates!$L$3:$L$10,MATCH($U7,Templates!$A$3:$A$10,0)),"")) | X7: =IF($U7="","",IFERROR(INDEX(Templates!$J$3:$J$10,MATCH($U7,Templates!$A$3:$A$10,0)),"")) | Y7: =IF(OR($U7="",$I7="",$J7="",$X7=""),"",$I7+$X7*($J7-$I7)) | Z7: 46212 | AD7: =IF($A7="","",IF($AA7="",$H7,$AA7)) | AE7: =IF($A7="","",IF($AB7="",$I7,$AB7)) | AF7: =IF($A7="","",IF($AC7="",$J7,$AC7)) | AG7: =IF(OR($U7="",$AE7="",$AF7="",$X7=""),"",$AE7+$X7*($AF7-$AE7)) | BD7: =IF($A7="","",SUM($AY7:$BC7)) | BE7: =IF($A7="","",IF(AND($I7<>"",$J7<>""),MAX(1,($J7-$I7)/7),Templates!$B$35)) | BF7: =IF($A7="","",IF(AND($I7<>"",$J7<>""),MAX(1,($J7-$I7)/7),Templates!$B$36)) | BG7: =IF($A7="","",IF(AND($I7<>"",$J7<>""),MAX(1,($J7-$I7)/7),Templates!$B$37)) | BH7: =IF($A7="","",IF(AND($I7<>"",$J7<>""),MAX(1,($J7-$I7)/7),Templates!$B$38)) | BI7: =IF($A7="","",IF(AND($I7<>"",$J7<>""),MAX(1,($J7-$I7)/7),Templates!$B$39)) | BJ7: =IF(OR($A7="",$BD7=0),0,($AY7*Templates!$B$27/$BE7+$AZ7*Templates!$B$28/$BF7+$BA7*Templates!$B$29/$BG7+$BB7*Templates!$B$30/$BH7+$BC7*Templates!$B$31/$BI7)/Templates!$B$17) | BK7: =IF(OR($A7="",$BD7=0),0,($AY7*Templates!$C$27/$BE7+$AZ7*Templates!$C$28/$BF7+$BA7*Templates!$C$29/$BG7+$BB7*Templates!$C$30/$BH7+$BC7*Templates!$C$31/$BI7)/Templates!$B$18) | BL7: =IF(OR($A7="",$BD7=0),0,($AY7*Templates!$D$27/$BE7+$AZ7*Templates!$D$28/$BF7+$BA7*Templates!$D$29/$BG7+$BB7*Templates!$D$30/$BH7+$BC7*Templates!$D$31/$BI7)/Templates!$B$19) | BM7: =IF(OR($A7="",$BD7=0),0,($AY7*Templates!$E$27/$BE7+$AZ7*Templates!$E$28/$BF7+$BA7*Templates!$E$29/$BG7+$BB7*Templates!$E$30/$BH7+$BC7*Templates!$E$31/$BI7)/Templates!$B$20) | BN7: =IF(OR($A7="",$BD7=0),0,($AY7*Templates!$F$27/$BE7+$AZ7*Templates!$F$28/$BF7+$BA7*Templates!$F$29/$BG7+$BB7*Templates!$F$30/$BH7+$BC7*Templates!$F$31/$BI7)/Templates!$B$21) | BO7: =IF(OR($A7="",$BD7=0),0,($AY7*Templates!$G$27/$BE7+$AZ7*Templates!$G$28/$BF7+$BA7*Templates!$G$29/$BG7+$BB7*Templates!$G$30/$BH7+$BC7*Templates!$G$31/$BI7)/Templates!$B$22) | BP7: =IF(OR($A7="",$BD7=0),0,($AY7*Templates!$H$27/$BE7+$AZ7*Templates!$H$28/$BF7+$BA7*Templates!$H$29/$BG7+$BB7*Templates!$H$30/$BH7+$BC7*Templates!$H$31/$BI7)/Templates!$B$23)
A8: Advantage_1 | B8: Q-Energy Private Equity | C8: Q-Energy Private Equity | E8: No | F8: Active | H8: 1 | Q8: =IF($A8="","",COUNTIFS(Assignments!$C$2:$C$769,$A8,Assignments!$G$2:$G$769,"Active")) | R8: =IF($A8="","",SUMIFS(Assignments!$I$2:$I$769,Assignments!$C$2:$C$769,$A8,Assignments!$G$2:$G$769,"Active")) | S8: WIP | V8: =IF($U8="","",IFERROR(INDEX(Templates!$K$3:$K$10,MATCH($U8,Templates!$A$3:$A$10,0)),"")) | W8: =IF($U8="","",IFERROR(INDEX(Templates!$L$3:$L$10,MATCH($U8,Templates!$A$3:$A$10,0)),"")) | X8: =IF($U8="","",IFERROR(INDEX(Templates!$J$3:$J$10,MATCH($U8,Templates!$A$3:$A$10,0)),"")) | Y8: =IF(OR($U8="",$I8="",$J8="",$X8=""),"",$I8+$X8*($J8-$I8)) | Z8: 46212 | AD8: =IF($A8="","",IF($AA8="",$H8,$AA8)) | AE8: =IF($A8="","",IF($AB8="",$I8,$AB8)) | AF8: =IF($A8="","",IF($AC8="",$J8,$AC8)) | AG8: =IF(OR($U8="",$AE8="",$AF8="",$X8=""),"",$AE8+$X8*($AF8-$AE8)) | BD8: =IF($A8="","",SUM($AY8:$BC8)) | BE8: =IF($A8="","",IF(AND($I8<>"",$J8<>""),MAX(1,($J8-$I8)/7),Templates!$B$35)) | BF8: =IF($A8="","",IF(AND($I8<>"",$J8<>""),MAX(1,($J8-$I8)/7),Templates!$B$36)) | BG8: =IF($A8="","",IF(AND($I8<>"",$J8<>""),MAX(1,($J8-$I8)/7),Templates!$B$37)) | BH8: =IF($A8="","",IF(AND($I8<>"",$J8<>""),MAX(1,($J8-$I8)/7),Templates!$B$38)) | BI8: =IF($A8="","",IF(AND($I8<>"",$J8<>""),MAX(1,($J8-$I8)/7),Templates!$B$39)) | BJ8: =IF(OR($A8="",$BD8=0),0,($AY8*Templates!$B$27/$BE8+$AZ8*Templates!$B$28/$BF8+$BA8*Templates!$B$29/$BG8+$BB8*Templates!$B$30/$BH8+$BC8*Templates!$B$31/$BI8)/Templates!$B$17) | BK8: =IF(OR($A8="",$BD8=0),0,($AY8*Templates!$C$27/$BE8+$AZ8*Templates!$C$28/$BF8+$BA8*Templates!$C$29/$BG8+$BB8*Templates!$C$30/$BH8+$BC8*Templates!$C$31/$BI8)/Templates!$B$18) | BL8: =IF(OR($A8="",$BD8=0),0,($AY8*Templates!$D$27/$BE8+$AZ8*Templates!$D$28/$BF8+$BA8*Templates!$D$29/$BG8+$BB8*Templates!$D$30/$BH8+$BC8*Templates!$D$31/$BI8)/Templates!$B$19) | BM8: =IF(OR($A8="",$BD8=0),0,($AY8*Templates!$E$27/$BE8+$AZ8*Templates!$E$28/$BF8+$BA8*Templates!$E$29/$BG8+$BB8*Templates!$E$30/$BH8+$BC8*Templates!$E$31/$BI8)/Templates!$B$20) | BN8: =IF(OR($A8="",$BD8=0),0,($AY8*Templates!$F$27/$BE8+$AZ8*Templates!$F$28/$BF8+$BA8*Templates!$F$29/$BG8+$BB8*Templates!$F$30/$BH8+$BC8*Templates!$F$31/$BI8)/Templates!$B$21) | BO8: =IF(OR($A8="",$BD8=0),0,($AY8*Templates!$G$27/$BE8+$AZ8*Templates!$G$28/$BF8+$BA8*Templates!$G$29/$BG8+$BB8*Templates!$G$30/$BH8+$BC8*Templates!$G$31/$BI8)/Templates!$B$22) | BP8: =IF(OR($A8="",$BD8=0),0,($AY8*Templates!$H$27/$BE8+$AZ8*Templates!$H$28/$BF8+$BA8*Templates!$H$29/$BG8+$BB8*Templates!$H$30/$BH8+$BC8*Templates!$H$31/$BI8)/Templates!$B$23)
A9: AIM_5 | B9: Eight Advisory | C9: Eight Advisory | E9: No | F9: Active | H9: 1 | Q9: =IF($A9="","",COUNTIFS(Assignments!$C$2:$C$769,$A9,Assignments!$G$2:$G$769,"Active")) | R9: =IF($A9="","",SUMIFS(Assignments!$I$2:$I$769,Assignments!$C$2:$C$769,$A9,Assignments!$G$2:$G$769,"Active")) | S9: WIP | V9: =IF($U9="","",IFERROR(INDEX(Templates!$K$3:$K$10,MATCH($U9,Templates!$A$3:$A$10,0)),"")) | W9: =IF($U9="","",IFERROR(INDEX(Templates!$L$3:$L$10,MATCH($U9,Templates!$A$3:$A$10,0)),"")) | X9: =IF($U9="","",IFERROR(INDEX(Templates!$J$3:$J$10,MATCH($U9,Templates!$A$3:$A$10,0)),"")) | Y9: =IF(OR($U9="",$I9="",$J9="",$X9=""),"",$I9+$X9*($J9-$I9)) | Z9: 46212 | AD9: =IF($A9="","",IF($AA9="",$H9,$AA9)) | AE9: =IF($A9="","",IF($AB9="",$I9,$AB9)) | AF9: =IF($A9="","",IF($AC9="",$J9,$AC9)) | AG9: =IF(OR($U9="",$AE9="",$AF9="",$X9=""),"",$AE9+$X9*($AF9-$AE9)) | BD9: =IF($A9="","",SUM($AY9:$BC9)) | BE9: =IF($A9="","",IF(AND($I9<>"",$J9<>""),MAX(1,($J9-$I9)/7),Templates!$B$35)) | BF9: =IF($A9="","",IF(AND($I9<>"",$J9<>""),MAX(1,($J9-$I9)/7),Templates!$B$36)) | BG9: =IF($A9="","",IF(AND($I9<>"",$J9<>""),MAX(1,($J9-$I9)/7),Templates!$B$37)) | BH9: =IF($A9="","",IF(AND($I9<>"",$J9<>""),MAX(1,($J9-$I9)/7),Templates!$B$38)) | BI9: =IF($A9="","",IF(AND($I9<>"",$J9<>""),MAX(1,($J9-$I9)/7),Templates!$B$39)) | BJ9: =IF(OR($A9="",$BD9=0),0,($AY9*Templates!$B$27/$BE9+$AZ9*Templates!$B$28/$BF9+$BA9*Templates!$B$29/$BG9+$BB9*Templates!$B$30/$BH9+$BC9*Templates!$B$31/$BI9)/Templates!$B$17) | BK9: =IF(OR($A9="",$BD9=0),0,($AY9*Templates!$C$27/$BE9+$AZ9*Templates!$C$28/$BF9+$BA9*Templates!$C$29/$BG9+$BB9*Templates!$C$30/$BH9+$BC9*Templates!$C$31/$BI9)/Templates!$B$18) | BL9: =IF(OR($A9="",$BD9=0),0,($AY9*Templates!$D$27/$BE9+$AZ9*Templates!$D$28/$BF9+$BA9*Templates!$D$29/$BG9+$BB9*Templates!$D$30/$BH9+$BC9*Templates!$D$31/$BI9)/Templates!$B$19) | BM9: =IF(OR($A9="",$BD9=0),0,($AY9*Templates!$E$27/$BE9+$AZ9*Templates!$E$28/$BF9+$BA9*Templates!$E$29/$BG9+$BB9*Templates!$E$30/$BH9+$BC9*Templates!$E$31/$BI9)/Templates!$B$20) | BN9: =IF(OR($A9="",$BD9=0),0,($AY9*Templates!$F$27/$BE9+$AZ9*Templates!$F$28/$BF9+$BA9*Templates!$F$29/$BG9+$BB9*Templates!$F$30/$BH9+$BC9*Templates!$F$31/$BI9)/Templates!$B$21) | BO9: =IF(OR($A9="",$BD9=0),0,($AY9*Templates!$G$27/$BE9+$AZ9*Templates!$G$28/$BF9+$BA9*Templates!$G$29/$BG9+$BB9*Templates!$G$30/$BH9+$BC9*Templates!$G$31/$BI9)/Templates!$B$22) | BP9: =IF(OR($A9="",$BD9=0),0,($AY9*Templates!$H$27/$BE9+$AZ9*Templates!$H$28/$BF9+$BA9*Templates!$H$29/$BG9+$BB9*Templates!$H$30/$BH9+$BC9*Templates!$H$31/$BI9)/Templates!$B$23)
A10: Atlas_4 | B10: Strattam Capital Management LLC | C10: Strattam Capital Management LLC | E10: No | F10: Active | H10: 1 | Q10: =IF($A10="","",COUNTIFS(Assignments!$C$2:$C$769,$A10,Assignments!$G$2:$G$769,"Active")) | R10: =IF($A10="","",SUMIFS(Assignments!$I$2:$I$769,Assignments!$C$2:$C$769,$A10,Assignments!$G$2:$G$769,"Active")) | S10: WIP | V10: =IF($U10="","",IFERROR(INDEX(Templates!$K$3:$K$10,MATCH($U10,Templates!$A$3:$A$10,0)),"")) | W10: =IF($U10="","",IFERROR(INDEX(Templates!$L$3:$L$10,MATCH($U10,Templates!$A$3:$A$10,0)),"")) | X10: =IF($U10="","",IFERROR(INDEX(Templates!$J$3:$J$10,MATCH($U10,Templates!$A$3:$A$10,0)),"")) | Y10: =IF(OR($U10="",$I10="",$J10="",$X10=""),"",$I10+$X10*($J10-$I10)) | Z10: 46212 | AD10: =IF($A10="","",IF($AA10="",$H10,$AA10)) | AE10: =IF($A10="","",IF($AB10="",$I10,$AB10)) | AF10: =IF($A10="","",IF($AC10="",$J10,$AC10)) | AG10: =IF(OR($U10="",$AE10="",$AF10="",$X10=""),"",$AE10+$X10*($AF10-$AE10)) | BD10: =IF($A10="","",SUM($AY10:$BC10)) | BE10: =IF($A10="","",IF(AND($I10<>"",$J10<>""),MAX(1,($J10-$I10)/7),Templates!$B$35)) | BF10: =IF($A10="","",IF(AND($I10<>"",$J10<>""),MAX(1,($J10-$I10)/7),Templates!$B$36)) | BG10: =IF($A10="","",IF(AND($I10<>"",$J10<>""),MAX(1,($J10-$I10)/7),Templates!$B$37)) | BH10: =IF($A10="","",IF(AND($I10<>"",$J10<>""),MAX(1,($J10-$I10)/7),Templates!$B$38)) | BI10: =IF($A10="","",IF(AND($I10<>"",$J10<>""),MAX(1,($J10-$I10)/7),Templates!$B$39)) | BJ10: =IF(OR($A10="",$BD10=0),0,($AY10*Templates!$B$27/$BE10+$AZ10*Templates!$B$28/$BF10+$BA10*Templates!$B$29/$BG10+$BB10*Templates!$B$30/$BH10+$BC10*Templates!$B$31/$BI10)/Templates!$B$17) | BK10: =IF(OR($A10="",$BD10=0),0,($AY10*Templates!$C$27/$BE10+$AZ10*Templates!$C$28/$BF10+$BA10*Templates!$C$29/$BG10+$BB10*Templates!$C$30/$BH10+$BC10*Templates!$C$31/$BI10)/Templates!$B$18) | BL10: =IF(OR($A10="",$BD10=0),0,($AY10*Templates!$D$27/$BE10+$AZ10*Templates!$D$28/$BF10+$BA10*Templates!$D$29/$BG10+$BB10*Templates!$D$30/$BH10+$BC10*Templates!$D$31/$BI10)/Templates!$B$19) | BM10: =IF(OR($A10="",$BD10=0),0,($AY10*Templates!$E$27/$BE10+$AZ10*Templates!$E$28/$BF10+$BA10*Templates!$E$29/$BG10+$BB10*Templates!$E$30/$BH10+$BC10*Templates!$E$31/$BI10)/Templates!$B$20) | BN10: =IF(OR($A10="",$BD10=0),0,($AY10*Templates!$F$27/$BE10+$AZ10*Templates!$F$28/$BF10+$BA10*Templates!$F$29/$BG10+$BB10*Templates!$F$30/$BH10+$BC10*Templates!$F$31/$BI10)/Templates!$B$21) | BO10: =IF(OR($A10="",$BD10=0),0,($AY10*Templates!$G$27/$BE10+$AZ10*Templates!$G$28/$BF10+$BA10*Templates!$G$29/$BG10+$BB10*Templates!$G$30/$BH10+$BC10*Templates!$G$31/$BI10)/Templates!$B$22) | BP10: =IF(OR($A10="",$BD10=0),0,($AY10*Templates!$H$27/$BE10+$AZ10*Templates!$H$28/$BF10+$BA10*Templates!$H$29/$BG10+$BB10*Templates!$H$30/$BH10+$BC10*Templates!$H$31/$BI10)/Templates!$B$23)
A11: Aypa_3 | B11: The Blackstone Group : Aypa Power | C11: The Blackstone Group | D11: Aypa Power | E11: No | F11: Active | H11: 1 | Q11: =IF($A11="","",COUNTIFS(Assignments!$C$2:$C$769,$A11,Assignments!$G$2:$G$769,"Active")) | R11: =IF($A11="","",SUMIFS(Assignments!$I$2:$I$769,Assignments!$C$2:$C$769,$A11,Assignments!$G$2:$G$769,"Active")) | S11: WIP | V11: =IF($U11="","",IFERROR(INDEX(Templates!$K$3:$K$10,MATCH($U11,Templates!$A$3:$A$10,0)),"")) | W11: =IF($U11="","",IFERROR(INDEX(Templates!$L$3:$L$10,MATCH($U11,Templates!$A$3:$A$10,0)),"")) | X11: =IF($U11="","",IFERROR(INDEX(Templates!$J$3:$J$10,MATCH($U11,Templates!$A$3:$A$10,0)),"")) | Y11: =IF(OR($U11="",$I11="",$J11="",$X11=""),"",$I11+$X11*($J11-$I11)) | Z11: 46212 | AD11: =IF($A11="","",IF($AA11="",$H11,$AA11)) | AE11: =IF($A11="","",IF($AB11="",$I11,$AB11)) | AF11: =IF($A11="","",IF($AC11="",$J11,$AC11)) | AG11: =IF(OR($U11="",$AE11="",$AF11="",$X11=""),"",$AE11+$X11*($AF11-$AE11)) | BD11: =IF($A11="","",SUM($AY11:$BC11)) | BE11: =IF($A11="","",IF(AND($I11<>"",$J11<>""),MAX(1,($J11-$I11)/7),Templates!$B$35)) | BF11: =IF($A11="","",IF(AND($I11<>"",$J11<>""),MAX(1,($J11-$I11)/7),Templates!$B$36)) | BG11: =IF($A11="","",IF(AND($I11<>"",$J11<>""),MAX(1,($J11-$I11)/7),Templates!$B$37)) | BH11: =IF($A11="","",IF(AND($I11<>"",$J11<>""),MAX(1,($J11-$I11)/7),Templates!$B$38)) | BI11: =IF($A11="","",IF(AND($I11<>"",$J11<>""),MAX(1,($J11-$I11)/7),Templates!$B$39)) | BJ11: =IF(OR($A11="",$BD11=0),0,($AY11*Templates!$B$27/$BE11+$AZ11*Templates!$B$28/$BF11+$BA11*Templates!$B$29/$BG11+$BB11*Templates!$B$30/$BH11+$BC11*Templates!$B$31/$BI11)/Templates!$B$17) | BK11: =IF(OR($A11="",$BD11=0),0,($AY11*Templates!$C$27/$BE11+$AZ11*Templates!$C$28/$BF11+$BA11*Templates!$C$29/$BG11+$BB11*Templates!$C$30/$BH11+$BC11*Templates!$C$31/$BI11)/Templates!$B$18) | BL11: =IF(OR($A11="",$BD11=0),0,($AY11*Templates!$D$27/$BE11+$AZ11*Templates!$D$28/$BF11+$BA11*Templates!$D$29/$BG11+$BB11*Templates!$D$30/$BH11+$BC11*Templates!$D$31/$BI11)/Templates!$B$19) | BM11: =IF(OR($A11="",$BD11=0),0,($AY11*Templates!$E$27/$BE11+$AZ11*Templates!$E$28/$BF11+$BA11*Templates!$E$29/$BG11+$BB11*Templates!$E$30/$BH11+$BC11*Templates!$E$31/$BI11)/Templates!$B$20) | BN11: =IF(OR($A11="",$BD11=0),0,($AY11*Templates!$F$27/$BE11+$AZ11*Templates!$F$28/$BF11+$BA11*Templates!$F$29/$BG11+$BB11*Templates!$F$30/$BH11+$BC11*Templates!$F$31/$BI11)/Templates!$B$21) | BO11: =IF(OR($A11="",$BD11=0),0,($AY11*Templates!$G$27/$BE11+$AZ11*Templates!$G$28/$BF11+$BA11*Templates!$G$29/$BG11+$BB11*Templates!$G$30/$BH11+$BC11*Templates!$G$31/$BI11)/Templates!$B$22) | BP11: =IF(OR($A11="",$BD11=0),0,($AY11*Templates!$H$27/$BE11+$AZ11*Templates!$H$28/$BF11+$BA11*Templates!$H$29/$BG11+$BB11*Templates!$H$30/$BH11+$BC11*Templates!$H$31/$BI11)/Templates!$B$23)
A12: B2V_1 | B12: Ares Management Corporation : AwayDay | C12: Ares Management Corporation | D12: AwayDay | E12: No | F12: Active | H12: 1 | Q12: =IF($A12="","",COUNTIFS(Assignments!$C$2:$C$769,$A12,Assignments!$G$2:$G$769,"Active")) | R12: =IF($A12="","",SUMIFS(Assignments!$I$2:$I$769,Assignments!$C$2:$C$769,$A12,Assignments!$G$2:$G$769,"Active")) | S12: WIP | V12: =IF($U12="","",IFERROR(INDEX(Templates!$K$3:$K$10,MATCH($U12,Templates!$A$3:$A$10,0)),"")) | W12: =IF($U12="","",IFERROR(INDEX(Templates!$L$3:$L$10,MATCH($U12,Templates!$A$3:$A$10,0)),"")) | X12: =IF($U12="","",IFERROR(INDEX(Templates!$J$3:$J$10,MATCH($U12,Templates!$A$3:$A$10,0)),"")) | Y12: =IF(OR($U12="",$I12="",$J12="",$X12=""),"",$I12+$X12*($J12-$I12)) | Z12: 46212 | AD12: =IF($A12="","",IF($AA12="",$H12,$AA12)) | AE12: =IF($A12="","",IF($AB12="",$I12,$AB12)) | AF12: =IF($A12="","",IF($AC12="",$J12,$AC12)) | AG12: =IF(OR($U12="",$AE12="",$AF12="",$X12=""),"",$AE12+$X12*($AF12-$AE12)) | BD12: =IF($A12="","",SUM($AY12:$BC12)) | BE12: =IF($A12="","",IF(AND($I12<>"",$J12<>""),MAX(1,($J12-$I12)/7),Templates!$B$35)) | BF12: =IF($A12="","",IF(AND($I12<>"",$J12<>""),MAX(1,($J12-$I12)/7),Templates!$B$36)) | BG12: =IF($A12="","",IF(AND($I12<>"",$J12<>""),MAX(1,($J12-$I12)/7),Templates!$B$37)) | BH12: =IF($A12="","",IF(AND($I12<>"",$J12<>""),MAX(1,($J12-$I12)/7),Templates!$B$38)) | BI12: =IF($A12="","",IF(AND($I12<>"",$J12<>""),MAX(1,($J12-$I12)/7),Templates!$B$39)) | BJ12: =IF(OR($A12="",$BD12=0),0,($AY12*Templates!$B$27/$BE12+$AZ12*Templates!$B$28/$BF12+$BA12*Templates!$B$29/$BG12+$BB12*Templates!$B$30/$BH12+$BC12*Templates!$B$31/$BI12)/Templates!$B$17) | BK12: =IF(OR($A12="",$BD12=0),0,($AY12*Templates!$C$27/$BE12+$AZ12*Templates!$C$28/$BF12+$BA12*Templates!$C$29/$BG12+$BB12*Templates!$C$30/$BH12+$BC12*Templates!$C$31/$BI12)/Templates!$B$18) | BL12: =IF(OR($A12="",$BD12=0),0,($AY12*Templates!$D$27/$BE12+$AZ12*Templates!$D$28/$BF12+$BA12*Templates!$D$29/$BG12+$BB12*Templates!$D$30/$BH12+$BC12*Templates!$D$31/$BI12)/Templates!$B$19) | BM12: =IF(OR($A12="",$BD12=0),0,($AY12*Templates!$E$27/$BE12+$AZ12*Templates!$E$28/$BF12+$BA12*Templates!$E$29/$BG12+$BB12*Templates!$E$30/$BH12+$BC12*Templates!$E$31/$BI12)/Templates!$B$20) | BN12: =IF(OR($A12="",$BD12=0),0,($AY12*Templates!$F$27/$BE12+$AZ12*Templates!$F$28/$BF12+$BA12*Templates!$F$29/$BG12+$BB12*Templates!$F$30/$BH12+$BC12*Templates!$F$31/$BI12)/Templates!$B$21) | BO12: =IF(OR($A12="",$BD12=0),0,($AY12*Templates!$G$27/$BE12+$AZ12*Templates!$G$28/$BF12+$BA12*Templates!$G$29/$BG12+$BB12*Templates!$G$30/$BH12+$BC12*Templates!$G$31/$BI12)/Templates!$B$22) | BP12: =IF(OR($A12="",$BD12=0),0,($AY12*Templates!$H$27/$BE12+$AZ12*Templates!$H$28/$BF12+$BA12*Templates!$H$29/$BG12+$BB12*Templates!$H$30/$BH12+$BC12*Templates!$H$31/$BI12)/Templates!$B$23)
A13: Bay_2 | B13: Manulife : John Hancock | C13: Manulife | D13: John Hancock | E13: No | F13: Active | H13: 1 | Q13: =IF($A13="","",COUNTIFS(Assignments!$C$2:$C$769,$A13,Assignments!$G$2:$G$769,"Active")) | R13: =IF($A13="","",SUMIFS(Assignments!$I$2:$I$769,Assignments!$C$2:$C$769,$A13,Assignments!$G$2:$G$769,"Active")) | S13: WIP | V13: =IF($U13="","",IFERROR(INDEX(Templates!$K$3:$K$10,MATCH($U13,Templates!$A$3:$A$10,0)),"")) | W13: =IF($U13="","",IFERROR(INDEX(Templates!$L$3:$L$10,MATCH($U13,Templates!$A$3:$A$10,0)),"")) | X13: =IF($U13="","",IFERROR(INDEX(Templates!$J$3:$J$10,MATCH($U13,Templates!$A$3:$A$10,0)),"")) | Y13: =IF(OR($U13="",$I13="",$J13="",$X13=""),"",$I13+$X13*($J13-$I13)) | Z13: 46212 | AD13: =IF($A13="","",IF($AA13="",$H13,$AA13)) | AE13: =IF($A13="","",IF($AB13="",$I13,$AB13)) | AF13: =IF($A13="","",IF($AC13="",$J13,$AC13)) | AG13: =IF(OR($U13="",$AE13="",$AF13="",$X13=""),"",$AE13+$X13*($AF13-$AE13)) | BD13: =IF($A13="","",SUM($AY13:$BC13)) | BE13: =IF($A13="","",IF(AND($I13<>"",$J13<>""),MAX(1,($J13-$I13)/7),Templates!$B$35)) | BF13: =IF($A13="","",IF(AND($I13<>"",$J13<>""),MAX(1,($J13-$I13)/7),Templates!$B$36)) | BG13: =IF($A13="","",IF(AND($I13<>"",$J13<>""),MAX(1,($J13-$I13)/7),Templates!$B$37)) | BH13: =IF($A13="","",IF(AND($I13<>"",$J13<>""),MAX(1,($J13-$I13)/7),Templates!$B$38)) | BI13: =IF($A13="","",IF(AND($I13<>"",$J13<>""),MAX(1,($J13-$I13)/7),Templates!$B$39)) | BJ13: =IF(OR($A13="",$BD13=0),0,($AY13*Templates!$B$27/$BE13+$AZ13*Templates!$B$28/$BF13+$BA13*Templates!$B$29/$BG13+$BB13*Templates!$B$30/$BH13+$BC13*Templates!$B$31/$BI13)/Templates!$B$17) | BK13: =IF(OR($A13="",$BD13=0),0,($AY13*Templates!$C$27/$BE13+$AZ13*Templates!$C$28/$BF13+$BA13*Templates!$C$29/$BG13+$BB13*Templates!$C$30/$BH13+$BC13*Templates!$C$31/$BI13)/Templates!$B$18) | BL13: =IF(OR($A13="",$BD13=0),0,($AY13*Templates!$D$27/$BE13+$AZ13*Templates!$D$28/$BF13+$BA13*Templates!$D$29/$BG13+$BB13*Templates!$D$30/$BH13+$BC13*Templates!$D$31/$BI13)/Templates!$B$19) | BM13: =IF(OR($A13="",$BD13=0),0,($AY13*Templates!$E$27/$BE13+$AZ13*Templates!$E$28/$BF13+$BA13*Templates!$E$29/$BG13+$BB13*Templates!$E$30/$BH13+$BC13*Templates!$E$31/$BI13)/Templates!$B$20) | BN13: =IF(OR($A13="",$BD13=0),0,($AY13*Templates!$F$27/$BE13+$AZ13*Templates!$F$28/$BF13+$BA13*Templates!$F$29/$BG13+$BB13*Templates!$F$30/$BH13+$BC13*Templates!$F$31/$BI13)/Templates!$B$21) | BO13: =IF(OR($A13="",$BD13=0),0,($AY13*Templates!$G$27/$BE13+$AZ13*Templates!$G$28/$BF13+$BA13*Templates!$G$29/$BG13+$BB13*Templates!$G$30/$BH13+$BC13*Templates!$G$31/$BI13)/Templates!$B$22) | BP13: =IF(OR($A13="",$BD13=0),0,($AY13*Templates!$H$27/$BE13+$AZ13*Templates!$H$28/$BF13+$BA13*Templates!$H$29/$BG13+$BB13*Templates!$H$30/$BH13+$BC13*Templates!$H$31/$BI13)/Templates!$B$23)
A14: Bernhard_3 | B14: DIF Capital Partners | C14: DIF Capital Partners | E14: No | F14: Active | H14: 1 | Q14: =IF($A14="","",COUNTIFS(Assignments!$C$2:$C$769,$A14,Assignments!$G$2:$G$769,"Active")) | R14: =IF($A14="","",SUMIFS(Assignments!$I$2:$I$769,Assignments!$C$2:$C$769,$A14,Assignments!$G$2:$G$769,"Active")) | S14: WIP | V14: =IF($U14="","",IFERROR(INDEX(Templates!$K$3:$K$10,MATCH($U14,Templates!$A$3:$A$10,0)),"")) | W14: =IF($U14="","",IFERROR(INDEX(Templates!$L$3:$L$10,MATCH($U14,Templates!$A$3:$A$10,0)),"")) | X14: =IF($U14="","",IFERROR(INDEX(Templates!$J$3:$J$10,MATCH($U14,Templates!$A$3:$A$10,0)),"")) | Y14: =IF(OR($U14="",$I14="",$J14="",$X14=""),"",$I14+$X14*($J14-$I14)) | Z14: 46212 | AD14: =IF($A14="","",IF($AA14="",$H14,$AA14)) | AE14: =IF($A14="","",IF($AB14="",$I14,$AB14)) | AF14: =IF($A14="","",IF($AC14="",$J14,$AC14)) | AG14: =IF(OR($U14="",$AE14="",$AF14="",$X14=""),"",$AE14+$X14*($AF14-$AE14)) | BD14: =IF($A14="","",SUM($AY14:$BC14)) | BE14: =IF($A14="","",IF(AND($I14<>"",$J14<>""),MAX(1,($J14-$I14)/7),Templates!$B$35)) | BF14: =IF($A14="","",IF(AND($I14<>"",$J14<>""),MAX(1,($J14-$I14)/7),Templates!$B$36)) | BG14: =IF($A14="","",IF(AND($I14<>"",$J14<>""),MAX(1,($J14-$I14)/7),Templates!$B$37)) | BH14: =IF($A14="","",IF(AND($I14<>"",$J14<>""),MAX(1,($J14-$I14)/7),Templates!$B$38)) | BI14: =IF($A14="","",IF(AND($I14<>"",$J14<>""),MAX(1,($J14-$I14)/7),Templates!$B$39)) | BJ14: =IF(OR($A14="",$BD14=0),0,($AY14*Templates!$B$27/$BE14+$AZ14*Templates!$B$28/$BF14+$BA14*Templates!$B$29/$BG14+$BB14*Templates!$B$30/$BH14+$BC14*Templates!$B$31/$BI14)/Templates!$B$17) | BK14: =IF(OR($A14="",$BD14=0),0,($AY14*Templates!$C$27/$BE14+$AZ14*Templates!$C$28/$BF14+$BA14*Templates!$C$29/$BG14+$BB14*Templates!$C$30/$BH14+$BC14*Templates!$C$31/$BI14)/Templates!$B$18) | BL14: =IF(OR($A14="",$BD14=0),0,($AY14*Templates!$D$27/$BE14+$AZ14*Templates!$D$28/$BF14+$BA14*Templates!$D$29/$BG14+$BB14*Templates!$D$30/$BH14+$BC14*Templates!$D$31/$BI14)/Templates!$B$19) | BM14: =IF(OR($A14="",$BD14=0),0,($AY14*Templates!$E$27/$BE14+$AZ14*Templates!$E$28/$BF14+$BA14*Templates!$E$29/$BG14+$BB14*Templates!$E$30/$BH14+$BC14*Templates!$E$31/$BI14)/Templates!$B$20) | BN14: =IF(OR($A14="",$BD14=0),0,($AY14*Templates!$F$27/$BE14+$AZ14*Templates!$F$28/$BF14+$BA14*Templates!$F$29/$BG14+$BB14*Templates!$F$30/$BH14+$BC14*Templates!$F$31/$BI14)/Templates!$B$21) | BO14: =IF(OR($A14="",$BD14=0),0,($AY14*Templates!$G$27/$BE14+$AZ14*Templates!$G$28/$BF14+$BA14*Templates!$G$29/$BG14+$BB14*Templates!$G$30/$BH14+$BC14*Templates!$G$31/$BI14)/Templates!$B$22) | BP14: =IF(OR($A14="",$BD14=0),0,($AY14*Templates!$H$27/$BE14+$AZ14*Templates!$H$28/$BF14+$BA14*Templates!$H$29/$BG14+$BB14*Templates!$H$30/$BH14+$BC14*Templates!$H$31/$BI14)/Templates!$B$23)
A15: Big_4 | B15: Ethos Specialty Insurance Services | C15: Ethos Specialty Insurance Services | E15: No | F15: Active | H15: 1 | Q15: =IF($A15="","",COUNTIFS(Assignments!$C$2:$C$769,$A15,Assignments!$G$2:$G$769,"Active")) | R15: =IF($A15="","",SUMIFS(Assignments!$I$2:$I$769,Assignments!$C$2:$C$769,$A15,Assignments!$G$2:$G$769,"Active")) | S15: WIP | V15: =IF($U15="","",IFERROR(INDEX(Templates!$K$3:$K$10,MATCH($U15,Templates!$A$3:$A$10,0)),"")) | W15: =IF($U15="","",IFERROR(INDEX(Templates!$L$3:$L$10,MATCH($U15,Templates!$A$3:$A$10,0)),"")) | X15: =IF($U15="","",IFERROR(INDEX(Templates!$J$3:$J$10,MATCH($U15,Templates!$A$3:$A$10,0)),"")) | Y15: =IF(OR($U15="",$I15="",$J15="",$X15=""),"",$I15+$X15*($J15-$I15)) | Z15: 46212 | AD15: =IF($A15="","",IF($AA15="",$H15,$AA15)) | AE15: =IF($A15="","",IF($AB15="",$I15,$AB15)) | AF15: =IF($A15="","",IF($AC15="",$J15,$AC15)) | AG15: =IF(OR($U15="",$AE15="",$AF15="",$X15=""),"",$AE15+$X15*($AF15-$AE15)) | BD15: =IF($A15="","",SUM($AY15:$BC15)) | BE15: =IF($A15="","",IF(AND($I15<>"",$J15<>""),MAX(1,($J15-$I15)/7),Templates!$B$35)) | BF15: =IF($A15="","",IF(AND($I15<>"",$J15<>""),MAX(1,($J15-$I15)/7),Templates!$B$36)) | BG15: =IF($A15="","",IF(AND($I15<>"",$J15<>""),MAX(1,($J15-$I15)/7),Templates!$B$37)) | BH15: =IF($A15="","",IF(AND($I15<>"",$J15<>""),MAX(1,($J15-$I15)/7),Templates!$B$38)) | BI15: =IF($A15="","",IF(AND($I15<>"",$J15<>""),MAX(1,($J15-$I15)/7),Templates!$B$39)) | BJ15: =IF(OR($A15="",$BD15=0),0,($AY15*Templates!$B$27/$BE15+$AZ15*Templates!$B$28/$BF15+$BA15*Templates!$B$29/$BG15+$BB15*Templates!$B$30/$BH15+$BC15*Templates!$B$31/$BI15)/Templates!$B$17) | BK15: =IF(OR($A15="",$BD15=0),0,($AY15*Templates!$C$27/$BE15+$AZ15*Templates!$C$28/$BF15+$BA15*Templates!$C$29/$BG15+$BB15*Templates!$C$30/$BH15+$BC15*Templates!$C$31/$BI15)/Templates!$B$18) | BL15: =IF(OR($A15="",$BD15=0),0,($AY15*Templates!$D$27/$BE15+$AZ15*Templates!$D$28/$BF15+$BA15*Templates!$D$29/$BG15+$BB15*Templates!$D$30/$BH15+$BC15*Templates!$D$31/$BI15)/Templates!$B$19) | BM15: =IF(OR($A15="",$BD15=0),0,($AY15*Templates!$E$27/$BE15+$AZ15*Templates!$E$28/$BF15+$BA15*Templates!$E$29/$BG15+$BB15*Templates!$E$30/$BH15+$BC15*Templates!$E$31/$BI15)/Templates!$B$20) | BN15: =IF(OR($A15="",$BD15=0),0,($AY15*Templates!$F$27/$BE15+$AZ15*Templates!$F$28/$BF15+$BA15*Templates!$F$29/$BG15+$BB15*Templates!$F$30/$BH15+$BC15*Templates!$F$31/$BI15)/Templates!$B$21) | BO15: =IF(OR($A15="",$BD15=0),0,($AY15*Templates!$G$27/$BE15+$AZ15*Templates!$G$28/$BF15+$BA15*Templates!$G$29/$BG15+$BB15*Templates!$G$30/$BH15+$BC15*Templates!$G$31/$BI15)/Templates!$B$22) | BP15: =IF(OR($A15="",$BD15=0),0,($AY15*Templates!$H$27/$BE15+$AZ15*Templates!$H$28/$BF15+$BA15*Templates!$H$29/$BG15+$BB15*Templates!$H$30/$BH15+$BC15*Templates!$H$31/$BI15)/Templates!$B$23)
A16: Bishopville_1 | B16: Volante Transaction Services, North America | C16: Volante Transaction Services, North America | E16: No | F16: Active | H16: 1 | Q16: =IF($A16="","",COUNTIFS(Assignments!$C$2:$C$769,$A16,Assignments!$G$2:$G$769,"Active")) | R16: =IF($A16="","",SUMIFS(Assignments!$I$2:$I$769,Assignments!$C$2:$C$769,$A16,Assignments!$G$2:$G$769,"Active")) | S16: WIP | V16: =IF($U16="","",IFERROR(INDEX(Templates!$K$3:$K$10,MATCH($U16,Templates!$A$3:$A$10,0)),"")) | W16: =IF($U16="","",IFERROR(INDEX(Templates!$L$3:$L$10,MATCH($U16,Templates!$A$3:$A$10,0)),"")) | X16: =IF($U16="","",IFERROR(INDEX(Templates!$J$3:$J$10,MATCH($U16,Templates!$A$3:$A$10,0)),"")) | Y16: =IF(OR($U16="",$I16="",$J16="",$X16=""),"",$I16+$X16*($J16-$I16)) | Z16: 46212 | AD16: =IF($A16="","",IF($AA16="",$H16,$AA16)) | AE16: =IF($A16="","",IF($AB16="",$I16,$AB16)) | AF16: =IF($A16="","",IF($AC16="",$J16,$AC16)) | AG16: =IF(OR($U16="",$AE16="",$AF16="",$X16=""),"",$AE16+$X16*($AF16-$AE16)) | BD16: =IF($A16="","",SUM($AY16:$BC16)) | BE16: =IF($A16="","",IF(AND($I16<>"",$J16<>""),MAX(1,($J16-$I16)/7),Templates!$B$35)) | BF16: =IF($A16="","",IF(AND($I16<>"",$J16<>""),MAX(1,($J16-$I16)/7),Templates!$B$36)) | BG16: =IF($A16="","",IF(AND($I16<>"",$J16<>""),MAX(1,($J16-$I16)/7),Templates!$B$37)) | BH16: =IF($A16="","",IF(AND($I16<>"",$J16<>""),MAX(1,($J16-$I16)/7),Templates!$B$38)) | BI16: =IF($A16="","",IF(AND($I16<>"",$J16<>""),MAX(1,($J16-$I16)/7),Templates!$B$39)) | BJ16: =IF(OR($A16="",$BD16=0),0,($AY16*Templates!$B$27/$BE16+$AZ16*Templates!$B$28/$BF16+$BA16*Templates!$B$29/$BG16+$BB16*Templates!$B$30/$BH16+$BC16*Templates!$B$31/$BI16)/Templates!$B$17) | BK16: =IF(OR($A16="",$BD16=0),0,($AY16*Templates!$C$27/$BE16+$AZ16*Templates!$C$28/$BF16+$BA16*Templates!$C$29/$BG16+$BB16*Templates!$C$30/$BH16+$BC16*Templates!$C$31/$BI16)/Templates!$B$18) | BL16: =IF(OR($A16="",$BD16=0),0,($AY16*Templates!$D$27/$BE16+$AZ16*Templates!$D$28/$BF16+$BA16*Templates!$D$29/$BG16+$BB16*Templates!$D$30/$BH16+$BC16*Templates!$D$31/$BI16)/Templates!$B$19) | BM16: =IF(OR($A16="",$BD16=0),0,($AY16*Templates!$E$27/$BE16+$AZ16*Templates!$E$28/$BF16+$BA16*Templates!$E$29/$BG16+$BB16*Templates!$E$30/$BH16+$BC16*Templates!$E$31/$BI16)/Templates!$B$20) | BN16: =IF(OR($A16="",$BD16=0),0,($AY16*Templates!$F$27/$BE16+$AZ16*Templates!$F$28/$BF16+$BA16*Templates!$F$29/$BG16+$BB16*Templates!$F$30/$BH16+$BC16*Templates!$F$31/$BI16)/Templates!$B$21) | BO16: =IF(OR($A16="",$BD16=0),0,($AY16*Templates!$G$27/$BE16+$AZ16*Templates!$G$28/$BF16+$BA16*Templates!$G$29/$BG16+$BB16*Templates!$G$30/$BH16+$BC16*Templates!$G$31/$BI16)/Templates!$B$22) | BP16: =IF(OR($A16="",$BD16=0),0,($AY16*Templates!$H$27/$BE16+$AZ16*Templates!$H$28/$BF16+$BA16*Templates!$H$29/$BG16+$BB16*Templates!$H$30/$BH16+$BC16*Templates!$H$31/$BI16)/Templates!$B$23)
A17: Bledsoe_1 | B17: Manulife : Manulife Infrastructure Fund III AIV Holdings B LP | C17: Manulife | D17: Manulife Infrastructure Fund III AIV Holdings B LP | E17: No | F17: Active | H17: 1 | Q17: =IF($A17="","",COUNTIFS(Assignments!$C$2:$C$769,$A17,Assignments!$G$2:$G$769,"Active")) | R17: =IF($A17="","",SUMIFS(Assignments!$I$2:$I$769,Assignments!$C$2:$C$769,$A17,Assignments!$G$2:$G$769,"Active")) | S17: WIP | V17: =IF($U17="","",IFERROR(INDEX(Templates!$K$3:$K$10,MATCH($U17,Templates!$A$3:$A$10,0)),"")) | W17: =IF($U17="","",IFERROR(INDEX(Templates!$L$3:$L$10,MATCH($U17,Templates!$A$3:$A$10,0)),"")) | X17: =IF($U17="","",IFERROR(INDEX(Templates!$J$3:$J$10,MATCH($U17,Templates!$A$3:$A$10,0)),"")) | Y17: =IF(OR($U17="",$I17="",$J17="",$X17=""),"",$I17+$X17*($J17-$I17)) | Z17: 46212 | AD17: =IF($A17="","",IF($AA17="",$H17,$AA17)) | AE17: =IF($A17="","",IF($AB17="",$I17,$AB17)) | AF17: =IF($A17="","",IF($AC17="",$J17,$AC17)) | AG17: =IF(OR($U17="",$AE17="",$AF17="",$X17=""),"",$AE17+$X17*($AF17-$AE17)) | BD17: =IF($A17="","",SUM($AY17:$BC17)) | BE17: =IF($A17="","",IF(AND($I17<>"",$J17<>""),MAX(1,($J17-$I17)/7),Templates!$B$35)) | BF17: =IF($A17="","",IF(AND($I17<>"",$J17<>""),MAX(1,($J17-$I17)/7),Templates!$B$36)) | BG17: =IF($A17="","",IF(AND($I17<>"",$J17<>""),MAX(1,($J17-$I17)/7),Templates!$B$37)) | BH17: =IF($A17="","",IF(AND($I17<>"",$J17<>""),MAX(1,($J17-$I17)/7),Templates!$B$38)) | BI17: =IF($A17="","",IF(AND($I17<>"",$J17<>""),MAX(1,($J17-$I17)/7),Templates!$B$39)) | BJ17: =IF(OR($A17="",$BD17=0),0,($AY17*Templates!$B$27/$BE17+$AZ17*Templates!$B$28/$BF17+$BA17*Templates!$B$29/$BG17+$BB17*Templates!$B$30/$BH17+$BC17*Templates!$B$31/$BI17)/Templates!$B$17) | BK17: =IF(OR($A17="",$BD17=0),0,($AY17*Templates!$C$27/$BE17+$AZ17*Templates!$C$28/$BF17+$BA17*Templates!$C$29/$BG17+$BB17*Templates!$C$30/$BH17+$BC17*Templates!$C$31/$BI17)/Templates!$B$18) | BL17: =IF(OR($A17="",$BD17=0),0,($AY17*Templates!$D$27/$BE17+$AZ17*Templates!$D$28/$BF17+$BA17*Templates!$D$29/$BG17+$BB17*Templates!$D$30/$BH17+$BC17*Templates!$D$31/$BI17)/Templates!$B$19) | BM17: =IF(OR($A17="",$BD17=0),0,($AY17*Templates!$E$27/$BE17+$AZ17*Templates!$E$28/$BF17+$BA17*Templates!$E$29/$BG17+$BB17*Templates!$E$30/$BH17+$BC17*Templates!$E$31/$BI17)/Templates!$B$20) | BN17: =IF(OR($A17="",$BD17=0),0,($AY17*Templates!$F$27/$BE17+$AZ17*Templates!$F$28/$BF17+$BA17*Templates!$F$29/$BG17+$BB17*Templates!$F$30/$BH17+$BC17*Templates!$F$31/$BI17)/Templates!$B$21) | BO17: =IF(OR($A17="",$BD17=0),0,($AY17*Templates!$G$27/$BE17+$AZ17*Templates!$G$28/$BF17+$BA17*Templates!$G$29/$BG17+$BB17*Templates!$G$30/$BH17+$BC17*Templates!$G$31/$BI17)/Templates!$B$22) | BP17: =IF(OR($A17="",$BD17=0),0,($AY17*Templates!$H$27/$BE17+$AZ17*Templates!$H$28/$BF17+$BA17*Templates!$H$29/$BG17+$BB17*Templates!$H$30/$BH17+$BC17*Templates!$H$31/$BI17)/Templates!$B$23)
A18: Blue_6 | B18: Repsol Renewables NA | C18: Repsol Renewables NA | E18: No | F18: Active | H18: 1 | Q18: =IF($A18="","",COUNTIFS(Assignments!$C$2:$C$769,$A18,Assignments!$G$2:$G$769,"Active")) | R18: =IF($A18="","",SUMIFS(Assignments!$I$2:$I$769,Assignments!$C$2:$C$769,$A18,Assignments!$G$2:$G$769,"Active")) | S18: WIP | V18: =IF($U18="","",IFERROR(INDEX(Templates!$K$3:$K$10,MATCH($U18,Templates!$A$3:$A$10,0)),"")) | W18: =IF($U18="","",IFERROR(INDEX(Templates!$L$3:$L$10,MATCH($U18,Templates!$A$3:$A$10,0)),"")) | X18: =IF($U18="","",IFERROR(INDEX(Templates!$J$3:$J$10,MATCH($U18,Templates!$A$3:$A$10,0)),"")) | Y18: =IF(OR($U18="",$I18="",$J18="",$X18=""),"",$I18+$X18*($J18-$I18)) | Z18: 46212 | AD18: =IF($A18="","",IF($AA18="",$H18,$AA18)) | AE18: =IF($A18="","",IF($AB18="",$I18,$AB18)) | AF18: =IF($A18="","",IF($AC18="",$J18,$AC18)) | AG18: =IF(OR($U18="",$AE18="",$AF18="",$X18=""),"",$AE18+$X18*($AF18-$AE18)) | BD18: =IF($A18="","",SUM($AY18:$BC18)) | BE18: =IF($A18="","",IF(AND($I18<>"",$J18<>""),MAX(1,($J18-$I18)/7),Templates!$B$35)) | BF18: =IF($A18="","",IF(AND($I18<>"",$J18<>""),MAX(1,($J18-$I18)/7),Templates!$B$36)) | BG18: =IF($A18="","",IF(AND($I18<>"",$J18<>""),MAX(1,($J18-$I18)/7),Templates!$B$37)) | BH18: =IF($A18="","",IF(AND($I18<>"",$J18<>""),MAX(1,($J18-$I18)/7),Templates!$B$38)) | BI18: =IF($A18="","",IF(AND($I18<>"",$J18<>""),MAX(1,($J18-$I18)/7),Templates!$B$39)) | BJ18: =IF(OR($A18="",$BD18=0),0,($AY18*Templates!$B$27/$BE18+$AZ18*Templates!$B$28/$BF18+$BA18*Templates!$B$29/$BG18+$BB18*Templates!$B$30/$BH18+$BC18*Templates!$B$31/$BI18)/Templates!$B$17) | BK18: =IF(OR($A18="",$BD18=0),0,($AY18*Templates!$C$27/$BE18+$AZ18*Templates!$C$28/$BF18+$BA18*Templates!$C$29/$BG18+$BB18*Templates!$C$30/$BH18+$BC18*Templates!$C$31/$BI18)/Templates!$B$18) | BL18: =IF(OR($A18="",$BD18=0),0,($AY18*Templates!$D$27/$BE18+$AZ18*Templates!$D$28/$BF18+$BA18*Templates!$D$29/$BG18+$BB18*Templates!$D$30/$BH18+$BC18*Templates!$D$31/$BI18)/Templates!$B$19) | BM18: =IF(OR($A18="",$BD18=0),0,($AY18*Templates!$E$27/$BE18+$AZ18*Templates!$E$28/$BF18+$BA18*Templates!$E$29/$BG18+$BB18*Templates!$E$30/$BH18+$BC18*Templates!$E$31/$BI18)/Templates!$B$20) | BN18: =IF(OR($A18="",$BD18=0),0,($AY18*Templates!$F$27/$BE18+$AZ18*Templates!$F$28/$BF18+$BA18*Templates!$F$29/$BG18+$BB18*Templates!$F$30/$BH18+$BC18*Templates!$F$31/$BI18)/Templates!$B$21) | BO18: =IF(OR($A18="",$BD18=0),0,($AY18*Templates!$G$27/$BE18+$AZ18*Templates!$G$28/$BF18+$BA18*Templates!$G$29/$BG18+$BB18*Templates!$G$30/$BH18+$BC18*Templates!$G$31/$BI18)/Templates!$B$22) | BP18: =IF(OR($A18="",$BD18=0),0,($AY18*Templates!$H$27/$BE18+$AZ18*Templates!$H$28/$BF18+$BA18*Templates!$H$29/$BG18+$BB18*Templates!$H$30/$BH18+$BC18*Templates!$H$31/$BI18)/Templates!$B$23)
A19: Blue_8 | B19: Ares Management Corporation | C19: Ares Management Corporation | E19: No | F19: Active | H19: 1 | Q19: =IF($A19="","",COUNTIFS(Assignments!$C$2:$C$769,$A19,Assignments!$G$2:$G$769,"Active")) | R19: =IF($A19="","",SUMIFS(Assignments!$I$2:$I$769,Assignments!$C$2:$C$769,$A19,Assignments!$G$2:$G$769,"Active")) | S19: WIP | V19: =IF($U19="","",IFERROR(INDEX(Templates!$K$3:$K$10,MATCH($U19,Templates!$A$3:$A$10,0)),"")) | W19: =IF($U19="","",IFERROR(INDEX(Templates!$L$3:$L$10,MATCH($U19,Templates!$A$3:$A$10,0)),"")) | X19: =IF($U19="","",IFERROR(INDEX(Templates!$J$3:$J$10,MATCH($U19,Templates!$A$3:$A$10,0)),"")) | Y19: =IF(OR($U19="",$I19="",$J19="",$X19=""),"",$I19+$X19*($J19-$I19)) | Z19: 46212 | AD19: =IF($A19="","",IF($AA19="",$H19,$AA19)) | AE19: =IF($A19="","",IF($AB19="",$I19,$AB19)) | AF19: =IF($A19="","",IF($AC19="",$J19,$AC19)) | AG19: =IF(OR($U19="",$AE19="",$AF19="",$X19=""),"",$AE19+$X19*($AF19-$AE19)) | BD19: =IF($A19="","",SUM($AY19:$BC19)) | BE19: =IF($A19="","",IF(AND($I19<>"",$J19<>""),MAX(1,($J19-$I19)/7),Templates!$B$35)) | BF19: =IF($A19="","",IF(AND($I19<>"",$J19<>""),MAX(1,($J19-$I19)/7),Templates!$B$36)) | BG19: =IF($A19="","",IF(AND($I19<>"",$J19<>""),MAX(1,($J19-$I19)/7),Templates!$B$37)) | BH19: =IF($A19="","",IF(AND($I19<>"",$J19<>""),MAX(1,($J19-$I19)/7),Templates!$B$38)) | BI19: =IF($A19="","",IF(AND($I19<>"",$J19<>""),MAX(1,($J19-$I19)/7),Templates!$B$39)) | BJ19: =IF(OR($A19="",$BD19=0),0,($AY19*Templates!$B$27/$BE19+$AZ19*Templates!$B$28/$BF19+$BA19*Templates!$B$29/$BG19+$BB19*Templates!$B$30/$BH19+$BC19*Templates!$B$31/$BI19)/Templates!$B$17) | BK19: =IF(OR($A19="",$BD19=0),0,($AY19*Templates!$C$27/$BE19+$AZ19*Templates!$C$28/$BF19+$BA19*Templates!$C$29/$BG19+$BB19*Templates!$C$30/$BH19+$BC19*Templates!$C$31/$BI19)/Templates!$B$18) | BL19: =IF(OR($A19="",$BD19=0),0,($AY19*Templates!$D$27/$BE19+$AZ19*Templates!$D$28/$BF19+$BA19*Templates!$D$29/$BG19+$BB19*Templates!$D$30/$BH19+$BC19*Templates!$D$31/$BI19)/Templates!$B$19) | BM19: =IF(OR($A19="",$BD19=0),0,($AY19*Templates!$E$27/$BE19+$AZ19*Templates!$E$28/$BF19+$BA19*Templates!$E$29/$BG19+$BB19*Templates!$E$30/$BH19+$BC19*Templates!$E$31/$BI19)/Templates!$B$20) | BN19: =IF(OR($A19="",$BD19=0),0,($AY19*Templates!$F$27/$BE19+$AZ19*Templates!$F$28/$BF19+$BA19*Templates!$F$29/$BG19+$BB19*Templates!$F$30/$BH19+$BC19*Templates!$F$31/$BI19)/Templates!$B$21) | BO19: =IF(OR($A19="",$BD19=0),0,($AY19*Templates!$G$27/$BE19+$AZ19*Templates!$G$28/$BF19+$BA19*Templates!$G$29/$BG19+$BB19*Templates!$G$30/$BH19+$BC19*Templates!$G$31/$BI19)/Templates!$B$22) | BP19: =IF(OR($A19="",$BD19=0),0,($AY19*Templates!$H$27/$BE19+$AZ19*Templates!$H$28/$BF19+$BA19*Templates!$H$29/$BG19+$BB19*Templates!$H$30/$BH19+$BC19*Templates!$H$31/$BI19)/Templates!$B$23)
A20: Bocce_2 | B20: Certa | C20: Certa | E20: No | F20: Active | H20: 1 | Q20: =IF($A20="","",COUNTIFS(Assignments!$C$2:$C$769,$A20,Assignments!$G$2:$G$769,"Active")) | R20: =IF($A20="","",SUMIFS(Assignments!$I$2:$I$769,Assignments!$C$2:$C$769,$A20,Assignments!$G$2:$G$769,"Active")) | S20: WIP | V20: =IF($U20="","",IFERROR(INDEX(Templates!$K$3:$K$10,MATCH($U20,Templates!$A$3:$A$10,0)),"")) | W20: =IF($U20="","",IFERROR(INDEX(Templates!$L$3:$L$10,MATCH($U20,Templates!$A$3:$A$10,0)),"")) | X20: =IF($U20="","",IFERROR(INDEX(Templates!$J$3:$J$10,MATCH($U20,Templates!$A$3:$A$10,0)),"")) | Y20: =IF(OR($U20="",$I20="",$J20="",$X20=""),"",$I20+$X20*($J20-$I20)) | Z20: 46212 | AD20: =IF($A20="","",IF($AA20="",$H20,$AA20)) | AE20: =IF($A20="","",IF($AB20="",$I20,$AB20)) | AF20: =IF($A20="","",IF($AC20="",$J20,$AC20)) | AG20: =IF(OR($U20="",$AE20="",$AF20="",$X20=""),"",$AE20+$X20*($AF20-$AE20)) | BD20: =IF($A20="","",SUM($AY20:$BC20)) | BE20: =IF($A20="","",IF(AND($I20<>"",$J20<>""),MAX(1,($J20-$I20)/7),Templates!$B$35)) | BF20: =IF($A20="","",IF(AND($I20<>"",$J20<>""),MAX(1,($J20-$I20)/7),Templates!$B$36)) | BG20: =IF($A20="","",IF(AND($I20<>"",$J20<>""),MAX(1,($J20-$I20)/7),Templates!$B$37)) | BH20: =IF($A20="","",IF(AND($I20<>"",$J20<>""),MAX(1,($J20-$I20)/7),Templates!$B$38)) | BI20: =IF($A20="","",IF(AND($I20<>"",$J20<>""),MAX(1,($J20-$I20)/7),Templates!$B$39)) | BJ20: =IF(OR($A20="",$BD20=0),0,($AY20*Templates!$B$27/$BE20+$AZ20*Templates!$B$28/$BF20+$BA20*Templates!$B$29/$BG20+$BB20*Templates!$B$30/$BH20+$BC20*Templates!$B$31/$BI20)/Templates!$B$17) | BK20: =IF(OR($A20="",$BD20=0),0,($AY20*Templates!$C$27/$BE20+$AZ20*Templates!$C$28/$BF20+$BA20*Templates!$C$29/$BG20+$BB20*Templates!$C$30/$BH20+$BC20*Templates!$C$31/$BI20)/Templates!$B$18) | BL20: =IF(OR($A20="",$BD20=0),0,($AY20*Templates!$D$27/$BE20+$AZ20*Templates!$D$28/$BF20+$BA20*Templates!$D$29/$BG20+$BB20*Templates!$D$30/$BH20+$BC20*Templates!$D$31/$BI20)/Templates!$B$19) | BM20: =IF(OR($A20="",$BD20=0),0,($AY20*Templates!$E$27/$BE20+$AZ20*Templates!$E$28/$BF20+$BA20*Templates!$E$29/$BG20+$BB20*Templates!$E$30/$BH20+$BC20*Templates!$E$31/$BI20)/Templates!$B$20) | BN20: =IF(OR($A20="",$BD20=0),0,($AY20*Templates!$F$27/$BE20+$AZ20*Templates!$F$28/$BF20+$BA20*Templates!$F$29/$BG20+$BB20*Templates!$F$30/$BH20+$BC20*Templates!$F$31/$BI20)/Templates!$B$21) | BO20: =IF(OR($A20="",$BD20=0),0,($AY20*Templates!$G$27/$BE20+$AZ20*Templates!$G$28/$BF20+$BA20*Templates!$G$29/$BG20+$BB20*Templates!$G$30/$BH20+$BC20*Templates!$G$31/$BI20)/Templates!$B$22) | BP20: =IF(OR($A20="",$BD20=0),0,($AY20*Templates!$H$27/$BE20+$AZ20*Templates!$H$28/$BF20+$BA20*Templates!$H$29/$BG20+$BB20*Templates!$H$30/$BH20+$BC20*Templates!$H$31/$BI20)/Templates!$B$23)
A21: Bolt_2 | B21: Brookfield | C21: Brookfield | E21: No | F21: Active | H21: 1 | Q21: =IF($A21="","",COUNTIFS(Assignments!$C$2:$C$769,$A21,Assignments!$G$2:$G$769,"Active")) | R21: =IF($A21="","",SUMIFS(Assignments!$I$2:$I$769,Assignments!$C$2:$C$769,$A21,Assignments!$G$2:$G$769,"Active")) | S21: Summary tab only (WIP) | V21: =IF($U21="","",IFERROR(INDEX(Templates!$K$3:$K$10,MATCH($U21,Templates!$A$3:$A$10,0)),"")) | W21: =IF($U21="","",IFERROR(INDEX(Templates!$L$3:$L$10,MATCH($U21,Templates!$A$3:$A$10,0)),"")) | X21: =IF($U21="","",IFERROR(INDEX(Templates!$J$3:$J$10,MATCH($U21,Templates!$A$3:$A$10,0)),"")) | Y21: =IF(OR($U21="",$I21="",$J21="",$X21=""),"",$I21+$X21*($J21-$I21)) | Z21: 46212 | AD21: =IF($A21="","",IF($AA21="",$H21,$AA21)) | AE21: =IF($A21="","",IF($AB21="",$I21,$AB21)) | AF21: =IF($A21="","",IF($AC21="",$J21,$AC21)) | AG21: =IF(OR($U21="",$AE21="",$AF21="",$X21=""),"",$AE21+$X21*($AF21-$AE21)) | BD21: =IF($A21="","",SUM($AY21:$BC21)) | BE21: =IF($A21="","",IF(AND($I21<>"",$J21<>""),MAX(1,($J21-$I21)/7),Templates!$B$35)) | BF21: =IF($A21="","",IF(AND($I21<>"",$J21<>""),MAX(1,($J21-$I21)/7),Templates!$B$36)) | BG21: =IF($A21="","",IF(AND($I21<>"",$J21<>""),MAX(1,($J21-$I21)/7),Templates!$B$37)) | BH21: =IF($A21="","",IF(AND($I21<>"",$J21<>""),MAX(1,($J21-$I21)/7),Templates!$B$38)) | BI21: =IF($A21="","",IF(AND($I21<>"",$J21<>""),MAX(1,($J21-$I21)/7),Templates!$B$39)) | BJ21: =IF(OR($A21="",$BD21=0),0,($AY21*Templates!$B$27/$BE21+$AZ21*Templates!$B$28/$BF21+$BA21*Templates!$B$29/$BG21+$BB21*Templates!$B$30/$BH21+$BC21*Templates!$B$31/$BI21)/Templates!$B$17) | BK21: =IF(OR($A21="",$BD21=0),0,($AY21*Templates!$C$27/$BE21+$AZ21*Templates!$C$28/$BF21+$BA21*Templates!$C$29/$BG21+$BB21*Templates!$C$30/$BH21+$BC21*Templates!$C$31/$BI21)/Templates!$B$18) | BL21: =IF(OR($A21="",$BD21=0),0,($AY21*Templates!$D$27/$BE21+$AZ21*Templates!$D$28/$BF21+$BA21*Templates!$D$29/$BG21+$BB21*Templates!$D$30/$BH21+$BC21*Templates!$D$31/$BI21)/Templates!$B$19) | BM21: =IF(OR($A21="",$BD21=0),0,($AY21*Templates!$E$27/$BE21+$AZ21*Templates!$E$28/$BF21+$BA21*Templates!$E$29/$BG21+$BB21*Templates!$E$30/$BH21+$BC21*Templates!$E$31/$BI21)/Templates!$B$20) | BN21: =IF(OR($A21="",$BD21=0),0,($AY21*Templates!$F$27/$BE21+$AZ21*Templates!$F$28/$BF21+$BA21*Templates!$F$29/$BG21+$BB21*Templates!$F$30/$BH21+$BC21*Templates!$F$31/$BI21)/Templates!$B$21) | BO21: =IF(OR($A21="",$BD21=0),0,($AY21*Templates!$G$27/$BE21+$AZ21*Templates!$G$28/$BF21+$BA21*Templates!$G$29/$BG21+$BB21*Templates!$G$30/$BH21+$BC21*Templates!$G$31/$BI21)/Templates!$B$22) | BP21: =IF(OR($A21="",$BD21=0),0,($AY21*Templates!$H$27/$BE21+$AZ21*Templates!$H$28/$BF21+$BA21*Templates!$H$29/$BG21+$BB21*Templates!$H$30/$BH21+$BC21*Templates!$H$31/$BI21)/Templates!$B$23)
A22: BPF_1 | B22: BPF Acquisition Co Series 11, LLC | C22: BPF Acquisition Co Series 11, LLC | E22: No | F22: Active | H22: 1 | Q22: =IF($A22="","",COUNTIFS(Assignments!$C$2:$C$769,$A22,Assignments!$G$2:$G$769,"Active")) | R22: =IF($A22="","",SUMIFS(Assignments!$I$2:$I$769,Assignments!$C$2:$C$769,$A22,Assignments!$G$2:$G$769,"Active")) | S22: WIP | V22: =IF($U22="","",IFERROR(INDEX(Templates!$K$3:$K$10,MATCH($U22,Templates!$A$3:$A$10,0)),"")) | W22: =IF($U22="","",IFERROR(INDEX(Templates!$L$3:$L$10,MATCH($U22,Templates!$A$3:$A$10,0)),"")) | X22: =IF($U22="","",IFERROR(INDEX(Templates!$J$3:$J$10,MATCH($U22,Templates!$A$3:$A$10,0)),"")) | Y22: =IF(OR($U22="",$I22="",$J22="",$X22=""),"",$I22+$X22*($J22-$I22)) | Z22: 46212 | AD22: =IF($A22="","",IF($AA22="",$H22,$AA22)) | AE22: =IF($A22="","",IF($AB22="",$I22,$AB22)) | AF22: =IF($A22="","",IF($AC22="",$J22,$AC22)) | AG22: =IF(OR($U22="",$AE22="",$AF22="",$X22=""),"",$AE22+$X22*($AF22-$AE22)) | BD22: =IF($A22="","",SUM($AY22:$BC22)) | BE22: =IF($A22="","",IF(AND($I22<>"",$J22<>""),MAX(1,($J22-$I22)/7),Templates!$B$35)) | BF22: =IF($A22="","",IF(AND($I22<>"",$J22<>""),MAX(1,($J22-$I22)/7),Templates!$B$36)) | BG22: =IF($A22="","",IF(AND($I22<>"",$J22<>""),MAX(1,($J22-$I22)/7),Templates!$B$37)) | BH22: =IF($A22="","",IF(AND($I22<>"",$J22<>""),MAX(1,($J22-$I22)/7),Templates!$B$38)) | BI22: =IF($A22="","",IF(AND($I22<>"",$J22<>""),MAX(1,($J22-$I22)/7),Templates!$B$39)) | BJ22: =IF(OR($A22="",$BD22=0),0,($AY22*Templates!$B$27/$BE22+$AZ22*Templates!$B$28/$BF22+$BA22*Templates!$B$29/$BG22+$BB22*Templates!$B$30/$BH22+$BC22*Templates!$B$31/$BI22)/Templates!$B$17) | BK22: =IF(OR($A22="",$BD22=0),0,($AY22*Templates!$C$27/$BE22+$AZ22*Templates!$C$28/$BF22+$BA22*Templates!$C$29/$BG22+$BB22*Templates!$C$30/$BH22+$BC22*Templates!$C$31/$BI22)/Templates!$B$18) | BL22: =IF(OR($A22="",$BD22=0),0,($AY22*Templates!$D$27/$BE22+$AZ22*Templates!$D$28/$BF22+$BA22*Templates!$D$29/$BG22+$BB22*Templates!$D$30/$BH22+$BC22*Templates!$D$31/$BI22)/Templates!$B$19) | BM22: =IF(OR($A22="",$BD22=0),0,($AY22*Templates!$E$27/$BE22+$AZ22*Templates!$E$28/$BF22+$BA22*Templates!$E$29/$BG22+$BB22*Templates!$E$30/$BH22+$BC22*Templates!$E$31/$BI22)/Templates!$B$20) | BN22: =IF(OR($A22="",$BD22=0),0,($AY22*Templates!$F$27/$BE22+$AZ22*Templates!$F$28/$BF22+$BA22*Templates!$F$29/$BG22+$BB22*Templates!$F$30/$BH22+$BC22*Templates!$F$31/$BI22)/Templates!$B$21) | BO22: =IF(OR($A22="",$BD22=0),0,($AY22*Templates!$G$27/$BE22+$AZ22*Templates!$G$28/$BF22+$BA22*Templates!$G$29/$BG22+$BB22*Templates!$G$30/$BH22+$BC22*Templates!$G$31/$BI22)/Templates!$B$22) | BP22: =IF(OR($A22="",$BD22=0),0,($AY22*Templates!$H$27/$BE22+$AZ22*Templates!$H$28/$BF22+$BA22*Templates!$H$29/$BG22+$BB22*Templates!$H$30/$BH22+$BC22*Templates!$H$31/$BI22)/Templates!$B$23)
A23: BPF_2 | B23: BPF Acquisition Co Series 11, LLC | C23: BPF Acquisition Co Series 11, LLC | E23: No | F23: Active | H23: 1 | Q23: =IF($A23="","",COUNTIFS(Assignments!$C$2:$C$769,$A23,Assignments!$G$2:$G$769,"Active")) | R23: =IF($A23="","",SUMIFS(Assignments!$I$2:$I$769,Assignments!$C$2:$C$769,$A23,Assignments!$G$2:$G$769,"Active")) | S23: WIP | V23: =IF($U23="","",IFERROR(INDEX(Templates!$K$3:$K$10,MATCH($U23,Templates!$A$3:$A$10,0)),"")) | W23: =IF($U23="","",IFERROR(INDEX(Templates!$L$3:$L$10,MATCH($U23,Templates!$A$3:$A$10,0)),"")) | X23: =IF($U23="","",IFERROR(INDEX(Templates!$J$3:$J$10,MATCH($U23,Templates!$A$3:$A$10,0)),"")) | Y23: =IF(OR($U23="",$I23="",$J23="",$X23=""),"",$I23+$X23*($J23-$I23)) | Z23: 46212 | AD23: =IF($A23="","",IF($AA23="",$H23,$AA23)) | AE23: =IF($A23="","",IF($AB23="",$I23,$AB23)) | AF23: =IF($A23="","",IF($AC23="",$J23,$AC23)) | AG23: =IF(OR($U23="",$AE23="",$AF23="",$X23=""),"",$AE23+$X23*($AF23-$AE23)) | BD23: =IF($A23="","",SUM($AY23:$BC23)) | BE23: =IF($A23="","",IF(AND($I23<>"",$J23<>""),MAX(1,($J23-$I23)/7),Templates!$B$35)) | BF23: =IF($A23="","",IF(AND($I23<>"",$J23<>""),MAX(1,($J23-$I23)/7),Templates!$B$36)) | BG23: =IF($A23="","",IF(AND($I23<>"",$J23<>""),MAX(1,($J23-$I23)/7),Templates!$B$37)) | BH23: =IF($A23="","",IF(AND($I23<>"",$J23<>""),MAX(1,($J23-$I23)/7),Templates!$B$38)) | BI23: =IF($A23="","",IF(AND($I23<>"",$J23<>""),MAX(1,($J23-$I23)/7),Templates!$B$39)) | BJ23: =IF(OR($A23="",$BD23=0),0,($AY23*Templates!$B$27/$BE23+$AZ23*Templates!$B$28/$BF23+$BA23*Templates!$B$29/$BG23+$BB23*Templates!$B$30/$BH23+$BC23*Templates!$B$31/$BI23)/Templates!$B$17) | BK23: =IF(OR($A23="",$BD23=0),0,($AY23*Templates!$C$27/$BE23+$AZ23*Templates!$C$28/$BF23+$BA23*Templates!$C$29/$BG23+$BB23*Templates!$C$30/$BH23+$BC23*Templates!$C$31/$BI23)/Templates!$B$18) | BL23: =IF(OR($A23="",$BD23=0),0,($AY23*Templates!$D$27/$BE23+$AZ23*Templates!$D$28/$BF23+$BA23*Templates!$D$29/$BG23+$BB23*Templates!$D$30/$BH23+$BC23*Templates!$D$31/$BI23)/Templates!$B$19) | BM23: =IF(OR($A23="",$BD23=0),0,($AY23*Templates!$E$27/$BE23+$AZ23*Templates!$E$28/$BF23+$BA23*Templates!$E$29/$BG23+$BB23*Templates!$E$30/$BH23+$BC23*Templates!$E$31/$BI23)/Templates!$B$20) | BN23: =IF(OR($A23="",$BD23=0),0,($AY23*Templates!$F$27/$BE23+$AZ23*Templates!$F$28/$BF23+$BA23*Templates!$F$29/$BG23+$BB23*Templates!$F$30/$BH23+$BC23*Templates!$F$31/$BI23)/Templates!$B$21) | BO23: =IF(OR($A23="",$BD23=0),0,($AY23*Templates!$G$27/$BE23+$AZ23*Templates!$G$28/$BF23+$BA23*Templates!$G$29/$BG23+$BB23*Templates!$G$30/$BH23+$BC23*Templates!$G$31/$BI23)/Templates!$B$22) | BP23: =IF(OR($A23="",$BD23=0),0,($AY23*Templates!$H$27/$BE23+$AZ23*Templates!$H$28/$BF23+$BA23*Templates!$H$29/$BG23+$BB23*Templates!$H$30/$BH23+$BC23*Templates!$H$31/$BI23)/Templates!$B$23)
